Workbook

Sheet EVERYTHING (Skaters)
K1: Quick Jumps: | M1: Goalies | N1: Plus/Minus & PP
M2: PIM/Hits/BS | N2: Help & Info
H3: AAV, Salary, or Cap Hit? (Type it): | M3: Potential | N3: EVERYTHING
H4: AAV | M4: ='Points&Potential'!$M$4 -> Updated: Aug 02 | P4: *Age is as of Jul 22
A6: Rank | B6: Player | C6: Age | D6: Pos | E6: 3YP | F6: Upside | G6: Team | H6: Games | I6: Goals | J6: Assists | K6: Points | L6: +/- | M6: PP Unit | N6: PIM | O6: Hits | P6: BLKS | Q6: SOG | R6: Sleeper | S6: =IF(H4="2011 - 2012 Cap #","Cap Hit", "Salary") -> Salary | T6: Band-Aid Boy | U6: Notes | V6: Rookie
A7: 1 | B7: Connor McDavid | C7: =VLOOKUP(B7, Paste!$AG$3:$AH$2083, 2, FALSE) -> 29.4 | D7: =VLOOKUP($B7, Paste!$A$3:$H$933, 6, FALSE) -> C | E7: =IFERROR(VLOOKUP($B7, Paste!$J$3:$L$933, 3, FALSE), "") -> 135 | F7: =IFERROR(VLOOKUP($B7, Paste!$J$3:$L$933, 2, FALSE), "") -> 160 | G7: =VLOOKUP($B7, Paste!$A$3:$H$933, 8, FALSE) -> EDM | H7: =VLOOKUP($B7, Paste!$A$3:$H$933, 2, FALSE) -> 77 | I7: =VLOOKUP($B7, Paste!$A$3:$H$933, 3, FALSE) -> 36.462054 | J7: =K7-I7 -> 94.720676 | K7: =VLOOKUP($B7, Paste!$A$3:$H$933, 4, FALSE) -> 131.18273 | L7: =IF(ISBLANK(VLOOKUP(B7, 'SOG&PlusMinus'!$B$7:$E$912, 3, FALSE)), "", VLOOKUP(B7,'SOG&PlusMinus'!$B$7:$E$912, 3, FALSE)) -> A | M7: =IF(ISBLANK(VLOOKUP(B7, 'SOG&PlusMinus'!$B$7:$E$912, 4, FALSE)), "", VLOOKUP(B7, 'SOG&PlusMinus'!$B$7:$E$912, 4, FALSE)) -> 1 | N7: =VLOOKUP($B7, Paste!$A$3:$H$933, 5, FALSE) -> 37.986667 | O7: =IF(ISERROR(VLOOKUP(B7, Paste!$AB$3:$AE$2349, 3, FALSE)), "", VLOOKUP(B7, Paste!$AB$3:$AE$2349, 3, FALSE)) -> 42 | P7: =IF(ISERROR(VLOOKUP(B7, Paste!$AB$3:$AC$2343, 2, FALSE)), "", VLOOKUP(B7, Paste!$AB$3:$AC$2343, 2, FALSE)) -> 27 | Q7: =IF(ISERROR(VLOOKUP(B7, Paste!$AB$3:$AE$2349, 4, FALSE)), "", VLOOKUP(B7, Paste!$AB$3:$AE$2349, 4, FALSE)) -> 277 | R7: =IF(ISERROR(VLOOKUP(B7, Paste!$N$3:$N$250, 1, FALSE)), "", VLOOKUP(B7, Paste!$N$3:$O$250, 2, FALSE)) | S7: =VLOOKUP($B7, Paste!$W$3:$Z$10064, IF($H$4="Cap Hit",3, IF($H$4="AAV", 4, 2)), FALSE) -> 12.5 | T7: =IF(ISERROR(VLOOKUP(B7, Paste!$Q$3:$Q$245, 1, FALSE)), "", VLOOKUP(B7, Paste!$Q$3:$R$245, 2, FALSE)) | U7: =IF(VLOOKUP(B7, 'Points&Potential'!$B$7:$O$943, 14, FALSE)=0, "", VLOOKUP(B7, 'Points&Potential'!$B$7:$O$943, 14, FALSE)) | V7: =IF(ISERROR(VLOOKUP(B7, Paste!$T$3:$T$1045, 1, FALSE)), "", VLOOKUP(B7, Paste!$T$3:$U$1144, 2, FALSE))
A8: 2 | B8: Nikita Kucherov | C8: =VLOOKUP(B8, Paste!$AG$3:$AH$2083, 2, FALSE) -> 33 | D8: =VLOOKUP($B8, Paste!$A$3:$H$933, 6, FALSE) -> RW | E8: =IFERROR(VLOOKUP($B8, Paste!$J$3:$L$933, 3, FALSE), "") -> 120 | F8: =IFERROR(VLOOKUP($B8, Paste!$J$3:$L$933, 2, FALSE), "") -> 140 | G8: =VLOOKUP($B8, Paste!$A$3:$H$933, 8, FALSE) -> TBL | H8: =VLOOKUP($B8, Paste!$A$3:$H$933, 2, FALSE) -> 80.666667 | I8: =VLOOKUP($B8, Paste!$A$3:$H$933, 3, FALSE) -> 41.575334 | J8: =K8-I8 -> 86.455976 | K8: =VLOOKUP($B8, Paste!$A$3:$H$933, 4, FALSE) -> 128.03131 | L8: =IF(ISBLANK(VLOOKUP(B8, 'SOG&PlusMinus'!$B$7:$E$912, 3, FALSE)), "", VLOOKUP(B8,'SOG&PlusMinus'!$B$7:$E$912, 3, FALSE)) -> A | M8: =IF(ISBLANK(VLOOKUP(B8, 'SOG&PlusMinus'!$B$7:$E$912, 4, FALSE)), "", VLOOKUP(B8, 'SOG&PlusMinus'!$B$7:$E$912, 4, FALSE)) -> 1 | N8: =VLOOKUP($B8, Paste!$A$3:$H$933, 5, FALSE) -> 39.991525 | O8: =IF(ISERROR(VLOOKUP(B8, Paste!$AB$3:$AE$2349, 3, FALSE)), "", VLOOKUP(B8, Paste!$AB$3:$AE$2349, 3, FALSE)) -> 35 | P8: =IF(ISERROR(VLOOKUP(B8, Paste!$AB$3:$AC$2343, 2, FALSE)), "", VLOOKUP(B8, Paste!$AB$3:$AC$2343, 2, FALSE)) -> 32 | Q8: =IF(ISERROR(VLOOKUP(B8, Paste!$AB$3:$AE$2349, 4, FALSE)), "", VLOOKUP(B8, Paste!$AB$3:$AE$2349, 4, FALSE)) -> 258 | R8: =IF(ISERROR(VLOOKUP(B8, Paste!$N$3:$N$250, 1, FALSE)), "", VLOOKUP(B8, Paste!$N$3:$O$250, 2, FALSE)) | S8: =VLOOKUP($B8, Paste!$W$3:$Z$10064, IF($H$4="Cap Hit",3, IF($H$4="AAV", 4, 2)), FALSE) -> 9.5 | T8: =IF(ISERROR(VLOOKUP(B8, Paste!$Q$3:$Q$245, 1, FALSE)), "", VLOOKUP(B8, Paste!$Q$3:$R$245, 2, FALSE)) | U8: =IF(VLOOKUP(B8, 'Points&Potential'!$B$7:$O$943, 14, FALSE)=0, "", VLOOKUP(B8, 'Points&Potential'!$B$7:$O$943, 14, FALSE)) | V8: =IF(ISERROR(VLOOKUP(B8, Paste!$T$3:$T$1045, 1, FALSE)), "", VLOOKUP(B8, Paste!$T$3:$U$1144, 2, FALSE))
A9: 3 | B9: Nathan MacKinnon | C9: =VLOOKUP(B9, Paste!$AG$3:$AH$2083, 2, FALSE) -> 30.8 | D9: =VLOOKUP($B9, Paste!$A$3:$H$933, 6, FALSE) -> C | E9: =IFERROR(VLOOKUP($B9, Paste!$J$3:$L$933, 3, FALSE), "") -> 123 | F9: =IFERROR(VLOOKUP($B9, Paste!$J$3:$L$933, 2, FALSE), "") -> 145 | G9: =VLOOKUP($B9, Paste!$A$3:$H$933, 8, FALSE) -> COL | H9: =VLOOKUP($B9, Paste!$A$3:$H$933, 2, FALSE) -> 82.333333 | I9: =VLOOKUP($B9, Paste!$A$3:$H$933, 3, FALSE) -> 45.150263 | J9: =K9-I9 -> 81.06191 | K9: =VLOOKUP($B9, Paste!$A$3:$H$933, 4, FALSE) -> 126.21217 | L9: =IF(ISBLANK(VLOOKUP(B9, 'SOG&PlusMinus'!$B$7:$E$912, 3, FALSE)), "", VLOOKUP(B9,'SOG&PlusMinus'!$B$7:$E$912, 3, FALSE)) -> A | M9: =IF(ISBLANK(VLOOKUP(B9, 'SOG&PlusMinus'!$B$7:$E$912, 4, FALSE)), "", VLOOKUP(B9, 'SOG&PlusMinus'!$B$7:$E$912, 4, FALSE)) -> 1 | N9: =VLOOKUP($B9, Paste!$A$3:$H$933, 5, FALSE) -> 41.679115 | O9: =IF(ISERROR(VLOOKUP(B9, Paste!$AB$3:$AE$2349, 3, FALSE)), "", VLOOKUP(B9, Paste!$AB$3:$AE$2349, 3, FALSE)) -> 54 | P9: =IF(ISERROR(VLOOKUP(B9, Paste!$AB$3:$AC$2343, 2, FALSE)), "", VLOOKUP(B9, Paste!$AB$3:$AC$2343, 2, FALSE)) -> 56 | Q9: =IF(ISERROR(VLOOKUP(B9, Paste!$AB$3:$AE$2349, 4, FALSE)), "", VLOOKUP(B9, Paste!$AB$3:$AE$2349, 4, FALSE)) -> 354 | R9: =IF(ISERROR(VLOOKUP(B9, Paste!$N$3:$N$250, 1, FALSE)), "", VLOOKUP(B9, Paste!$N$3:$O$250, 2, FALSE)) | S9: =VLOOKUP($B9, Paste!$W$3:$Z$10064, IF($H$4="Cap Hit",3, IF($H$4="AAV", 4, 2)), FALSE) -> 12.6 | T9: =IF(ISERROR(VLOOKUP(B9, Paste!$Q$3:$Q$245, 1, FALSE)), "", VLOOKUP(B9, Paste!$Q$3:$R$245, 2, FALSE)) | U9: =IF(VLOOKUP(B9, 'Points&Potential'!$B$7:$O$943, 14, FALSE)=0, "", VLOOKUP(B9, 'Points&Potential'!$B$7:$O$943, 14, FALSE)) | V9: =IF(ISERROR(VLOOKUP(B9, Paste!$T$3:$T$1045, 1, FALSE)), "", VLOOKUP(B9, Paste!$T$3:$U$1144, 2, FALSE))
A10: 4 | B10: Macklin Celebrini | C10: =VLOOKUP(B10, Paste!$AG$3:$AH$2083, 2, FALSE) -> 20 | D10: =VLOOKUP($B10, Paste!$A$3:$H$933, 6, FALSE) -> C | E10: =IFERROR(VLOOKUP($B10, Paste!$J$3:$L$933, 3, FALSE), "") -> 112 | F10: =IFERROR(VLOOKUP($B10, Paste!$J$3:$L$933, 2, FALSE), "") -> 125 | G10: =VLOOKUP($B10, Paste!$A$3:$H$933, 8, FALSE) -> SJS | H10: =VLOOKUP($B10, Paste!$A$3:$H$933, 2, FALSE) -> 78 | I10: =VLOOKUP($B10, Paste!$A$3:$H$933, 3, FALSE) -> 39 | J10: =K10-I10 -> 72.815418 | K10: =VLOOKUP($B10, Paste!$A$3:$H$933, 4, FALSE) -> 111.81542 | L10: =IF(ISBLANK(VLOOKUP(B10, 'SOG&PlusMinus'!$B$7:$E$912, 3, FALSE)), "", VLOOKUP(B10,'SOG&PlusMinus'!$B$7:$E$912, 3, FALSE)) -> B | M10: =IF(ISBLANK(VLOOKUP(B10, 'SOG&PlusMinus'!$B$7:$E$912, 4, FALSE)), "", VLOOKUP(B10, 'SOG&PlusMinus'!$B$7:$E$912, 4, FALSE)) -> 1 | N10: =VLOOKUP($B10, Paste!$A$3:$H$933, 5, FALSE) -> 35.1 | O10: =IF(ISERROR(VLOOKUP(B10, Paste!$AB$3:$AE$2349, 3, FALSE)), "", VLOOKUP(B10, Paste!$AB$3:$AE$2349, 3, FALSE)) -> 55 | P10: =IF(ISERROR(VLOOKUP(B10, Paste!$AB$3:$AC$2343, 2, FALSE)), "", VLOOKUP(B10, Paste!$AB$3:$AC$2343, 2, FALSE)) -> 55 | Q10: =IF(ISERROR(VLOOKUP(B10, Paste!$AB$3:$AE$2349, 4, FALSE)), "", VLOOKUP(B10, Paste!$AB$3:$AE$2349, 4, FALSE)) -> 281 | R10: =IF(ISERROR(VLOOKUP(B10, Paste!$N$3:$N$250, 1, FALSE)), "", VLOOKUP(B10, Paste!$N$3:$O$250, 2, FALSE)) | S10: =VLOOKUP($B10, Paste!$W$3:$Z$10064, IF($H$4="Cap Hit",3, IF($H$4="AAV", 4, 2)), FALSE) -> 4.475 | T10: =IF(ISERROR(VLOOKUP(B10, Paste!$Q$3:$Q$245, 1, FALSE)), "", VLOOKUP(B10, Paste!$Q$3:$R$245, 2, FALSE)) | U10: =IF(VLOOKUP(B10, 'Points&Potential'!$B$7:$O$943, 14, FALSE)=0, "", VLOOKUP(B10, 'Points&Potential'!$B$7:$O$943, 14, FALSE)) | V10: =IF(ISERROR(VLOOKUP(B10, Paste!$T$3:$T$1045, 1, FALSE)), "", VLOOKUP(B10, Paste!$T$3:$U$1144, 2, FALSE))
A11: 5 | B11: Jason Robertson | C11: =VLOOKUP(B11, Paste!$AG$3:$AH$2083, 2, FALSE) -> 26.9 | D11: =VLOOKUP($B11, Paste!$A$3:$H$933, 6, FALSE) -> LW | E11: =IFERROR(VLOOKUP($B11, Paste!$J$3:$L$933, 3, FALSE), "") -> 93 | F11: =IFERROR(VLOOKUP($B11, Paste!$J$3:$L$933, 2, FALSE), "") -> 110 | G11: =VLOOKUP($B11, Paste!$A$3:$H$933, 8, FALSE) -> DAL | H11: =VLOOKUP($B11, Paste!$A$3:$H$933, 2, FALSE) -> 84 | I11: =VLOOKUP($B11, Paste!$A$3:$H$933, 3, FALSE) -> 38.79345 | J11: =K11-I11 -> 70.478485 | K11: =VLOOKUP($B11, Paste!$A$3:$H$933, 4, FALSE) -> 109.27194 | L11: =IF(ISBLANK(VLOOKUP(B11, 'SOG&PlusMinus'!$B$7:$E$912, 3, FALSE)), "", VLOOKUP(B11,'SOG&PlusMinus'!$B$7:$E$912, 3, FALSE)) -> A | M11: =IF(ISBLANK(VLOOKUP(B11, 'SOG&PlusMinus'!$B$7:$E$912, 4, FALSE)), "", VLOOKUP(B11, 'SOG&PlusMinus'!$B$7:$E$912, 4, FALSE)) -> 1 | N11: =VLOOKUP($B11, Paste!$A$3:$H$933, 5, FALSE) -> 24.585366 | O11: =IF(ISERROR(VLOOKUP(B11, Paste!$AB$3:$AE$2349, 3, FALSE)), "", VLOOKUP(B11, Paste!$AB$3:$AE$2349, 3, FALSE)) -> 59 | P11: =IF(ISERROR(VLOOKUP(B11, Paste!$AB$3:$AC$2343, 2, FALSE)), "", VLOOKUP(B11, Paste!$AB$3:$AC$2343, 2, FALSE)) -> 34 | Q11: =IF(ISERROR(VLOOKUP(B11, Paste!$AB$3:$AE$2349, 4, FALSE)), "", VLOOKUP(B11, Paste!$AB$3:$AE$2349, 4, FALSE)) -> 286 | R11: =IF(ISERROR(VLOOKUP(B11, Paste!$N$3:$N$250, 1, FALSE)), "", VLOOKUP(B11, Paste!$N$3:$O$250, 2, FALSE)) | S11: =VLOOKUP($B11, Paste!$W$3:$Z$10064, IF($H$4="Cap Hit",3, IF($H$4="AAV", 4, 2)), FALSE) -> 12 | T11: =IF(ISERROR(VLOOKUP(B11, Paste!$Q$3:$Q$245, 1, FALSE)), "", VLOOKUP(B11, Paste!$Q$3:$R$245, 2, FALSE)) | U11: =IF(VLOOKUP(B11, 'Points&Potential'!$B$7:$O$943, 14, FALSE)=0, "", VLOOKUP(B11, 'Points&Potential'!$B$7:$O$943, 14, FALSE)) | V11: =IF(ISERROR(VLOOKUP(B11, Paste!$T$3:$T$1045, 1, FALSE)), "", VLOOKUP(B11, Paste!$T$3:$U$1144, 2, FALSE))
A12: 6 | B12: Martin Necas | C12: =VLOOKUP(B12, Paste!$AG$3:$AH$2083, 2, FALSE) -> 27.4 | D12: =VLOOKUP($B12, Paste!$A$3:$H$933, 6, FALSE) -> RW | E12: =IFERROR(VLOOKUP($B12, Paste!$J$3:$L$933, 3, FALSE), "") -> 105 | F12: =IFERROR(VLOOKUP($B12, Paste!$J$3:$L$933, 2, FALSE), "") -> 112 | G12: =VLOOKUP($B12, Paste!$A$3:$H$933, 8, FALSE) -> COL | H12: =VLOOKUP($B12, Paste!$A$3:$H$933, 2, FALSE) -> 80 | I12: =VLOOKUP($B12, Paste!$A$3:$H$933, 3, FALSE) -> 32 | J12: =K12-I12 -> 75.804813 | K12: =VLOOKUP($B12, Paste!$A$3:$H$933, 4, FALSE) -> 107.80481 | L12: =IF(ISBLANK(VLOOKUP(B12, 'SOG&PlusMinus'!$B$7:$E$912, 3, FALSE)), "", VLOOKUP(B12,'SOG&PlusMinus'!$B$7:$E$912, 3, FALSE)) -> A | M12: =IF(ISBLANK(VLOOKUP(B12, 'SOG&PlusMinus'!$B$7:$E$912, 4, FALSE)), "", VLOOKUP(B12, 'SOG&PlusMinus'!$B$7:$E$912, 4, FALSE)) -> 1 | N12: =VLOOKUP($B12, Paste!$A$3:$H$933, 5, FALSE) -> 30.08547 | O12: =IF(ISERROR(VLOOKUP(B12, Paste!$AB$3:$AE$2349, 3, FALSE)), "", VLOOKUP(B12, Paste!$AB$3:$AE$2349, 3, FALSE)) -> 76 | P12: =IF(ISERROR(VLOOKUP(B12, Paste!$AB$3:$AC$2343, 2, FALSE)), "", VLOOKUP(B12, Paste!$AB$3:$AC$2343, 2, FALSE)) -> 26 | Q12: =IF(ISERROR(VLOOKUP(B12, Paste!$AB$3:$AE$2349, 4, FALSE)), "", VLOOKUP(B12, Paste!$AB$3:$AE$2349, 4, FALSE)) -> 216 | R12: =IF(ISERROR(VLOOKUP(B12, Paste!$N$3:$N$250, 1, FALSE)), "", VLOOKUP(B12, Paste!$N$3:$O$250, 2, FALSE)) | S12: =VLOOKUP($B12, Paste!$W$3:$Z$10064, IF($H$4="Cap Hit",3, IF($H$4="AAV", 4, 2)), FALSE) -> 11.5 | T12: =IF(ISERROR(VLOOKUP(B12, Paste!$Q$3:$Q$245, 1, FALSE)), "", VLOOKUP(B12, Paste!$Q$3:$R$245, 2, FALSE)) | U12: =IF(VLOOKUP(B12, 'Points&Potential'!$B$7:$O$943, 14, FALSE)=0, "", VLOOKUP(B12, 'Points&Potential'!$B$7:$O$943, 14, FALSE)) | V12: =IF(ISERROR(VLOOKUP(B12, Paste!$T$3:$T$1045, 1, FALSE)), "", VLOOKUP(B12, Paste!$T$3:$U$1144, 2, FALSE))
A13: 7 | B13: Leon Draisaitl | C13: =VLOOKUP(B13, Paste!$AG$3:$AH$2083, 2, FALSE) -> 30.6 | D13: =VLOOKUP($B13, Paste!$A$3:$H$933, 6, FALSE) -> C | E13: =IFERROR(VLOOKUP($B13, Paste!$J$3:$L$933, 3, FALSE), "") -> 112 | F13: =IFERROR(VLOOKUP($B13, Paste!$J$3:$L$933, 2, FALSE), "") -> 145 | G13: =VLOOKUP($B13, Paste!$A$3:$H$933, 8, FALSE) -> EDM | H13: =VLOOKUP($B13, Paste!$A$3:$H$933, 2, FALSE) -> 74.333333 | I13: =VLOOKUP($B13, Paste!$A$3:$H$933, 3, FALSE) -> 44.196876 | J13: =K13-I13 -> 61.778262 | K13: =VLOOKUP($B13, Paste!$A$3:$H$933, 4, FALSE) -> 105.97514 | L13: =IF(ISBLANK(VLOOKUP(B13, 'SOG&PlusMinus'!$B$7:$E$912, 3, FALSE)), "", VLOOKUP(B13,'SOG&PlusMinus'!$B$7:$E$912, 3, FALSE)) -> A | M13: =IF(ISBLANK(VLOOKUP(B13, 'SOG&PlusMinus'!$B$7:$E$912, 4, FALSE)), "", VLOOKUP(B13, 'SOG&PlusMinus'!$B$7:$E$912, 4, FALSE)) -> 1 | N13: =VLOOKUP($B13, Paste!$A$3:$H$933, 5, FALSE) -> 46.58679 | O13: =IF(ISERROR(VLOOKUP(B13, Paste!$AB$3:$AE$2349, 3, FALSE)), "", VLOOKUP(B13, Paste!$AB$3:$AE$2349, 3, FALSE)) -> 37 | P13: =IF(ISERROR(VLOOKUP(B13, Paste!$AB$3:$AC$2343, 2, FALSE)), "", VLOOKUP(B13, Paste!$AB$3:$AC$2343, 2, FALSE)) -> 22 | Q13: =IF(ISERROR(VLOOKUP(B13, Paste!$AB$3:$AE$2349, 4, FALSE)), "", VLOOKUP(B13, Paste!$AB$3:$AE$2349, 4, FALSE)) -> 223 | R13: =IF(ISERROR(VLOOKUP(B13, Paste!$N$3:$N$250, 1, FALSE)), "", VLOOKUP(B13, Paste!$N$3:$O$250, 2, FALSE)) | S13: =VLOOKUP($B13, Paste!$W$3:$Z$10064, IF($H$4="Cap Hit",3, IF($H$4="AAV", 4, 2)), FALSE) -> 14 | T13: =IF(ISERROR(VLOOKUP(B13, Paste!$Q$3:$Q$245, 1, FALSE)), "", VLOOKUP(B13, Paste!$Q$3:$R$245, 2, FALSE)) -> Y | U13: =IF(VLOOKUP(B13, 'Points&Potential'!$B$7:$O$943, 14, FALSE)=0, "", VLOOKUP(B13, 'Points&Potential'!$B$7:$O$943, 14, FALSE)) | V13: =IF(ISERROR(VLOOKUP(B13, Paste!$T$3:$T$1045, 1, FALSE)), "", VLOOKUP(B13, Paste!$T$3:$U$1144, 2, FALSE))
A14: 8 | B14: David Pastrnak | C14: =VLOOKUP(B14, Paste!$AG$3:$AH$2083, 2, FALSE) -> 30.1 | D14: =VLOOKUP($B14, Paste!$A$3:$H$933, 6, FALSE) -> RW | E14: =IFERROR(VLOOKUP($B14, Paste!$J$3:$L$933, 3, FALSE), "") -> 100 | F14: =IFERROR(VLOOKUP($B14, Paste!$J$3:$L$933, 2, FALSE), "") -> 115 | G14: =VLOOKUP($B14, Paste!$A$3:$H$933, 8, FALSE) -> BOS | H14: =VLOOKUP($B14, Paste!$A$3:$H$933, 2, FALSE) -> 82.333333 | I14: =VLOOKUP($B14, Paste!$A$3:$H$933, 3, FALSE) -> 38.152501 | J14: =K14-I14 -> 67.214735 | K14: =VLOOKUP($B14, Paste!$A$3:$H$933, 4, FALSE) -> 105.36724 | L14: =IF(ISBLANK(VLOOKUP(B14, 'SOG&PlusMinus'!$B$7:$E$912, 3, FALSE)), "", VLOOKUP(B14,'SOG&PlusMinus'!$B$7:$E$912, 3, FALSE)) -> B | M14: =IF(ISBLANK(VLOOKUP(B14, 'SOG&PlusMinus'!$B$7:$E$912, 4, FALSE)), "", VLOOKUP(B14, 'SOG&PlusMinus'!$B$7:$E$912, 4, FALSE)) -> 1 | N14: =VLOOKUP($B14, Paste!$A$3:$H$933, 5, FALSE) -> 55.002766 | O14: =IF(ISERROR(VLOOKUP(B14, Paste!$AB$3:$AE$2349, 3, FALSE)), "", VLOOKUP(B14, Paste!$AB$3:$AE$2349, 3, FALSE)) -> 73 | P14: =IF(ISERROR(VLOOKUP(B14, Paste!$AB$3:$AC$2343, 2, FALSE)), "", VLOOKUP(B14, Paste!$AB$3:$AC$2343, 2, FALSE)) -> 26 | Q14: =IF(ISERROR(VLOOKUP(B14, Paste!$AB$3:$AE$2349, 4, FALSE)), "", VLOOKUP(B14, Paste!$AB$3:$AE$2349, 4, FALSE)) -> 296 | R14: =IF(ISERROR(VLOOKUP(B14, Paste!$N$3:$N$250, 1, FALSE)), "", VLOOKUP(B14, Paste!$N$3:$O$250, 2, FALSE)) | S14: =VLOOKUP($B14, Paste!$W$3:$Z$10064, IF($H$4="Cap Hit",3, IF($H$4="AAV", 4, 2)), FALSE) -> 11.25 | T14: =IF(ISERROR(VLOOKUP(B14, Paste!$Q$3:$Q$245, 1, FALSE)), "", VLOOKUP(B14, Paste!$Q$3:$R$245, 2, FALSE)) | U14: =IF(VLOOKUP(B14, 'Points&Potential'!$B$7:$O$943, 14, FALSE)=0, "", VLOOKUP(B14, 'Points&Potential'!$B$7:$O$943, 14, FALSE)) | V14: =IF(ISERROR(VLOOKUP(B14, Paste!$T$3:$T$1045, 1, FALSE)), "", VLOOKUP(B14, Paste!$T$3:$U$1144, 2, FALSE))
A15: 9 | B15: Mitch Marner | C15: =VLOOKUP(B15, Paste!$AG$3:$AH$2083, 2, FALSE) -> 29.1 | D15: =VLOOKUP($B15, Paste!$A$3:$H$933, 6, FALSE) -> RW | E15: =IFERROR(VLOOKUP($B15, Paste!$J$3:$L$933, 3, FALSE), "") -> 98 | F15: =IFERROR(VLOOKUP($B15, Paste!$J$3:$L$933, 2, FALSE), "") -> 118 | G15: =VLOOKUP($B15, Paste!$A$3:$H$933, 8, FALSE) -> VGK | H15: =VLOOKUP($B15, Paste!$A$3:$H$933, 2, FALSE) -> 83 | I15: =VLOOKUP($B15, Paste!$A$3:$H$933, 3, FALSE) -> 27.235265 | J15: =K15-I15 -> 71.736269 | K15: =VLOOKUP($B15, Paste!$A$3:$H$933, 4, FALSE) -> 98.971534 | L15: =IF(ISBLANK(VLOOKUP(B15, 'SOG&PlusMinus'!$B$7:$E$912, 3, FALSE)), "", VLOOKUP(B15,'SOG&PlusMinus'!$B$7:$E$912, 3, FALSE)) -> A | M15: =IF(ISBLANK(VLOOKUP(B15, 'SOG&PlusMinus'!$B$7:$E$912, 4, FALSE)), "", VLOOKUP(B15, 'SOG&PlusMinus'!$B$7:$E$912, 4, FALSE)) -> 1 | N15: =VLOOKUP($B15, Paste!$A$3:$H$933, 5, FALSE) -> 20.121212 | O15: =IF(ISERROR(VLOOKUP(B15, Paste!$AB$3:$AE$2349, 3, FALSE)), "", VLOOKUP(B15, Paste!$AB$3:$AE$2349, 3, FALSE)) -> 33 | P15: =IF(ISERROR(VLOOKUP(B15, Paste!$AB$3:$AC$2343, 2, FALSE)), "", VLOOKUP(B15, Paste!$AB$3:$AC$2343, 2, FALSE)) -> 50 | Q15: =IF(ISERROR(VLOOKUP(B15, Paste!$AB$3:$AE$2349, 4, FALSE)), "", VLOOKUP(B15, Paste!$AB$3:$AE$2349, 4, FALSE)) -> 174 | R15: =IF(ISERROR(VLOOKUP(B15, Paste!$N$3:$N$250, 1, FALSE)), "", VLOOKUP(B15, Paste!$N$3:$O$250, 2, FALSE)) | S15: =VLOOKUP($B15, Paste!$W$3:$Z$10064, IF($H$4="Cap Hit",3, IF($H$4="AAV", 4, 2)), FALSE) -> 12 | T15: =IF(ISERROR(VLOOKUP(B15, Paste!$Q$3:$Q$245, 1, FALSE)), "", VLOOKUP(B15, Paste!$Q$3:$R$245, 2, FALSE)) | U15: =IF(VLOOKUP(B15, 'Points&Potential'!$B$7:$O$943, 14, FALSE)=0, "", VLOOKUP(B15, 'Points&Potential'!$B$7:$O$943, 14, FALSE)) | V15: =IF(ISERROR(VLOOKUP(B15, Paste!$T$3:$T$1045, 1, FALSE)), "", VLOOKUP(B15, Paste!$T$3:$U$1144, 2, FALSE))
A16: 10 | B16: Kirill Kaprizov | C16: =VLOOKUP(B16, Paste!$AG$3:$AH$2083, 2, FALSE) -> 29.1 | D16: =VLOOKUP($B16, Paste!$A$3:$H$933, 6, FALSE) -> LW | E16: =IFERROR(VLOOKUP($B16, Paste!$J$3:$L$933, 3, FALSE), "") -> 92 | F16: =IFERROR(VLOOKUP($B16, Paste!$J$3:$L$933, 2, FALSE), "") -> 120 | G16: =VLOOKUP($B16, Paste!$A$3:$H$933, 8, FALSE) -> MIN | H16: =VLOOKUP($B16, Paste!$A$3:$H$933, 2, FALSE) -> 76 | I16: =VLOOKUP($B16, Paste!$A$3:$H$933, 3, FALSE) -> 45.085074 | J16: =K16-I16 -> 51.181705 | K16: =VLOOKUP($B16, Paste!$A$3:$H$933, 4, FALSE) -> 96.266779 | L16: =IF(ISBLANK(VLOOKUP(B16, 'SOG&PlusMinus'!$B$7:$E$912, 3, FALSE)), "", VLOOKUP(B16,'SOG&PlusMinus'!$B$7:$E$912, 3, FALSE)) -> A | M16: =IF(ISBLANK(VLOOKUP(B16, 'SOG&PlusMinus'!$B$7:$E$912, 4, FALSE)), "", VLOOKUP(B16, 'SOG&PlusMinus'!$B$7:$E$912, 4, FALSE)) -> 1 | N16: =VLOOKUP($B16, Paste!$A$3:$H$933, 5, FALSE) -> 31.340206 | O16: =IF(ISERROR(VLOOKUP(B16, Paste!$AB$3:$AE$2349, 3, FALSE)), "", VLOOKUP(B16, Paste!$AB$3:$AE$2349, 3, FALSE)) -> 48 | P16: =IF(ISERROR(VLOOKUP(B16, Paste!$AB$3:$AC$2343, 2, FALSE)), "", VLOOKUP(B16, Paste!$AB$3:$AC$2343, 2, FALSE)) -> 33 | Q16: =IF(ISERROR(VLOOKUP(B16, Paste!$AB$3:$AE$2349, 4, FALSE)), "", VLOOKUP(B16, Paste!$AB$3:$AE$2349, 4, FALSE)) -> 266 | R16: =IF(ISERROR(VLOOKUP(B16, Paste!$N$3:$N$250, 1, FALSE)), "", VLOOKUP(B16, Paste!$N$3:$O$250, 2, FALSE)) | S16: =VLOOKUP($B16, Paste!$W$3:$Z$10064, IF($H$4="Cap Hit",3, IF($H$4="AAV", 4, 2)), FALSE) -> 17 | T16: =IF(ISERROR(VLOOKUP(B16, Paste!$Q$3:$Q$245, 1, FALSE)), "", VLOOKUP(B16, Paste!$Q$3:$R$245, 2, FALSE)) | U16: =IF(VLOOKUP(B16, 'Points&Potential'!$B$7:$O$943, 14, FALSE)=0, "", VLOOKUP(B16, 'Points&Potential'!$B$7:$O$943, 14, FALSE)) | V16: =IF(ISERROR(VLOOKUP(B16, Paste!$T$3:$T$1045, 1, FALSE)), "", VLOOKUP(B16, Paste!$T$3:$U$1144, 2, FALSE))
A17: 11 | B17: Nick Suzuki | C17: =VLOOKUP(B17, Paste!$AG$3:$AH$2083, 2, FALSE) -> 26.8 | D17: =VLOOKUP($B17, Paste!$A$3:$H$933, 6, FALSE) -> C | E17: =IFERROR(VLOOKUP($B17, Paste!$J$3:$L$933, 3, FALSE), "") -> 93 | F17: =IFERROR(VLOOKUP($B17, Paste!$J$3:$L$933, 2, FALSE), "") -> 105 | G17: =VLOOKUP($B17, Paste!$A$3:$H$933, 8, FALSE) -> MTL | H17: =VLOOKUP($B17, Paste!$A$3:$H$933, 2, FALSE) -> 84 | I17: =VLOOKUP($B17, Paste!$A$3:$H$933, 3, FALSE) -> 31.366018 | J17: =K17-I17 -> 64.403912 | K17: =VLOOKUP($B17, Paste!$A$3:$H$933, 4, FALSE) -> 95.769931 | L17: =IF(ISBLANK(VLOOKUP(B17, 'SOG&PlusMinus'!$B$7:$E$912, 3, FALSE)), "", VLOOKUP(B17,'SOG&PlusMinus'!$B$7:$E$912, 3, FALSE)) -> A | M17: =IF(ISBLANK(VLOOKUP(B17, 'SOG&PlusMinus'!$B$7:$E$912, 4, FALSE)), "", VLOOKUP(B17, 'SOG&PlusMinus'!$B$7:$E$912, 4, FALSE)) -> 1 | N17: =VLOOKUP($B17, Paste!$A$3:$H$933, 5, FALSE) -> 24.585366 | O17: =IF(ISERROR(VLOOKUP(B17, Paste!$AB$3:$AE$2349, 3, FALSE)), "", VLOOKUP(B17, Paste!$AB$3:$AE$2349, 3, FALSE)) -> 66 | P17: =IF(ISERROR(VLOOKUP(B17, Paste!$AB$3:$AC$2343, 2, FALSE)), "", VLOOKUP(B17, Paste!$AB$3:$AC$2343, 2, FALSE)) -> 59 | Q17: =IF(ISERROR(VLOOKUP(B17, Paste!$AB$3:$AE$2349, 4, FALSE)), "", VLOOKUP(B17, Paste!$AB$3:$AE$2349, 4, FALSE)) -> 185 | R17: =IF(ISERROR(VLOOKUP(B17, Paste!$N$3:$N$250, 1, FALSE)), "", VLOOKUP(B17, Paste!$N$3:$O$250, 2, FALSE)) | S17: =VLOOKUP($B17, Paste!$W$3:$Z$10064, IF($H$4="Cap Hit",3, IF($H$4="AAV", 4, 2)), FALSE) -> 7.875 | T17: =IF(ISERROR(VLOOKUP(B17, Paste!$Q$3:$Q$245, 1, FALSE)), "", VLOOKUP(B17, Paste!$Q$3:$R$245, 2, FALSE)) | U17: =IF(VLOOKUP(B17, 'Points&Potential'!$B$7:$O$943, 14, FALSE)=0, "", VLOOKUP(B17, 'Points&Potential'!$B$7:$O$943, 14, FALSE)) | V17: =IF(ISERROR(VLOOKUP(B17, Paste!$T$3:$T$1045, 1, FALSE)), "", VLOOKUP(B17, Paste!$T$3:$U$1144, 2, FALSE))
A18: 12 | B18: Kyle Connor | C18: =VLOOKUP(B18, Paste!$AG$3:$AH$2083, 2, FALSE) -> 29.5 | D18: =VLOOKUP($B18, Paste!$A$3:$H$933, 6, FALSE) -> LW | E18: =IFERROR(VLOOKUP($B18, Paste!$J$3:$L$933, 3, FALSE), "") -> 90 | F18: =IFERROR(VLOOKUP($B18, Paste!$J$3:$L$933, 2, FALSE), "") -> 100 | G18: =VLOOKUP($B18, Paste!$A$3:$H$933, 8, FALSE) -> WPG | H18: =VLOOKUP($B18, Paste!$A$3:$H$933, 2, FALSE) -> 84 | I18: =VLOOKUP($B18, Paste!$A$3:$H$933, 3, FALSE) -> 41.842637 | J18: =K18-I18 -> 53.884545 | K18: =VLOOKUP($B18, Paste!$A$3:$H$933, 4, FALSE) -> 95.727182 | L18: =IF(ISBLANK(VLOOKUP(B18, 'SOG&PlusMinus'!$B$7:$E$912, 3, FALSE)), "", VLOOKUP(B18,'SOG&PlusMinus'!$B$7:$E$912, 3, FALSE)) -> C | M18: =IF(ISBLANK(VLOOKUP(B18, 'SOG&PlusMinus'!$B$7:$E$912, 4, FALSE)), "", VLOOKUP(B18, 'SOG&PlusMinus'!$B$7:$E$912, 4, FALSE)) -> 1 | N18: =VLOOKUP($B18, Paste!$A$3:$H$933, 5, FALSE) -> 17.240175 | O18: =IF(ISERROR(VLOOKUP(B18, Paste!$AB$3:$AE$2349, 3, FALSE)), "", VLOOKUP(B18, Paste!$AB$3:$AE$2349, 3, FALSE)) -> 25 | P18: =IF(ISERROR(VLOOKUP(B18, Paste!$AB$3:$AC$2343, 2, FALSE)), "", VLOOKUP(B18, Paste!$AB$3:$AC$2343, 2, FALSE)) -> 25 | Q18: =IF(ISERROR(VLOOKUP(B18, Paste!$AB$3:$AE$2349, 4, FALSE)), "", VLOOKUP(B18, Paste!$AB$3:$AE$2349, 4, FALSE)) -> 277 | R18: =IF(ISERROR(VLOOKUP(B18, Paste!$N$3:$N$250, 1, FALSE)), "", VLOOKUP(B18, Paste!$N$3:$O$250, 2, FALSE)) | S18: =VLOOKUP($B18, Paste!$W$3:$Z$10064, IF($H$4="Cap Hit",3, IF($H$4="AAV", 4, 2)), FALSE) -> 12 | T18: =IF(ISERROR(VLOOKUP(B18, Paste!$Q$3:$Q$245, 1, FALSE)), "", VLOOKUP(B18, Paste!$Q$3:$R$245, 2, FALSE)) | U18: =IF(VLOOKUP(B18, 'Points&Potential'!$B$7:$O$943, 14, FALSE)=0, "", VLOOKUP(B18, 'Points&Potential'!$B$7:$O$943, 14, FALSE)) | V18: =IF(ISERROR(VLOOKUP(B18, Paste!$T$3:$T$1045, 1, FALSE)), "", VLOOKUP(B18, Paste!$T$3:$U$1144, 2, FALSE))
... A49: 43 | B49: Lane Hutson | C49: =VLOOKUP(B49, Paste!$AG$3:$AH$2083, 2, FALSE) -> 22.3 | D49: =VLOOKUP($B49, Paste!$A$3:$H$933, 6, FALSE) -> LD | E49: =IFERROR(VLOOKUP($B49, Paste!$J$3:$L$933, 3, FALSE), "") -> 80 | F49: =IFERROR(VLOOKUP($B49, Paste!$J$3:$L$933, 2, FALSE), "") -> 95 | G49: =VLOOKUP($B49, Paste!$A$3:$H$933, 8, FALSE) -> MTL | H49: =VLOOKUP($B49, Paste!$A$3:$H$933, 2, FALSE) -> 84 | I49: =VLOOKUP($B49, Paste!$A$3:$H$933, 3, FALSE) -> 6.2785208 | J49: =K49-I49 -> 72.286405 | K49: =VLOOKUP($B49, Paste!$A$3:$H$933, 4, FALSE) -> 78.564926 | L49: =IF(ISBLANK(VLOOKUP(B49, 'SOG&PlusMinus'!$B$7:$E$912, 3, FALSE)), "", VLOOKUP(B49,'SOG&PlusMinus'!$B$7:$E$912, 3, FALSE)) -> A | M49: =IF(ISBLANK(VLOOKUP(B49, 'SOG&PlusMinus'!$B$7:$E$912, 4, FALSE)), "", VLOOKUP(B49, 'SOG&PlusMinus'!$B$7:$E$912, 4, FALSE)) -> 1 | N49: =VLOOKUP($B49, Paste!$A$3:$H$933, 5, FALSE) -> 34.409639 | O49: =IF(ISERROR(VLOOKUP(B49, Paste!$AB$3:$AE$2349, 3, FALSE)), "", VLOOKUP(B49, Paste!$AB$3:$AE$2349, 3, FALSE)) -> 37 | P49: =IF(ISERROR(VLOOKUP(B49, Paste!$AB$3:$AC$2343, 2, FALSE)), "", VLOOKUP(B49, Paste!$AB$3:$AC$2343, 2, FALSE)) -> 126 | Q49: =IF(ISERROR(VLOOKUP(B49, Paste!$AB$3:$AE$2349, 4, FALSE)), "", VLOOKUP(B49, Paste!$AB$3:$AE$2349, 4, FALSE)) -> 134 | R49: =IF(ISERROR(VLOOKUP(B49, Paste!$N$3:$N$250, 1, FALSE)), "", VLOOKUP(B49, Paste!$N$3:$O$250, 2, FALSE)) | S49: =VLOOKUP($B49, Paste!$W$3:$Z$10064, IF($H$4="Cap Hit",3, IF($H$4="AAV", 4, 2)), FALSE) -> 8.85 | T49: =IF(ISERROR(VLOOKUP(B49, Paste!$Q$3:$Q$245, 1, FALSE)), "", VLOOKUP(B49, Paste!$Q$3:$R$245, 2, FALSE)) | U49: =IF(VLOOKUP(B49, 'Points&Potential'!$B$7:$O$943, 14, FALSE)=0, "", VLOOKUP(B49, 'Points&Potential'!$B$7:$O$943, 14, FALSE)) | V49: =IF(ISERROR(VLOOKUP(B49, Paste!$T$3:$T$1045, 1, FALSE)), "", VLOOKUP(B49, Paste!$T$3:$U$1144, 2, FALSE))
A50: 44 | B50: Sam Reinhart | C50: =VLOOKUP(B50, Paste!$AG$3:$AH$2083, 2, FALSE) -> 30.6 | D50: =VLOOKUP($B50, Paste!$A$3:$H$933, 6, FALSE) -> RW | E50: =IFERROR(VLOOKUP($B50, Paste!$J$3:$L$933, 3, FALSE), "") -> 87 | F50: =IFERROR(VLOOKUP($B50, Paste!$J$3:$L$933, 2, FALSE), "") -> 100 | G50: =VLOOKUP($B50, Paste!$A$3:$H$933, 8, FALSE) -> FLA | H50: =VLOOKUP($B50, Paste!$A$3:$H$933, 2, FALSE) -> 77 | I50: =VLOOKUP($B50, Paste!$A$3:$H$933, 3, FALSE) -> 41.272125 | J50: =K50-I50 -> 37.199264 | K50: =VLOOKUP($B50, Paste!$A$3:$H$933, 4, FALSE) -> 78.471388 | L50: =IF(ISBLANK(VLOOKUP(B50, 'SOG&PlusMinus'!$B$7:$E$912, 3, FALSE)), "", VLOOKUP(B50,'SOG&PlusMinus'!$B$7:$E$912, 3, FALSE)) -> C | M50: =IF(ISBLANK(VLOOKUP(B50, 'SOG&PlusMinus'!$B$7:$E$912, 4, FALSE)), "", VLOOKUP(B50, 'SOG&PlusMinus'!$B$7:$E$912, 4, FALSE)) -> 1 | N50: =VLOOKUP($B50, Paste!$A$3:$H$933, 5, FALSE) -> 22.33 | O50: =IF(ISERROR(VLOOKUP(B50, Paste!$AB$3:$AE$2349, 3, FALSE)), "", VLOOKUP(B50, Paste!$AB$3:$AE$2349, 3, FALSE)) -> 73 | P50: =IF(ISERROR(VLOOKUP(B50, Paste!$AB$3:$AC$2343, 2, FALSE)), "", VLOOKUP(B50, Paste!$AB$3:$AC$2343, 2, FALSE)) -> 54 | Q50: =IF(ISERROR(VLOOKUP(B50, Paste!$AB$3:$AE$2349, 4, FALSE)), "", VLOOKUP(B50, Paste!$AB$3:$AE$2349, 4, FALSE)) -> 208 | R50: =IF(ISERROR(VLOOKUP(B50, Paste!$N$3:$N$250, 1, FALSE)), "", VLOOKUP(B50, Paste!$N$3:$O$250, 2, FALSE)) | S50: =VLOOKUP($B50, Paste!$W$3:$Z$10064, IF($H$4="Cap Hit",3, IF($H$4="AAV", 4, 2)), FALSE) -> 8.625 | U50: =IF(VLOOKUP(B50, 'Points&Potential'!$B$7:$O$943, 14, FALSE)=0, "", VLOOKUP(B50, 'Points&Potential'!$B$7:$O$943, 14, FALSE)) | V50: =IF(ISERROR(VLOOKUP(B50, Paste!$T$3:$T$1045, 1, FALSE)), "", VLOOKUP(B50, Paste!$T$3:$U$1144, 2, FALSE))
A51: 45 | B51: Drake Batherson | C51: =VLOOKUP(B51, Paste!$AG$3:$AH$2083, 2, FALSE) -> 28.1 | D51: =VLOOKUP($B51, Paste!$A$3:$H$933, 6, FALSE) -> RW | E51: =IFERROR(VLOOKUP($B51, Paste!$J$3:$L$933, 3, FALSE), "") -> 75 | F51: =IFERROR(VLOOKUP($B51, Paste!$J$3:$L$933, 2, FALSE), "") -> 87 | G51: =VLOOKUP($B51, Paste!$A$3:$H$933, 8, FALSE) -> OTT | H51: =VLOOKUP($B51, Paste!$A$3:$H$933, 2, FALSE) -> 83 | I51: =VLOOKUP($B51, Paste!$A$3:$H$933, 3, FALSE) -> 30.71 | J51: =K51-I51 -> 47.728113 | K51: =VLOOKUP($B51, Paste!$A$3:$H$933, 4, FALSE) -> 78.438113 | L51: =IF(ISBLANK(VLOOKUP(B51, 'SOG&PlusMinus'!$B$7:$E$912, 3, FALSE)), "", VLOOKUP(B51,'SOG&PlusMinus'!$B$7:$E$912, 3, FALSE)) -> C | M51: =IF(ISBLANK(VLOOKUP(B51, 'SOG&PlusMinus'!$B$7:$E$912, 4, FALSE)), "", VLOOKUP(B51, 'SOG&PlusMinus'!$B$7:$E$912, 4, FALSE)) -> 1 | N51: =VLOOKUP($B51, Paste!$A$3:$H$933, 5, FALSE) -> 35.864198 | O51: =IF(ISERROR(VLOOKUP(B51, Paste!$AB$3:$AE$2349, 3, FALSE)), "", VLOOKUP(B51, Paste!$AB$3:$AE$2349, 3, FALSE)) -> 125 | P51: =IF(ISERROR(VLOOKUP(B51, Paste!$AB$3:$AC$2343, 2, FALSE)), "", VLOOKUP(B51, Paste!$AB$3:$AC$2343, 2, FALSE)) -> 29 | Q51: =IF(ISERROR(VLOOKUP(B51, Paste!$AB$3:$AE$2349, 4, FALSE)), "", VLOOKUP(B51, Paste!$AB$3:$AE$2349, 4, FALSE)) -> 191 | R51: =IF(ISERROR(VLOOKUP(B51, Paste!$N$3:$N$250, 1, FALSE)), "", VLOOKUP(B51, Paste!$N$3:$O$250, 2, FALSE)) | S51: =VLOOKUP($B51, Paste!$W$3:$Z$10064, IF($H$4="Cap Hit",3, IF($H$4="AAV", 4, 2)), FALSE) -> 4.975 | T51: =IF(ISERROR(VLOOKUP(B51, Paste!$Q$3:$Q$245, 1, FALSE)), "", VLOOKUP(B51, Paste!$Q$3:$R$245, 2, FALSE)) | U51: =IF(VLOOKUP(B51, 'Points&Potential'!$B$7:$O$943, 14, FALSE)=0, "", VLOOKUP(B51, 'Points&Potential'!$B$7:$O$943, 14, FALSE)) | V51: =IF(ISERROR(VLOOKUP(B51, Paste!$T$3:$T$1045, 1, FALSE)), "", VLOOKUP(B51, Paste!$T$3:$U$1144, 2, FALSE))
A52: 46 | B52: Lucas Raymond | C52: =VLOOKUP(B52, Paste!$AG$3:$AH$2083, 2, FALSE) -> 24.2 | D52: =VLOOKUP($B52, Paste!$A$3:$H$933, 6, FALSE) -> RW | E52: =IFERROR(VLOOKUP($B52, Paste!$J$3:$L$933, 3, FALSE), "") -> 80 | F52: =IFERROR(VLOOKUP($B52, Paste!$J$3:$L$933, 2, FALSE), "") -> 92 | G52: =VLOOKUP($B52, Paste!$A$3:$H$933, 8, FALSE) -> DET | H52: =VLOOKUP($B52, Paste!$A$3:$H$933, 2, FALSE) -> 76.666667 | I52: =VLOOKUP($B52, Paste!$A$3:$H$933, 3, FALSE) -> 26.638858 | J52: =K52-I52 -> 51.474436 | K52: =VLOOKUP($B52, Paste!$A$3:$H$933, 4, FALSE) -> 78.113295 | L52: =IF(ISBLANK(VLOOKUP(B52, 'SOG&PlusMinus'!$B$7:$E$912, 3, FALSE)), "", VLOOKUP(B52,'SOG&PlusMinus'!$B$7:$E$912, 3, FALSE)) -> C | M52: =IF(ISBLANK(VLOOKUP(B52, 'SOG&PlusMinus'!$B$7:$E$912, 4, FALSE)), "", VLOOKUP(B52, 'SOG&PlusMinus'!$B$7:$E$912, 4, FALSE)) -> 1 | N52: =VLOOKUP($B52, Paste!$A$3:$H$933, 5, FALSE) -> 21.994536 | O52: =IF(ISERROR(VLOOKUP(B52, Paste!$AB$3:$AE$2349, 3, FALSE)), "", VLOOKUP(B52, Paste!$AB$3:$AE$2349, 3, FALSE)) -> 41 | P52: =IF(ISERROR(VLOOKUP(B52, Paste!$AB$3:$AC$2343, 2, FALSE)), "", VLOOKUP(B52, Paste!$AB$3:$AC$2343, 2, FALSE)) -> 31 | Q52: =IF(ISERROR(VLOOKUP(B52, Paste!$AB$3:$AE$2349, 4, FALSE)), "", VLOOKUP(B52, Paste!$AB$3:$AE$2349, 4, FALSE)) -> 176 | R52: =IF(ISERROR(VLOOKUP(B52, Paste!$N$3:$N$250, 1, FALSE)), "", VLOOKUP(B52, Paste!$N$3:$O$250, 2, FALSE)) | S52: =VLOOKUP($B52, Paste!$W$3:$Z$10064, IF($H$4="Cap Hit",3, IF($H$4="AAV", 4, 2)), FALSE) -> 8.075 | T52: =IF(ISERROR(VLOOKUP(B52, Paste!$Q$3:$Q$245, 1, FALSE)), "", VLOOKUP(B52, Paste!$Q$3:$R$245, 2, FALSE)) | U52: =IF(VLOOKUP(B52, 'Points&Potential'!$B$7:$O$943, 14, FALSE)=0, "", VLOOKUP(B52, 'Points&Potential'!$B$7:$O$943, 14, FALSE)) | V52: =IF(ISERROR(VLOOKUP(B52, Paste!$T$3:$T$1045, 1, FALSE)), "", VLOOKUP(B52, Paste!$T$3:$U$1144, 2, FALSE))
A53: 47 | B53: Aleksander Barkov | C53: =VLOOKUP(B53, Paste!$AG$3:$AH$2083, 2, FALSE) -> 30.8 | D53: =VLOOKUP($B53, Paste!$A$3:$H$933, 6, FALSE) -> C | E53: =IFERROR(VLOOKUP($B53, Paste!$J$3:$L$933, 3, FALSE), "") -> 80 | F53: =IFERROR(VLOOKUP($B53, Paste!$J$3:$L$933, 2, FALSE), "") -> 100 | G53: =VLOOKUP($B53, Paste!$A$3:$H$933, 8, FALSE) -> FLA | H53: =VLOOKUP($B53, Paste!$A$3:$H$933, 2, FALSE) -> 75 | I53: =VLOOKUP($B53, Paste!$A$3:$H$933, 3, FALSE) -> 23.25 | J53: =K53-I53 -> 54.705961 | K53: =VLOOKUP($B53, Paste!$A$3:$H$933, 4, FALSE) -> 77.955961 | L53: =IF(ISBLANK(VLOOKUP(B53, 'SOG&PlusMinus'!$B$7:$E$912, 3, FALSE)), "", VLOOKUP(B53,'SOG&PlusMinus'!$B$7:$E$912, 3, FALSE)) -> B | M53: =IF(ISBLANK(VLOOKUP(B53, 'SOG&PlusMinus'!$B$7:$E$912, 4, FALSE)), "", VLOOKUP(B53, 'SOG&PlusMinus'!$B$7:$E$912, 4, FALSE)) -> 1 | N53: =VLOOKUP($B53, Paste!$A$3:$H$933, 5, FALSE) -> 18 | O53: =IF(ISERROR(VLOOKUP(B53, Paste!$AB$3:$AE$2349, 3, FALSE)), "", VLOOKUP(B53, Paste!$AB$3:$AE$2349, 3, FALSE)) -> 90 | P53: =IF(ISERROR(VLOOKUP(B53, Paste!$AB$3:$AC$2343, 2, FALSE)), "", VLOOKUP(B53, Paste!$AB$3:$AC$2343, 2, FALSE)) -> 53 | Q53: =IF(ISERROR(VLOOKUP(B53, Paste!$AB$3:$AE$2349, 4, FALSE)), "", VLOOKUP(B53, Paste!$AB$3:$AE$2349, 4, FALSE)) -> 165 | R53: =IF(ISERROR(VLOOKUP(B53, Paste!$N$3:$N$250, 1, FALSE)), "", VLOOKUP(B53, Paste!$N$3:$O$250, 2, FALSE)) | S53: =VLOOKUP($B53, Paste!$W$3:$Z$10064, IF($H$4="Cap Hit",3, IF($H$4="AAV", 4, 2)), FALSE) -> 10 | T53: =IF(ISERROR(VLOOKUP(B53, Paste!$Q$3:$Q$245, 1, FALSE)), "", VLOOKUP(B53, Paste!$Q$3:$R$245, 2, FALSE)) -> Y | U53: =IF(VLOOKUP(B53, 'Points&Potential'!$B$7:$O$943, 14, FALSE)=0, "", VLOOKUP(B53, 'Points&Potential'!$B$7:$O$943, 14, FALSE)) | V53: =IF(ISERROR(VLOOKUP(B53, Paste!$T$3:$T$1045, 1, FALSE)), "", VLOOKUP(B53, Paste!$T$3:$U$1144, 2, FALSE))
A54: 48 | B54: Filip Forsberg | C54: =VLOOKUP(B54, Paste!$AG$3:$AH$2083, 2, FALSE) -> 31.8 | D54: =VLOOKUP($B54, Paste!$A$3:$H$933, 6, FALSE) -> LW | E54: =IFERROR(VLOOKUP($B54, Paste!$J$3:$L$933, 3, FALSE), "") -> 75 | F54: =IFERROR(VLOOKUP($B54, Paste!$J$3:$L$933, 2, FALSE), "") -> 95 | G54: =VLOOKUP($B54, Paste!$A$3:$H$933, 8, FALSE) -> NSH | H54: =VLOOKUP($B54, Paste!$A$3:$H$933, 2, FALSE) -> 84 | I54: =VLOOKUP($B54, Paste!$A$3:$H$933, 3, FALSE) -> 38.547206 | J54: =K54-I54 -> 39.205226 | K54: =VLOOKUP($B54, Paste!$A$3:$H$933, 4, FALSE) -> 77.752432 | L54: =IF(ISBLANK(VLOOKUP(B54, 'SOG&PlusMinus'!$B$7:$E$912, 3, FALSE)), "", VLOOKUP(B54,'SOG&PlusMinus'!$B$7:$E$912, 3, FALSE)) -> C | M54: =IF(ISBLANK(VLOOKUP(B54, 'SOG&PlusMinus'!$B$7:$E$912, 4, FALSE)), "", VLOOKUP(B54, 'SOG&PlusMinus'!$B$7:$E$912, 4, FALSE)) -> 1 | N54: =VLOOKUP($B54, Paste!$A$3:$H$933, 5, FALSE) -> 41.317073 | O54: =IF(ISERROR(VLOOKUP(B54, Paste!$AB$3:$AE$2349, 3, FALSE)), "", VLOOKUP(B54, Paste!$AB$3:$AE$2349, 3, FALSE)) -> 134 | P54: =IF(ISERROR(VLOOKUP(B54, Paste!$AB$3:$AC$2343, 2, FALSE)), "", VLOOKUP(B54, Paste!$AB$3:$AC$2343, 2, FALSE)) -> 42 | Q54: =IF(ISERROR(VLOOKUP(B54, Paste!$AB$3:$AE$2349, 4, FALSE)), "", VLOOKUP(B54, Paste!$AB$3:$AE$2349, 4, FALSE)) -> 260 | R54: =IF(ISERROR(VLOOKUP(B54, Paste!$N$3:$N$250, 1, FALSE)), "", VLOOKUP(B54, Paste!$N$3:$O$250, 2, FALSE)) | S54: =VLOOKUP($B54, Paste!$W$3:$Z$10064, IF($H$4="Cap Hit",3, IF($H$4="AAV", 4, 2)), FALSE) -> 8.5 | T54: =IF(ISERROR(VLOOKUP(B54, Paste!$Q$3:$Q$245, 1, FALSE)), "", VLOOKUP(B54, Paste!$Q$3:$R$245, 2, FALSE)) | U54: =IF(VLOOKUP(B54, 'Points&Potential'!$B$7:$O$943, 14, FALSE)=0, "", VLOOKUP(B54, 'Points&Potential'!$B$7:$O$943, 14, FALSE)) | V54: =IF(ISERROR(VLOOKUP(B54, Paste!$T$3:$T$1045, 1, FALSE)), "", VLOOKUP(B54, Paste!$T$3:$U$1144, 2, FALSE))
A55: 49 | B55: Adrian Kempe | C55: =VLOOKUP(B55, Paste!$AG$3:$AH$2083, 2, FALSE) -> 29.8 | D55: =VLOOKUP($B55, Paste!$A$3:$H$933, 6, FALSE) -> RW | E55: =IFERROR(VLOOKUP($B55, Paste!$J$3:$L$933, 3, FALSE), "") -> 73 | F55: =IFERROR(VLOOKUP($B55, Paste!$J$3:$L$933, 2, FALSE), "") -> 83 | G55: =VLOOKUP($B55, Paste!$A$3:$H$933, 8, FALSE) -> LAK | H55: =VLOOKUP($B55, Paste!$A$3:$H$933, 2, FALSE) -> 81.666667 | I55: =VLOOKUP($B55, Paste!$A$3:$H$933, 3, FALSE) -> 33.253977 | J55: =K55-I55 -> 42.631833 | K55: =VLOOKUP($B55, Paste!$A$3:$H$933, 4, FALSE) -> 75.88581 | L55: =IF(ISBLANK(VLOOKUP(B55, 'SOG&PlusMinus'!$B$7:$E$912, 3, FALSE)), "", VLOOKUP(B55,'SOG&PlusMinus'!$B$7:$E$912, 3, FALSE)) -> A | M55: =IF(ISBLANK(VLOOKUP(B55, 'SOG&PlusMinus'!$B$7:$E$912, 4, FALSE)), "", VLOOKUP(B55, 'SOG&PlusMinus'!$B$7:$E$912, 4, FALSE)) -> 1 | N55: =VLOOKUP($B55, Paste!$A$3:$H$933, 5, FALSE) -> 56.722455 | O55: =IF(ISERROR(VLOOKUP(B55, Paste!$AB$3:$AE$2349, 3, FALSE)), "", VLOOKUP(B55, Paste!$AB$3:$AE$2349, 3, FALSE)) -> 123 | P55: =IF(ISERROR(VLOOKUP(B55, Paste!$AB$3:$AC$2343, 2, FALSE)), "", VLOOKUP(B55, Paste!$AB$3:$AC$2343, 2, FALSE)) -> 37 | Q55: =IF(ISERROR(VLOOKUP(B55, Paste!$AB$3:$AE$2349, 4, FALSE)), "", VLOOKUP(B55, Paste!$AB$3:$AE$2349, 4, FALSE)) -> 237 | R55: =IF(ISERROR(VLOOKUP(B55, Paste!$N$3:$N$250, 1, FALSE)), "", VLOOKUP(B55, Paste!$N$3:$O$250, 2, FALSE)) | S55: =VLOOKUP($B55, Paste!$W$3:$Z$10064, IF($H$4="Cap Hit",3, IF($H$4="AAV", 4, 2)), FALSE) -> 10.625 | T55: =IF(ISERROR(VLOOKUP(B55, Paste!$Q$3:$Q$245, 1, FALSE)), "", VLOOKUP(B55, Paste!$Q$3:$R$245, 2, FALSE)) | U55: =IF(VLOOKUP(B55, 'Points&Potential'!$B$7:$O$943, 14, FALSE)=0, "", VLOOKUP(B55, 'Points&Potential'!$B$7:$O$943, 14, FALSE)) | V55: =IF(ISERROR(VLOOKUP(B55, Paste!$T$3:$T$1045, 1, FALSE)), "", VLOOKUP(B55, Paste!$T$3:$U$1144, 2, FALSE))
A56: 50 | B56: Kirill Marchenko | C56: =VLOOKUP(B56, Paste!$AG$3:$AH$2083, 2, FALSE) -> 25.9 | D56: =VLOOKUP($B56, Paste!$A$3:$H$933, 6, FALSE) -> LW | E56: =IFERROR(VLOOKUP($B56, Paste!$J$3:$L$933, 3, FALSE), "") -> 75 | F56: =IFERROR(VLOOKUP($B56, Paste!$J$3:$L$933, 2, FALSE), "") -> 85 | G56: =VLOOKUP($B56, Paste!$A$3:$H$933, 8, FALSE) -> CBJ | H56: =VLOOKUP($B56, Paste!$A$3:$H$933, 2, FALSE) -> 79.666667 | I56: =VLOOKUP($B56, Paste!$A$3:$H$933, 3, FALSE) -> 28.371351 | J56: =K56-I56 -> 47.485345 | K56: =VLOOKUP($B56, Paste!$A$3:$H$933, 4, FALSE) -> 75.856695 | L56: =IF(ISBLANK(VLOOKUP(B56, 'SOG&PlusMinus'!$B$7:$E$912, 3, FALSE)), "", VLOOKUP(B56,'SOG&PlusMinus'!$B$7:$E$912, 3, FALSE)) -> C | M56: =IF(ISBLANK(VLOOKUP(B56, 'SOG&PlusMinus'!$B$7:$E$912, 4, FALSE)), "", VLOOKUP(B56, 'SOG&PlusMinus'!$B$7:$E$912, 4, FALSE)) -> 1 | N56: =VLOOKUP($B56, Paste!$A$3:$H$933, 5, FALSE) -> 22.566524 | O56: =IF(ISERROR(VLOOKUP(B56, Paste!$AB$3:$AE$2349, 3, FALSE)), "", VLOOKUP(B56, Paste!$AB$3:$AE$2349, 3, FALSE)) -> 60 | P56: =IF(ISERROR(VLOOKUP(B56, Paste!$AB$3:$AC$2343, 2, FALSE)), "", VLOOKUP(B56, Paste!$AB$3:$AC$2343, 2, FALSE)) -> 41 | Q56: =IF(ISERROR(VLOOKUP(B56, Paste!$AB$3:$AE$2349, 4, FALSE)), "", VLOOKUP(B56, Paste!$AB$3:$AE$2349, 4, FALSE)) -> 239 | R56: =IF(ISERROR(VLOOKUP(B56, Paste!$N$3:$N$250, 1, FALSE)), "", VLOOKUP(B56, Paste!$N$3:$O$250, 2, FALSE)) | S56: =VLOOKUP($B56, Paste!$W$3:$Z$10064, IF($H$4="Cap Hit",3, IF($H$4="AAV", 4, 2)), FALSE) -> 3.85 | T56: =IF(ISERROR(VLOOKUP(B56, Paste!$Q$3:$Q$245, 1, FALSE)), "", VLOOKUP(B56, Paste!$Q$3:$R$245, 2, FALSE)) | U56: =IF(VLOOKUP(B56, 'Points&Potential'!$B$7:$O$943, 14, FALSE)=0, "", VLOOKUP(B56, 'Points&Potential'!$B$7:$O$943, 14, FALSE)) | V56: =IF(ISERROR(VLOOKUP(B56, Paste!$T$3:$T$1045, 1, FALSE)), "", VLOOKUP(B56, Paste!$T$3:$U$1144, 2, FALSE))
A57: 51 | B57: Ivan Demidov | C57: =VLOOKUP(B57, Paste!$AG$3:$AH$2083, 2, FALSE) -> 20.5 | D57: =VLOOKUP($B57, Paste!$A$3:$H$933, 6, FALSE) -> RW | E57: =IFERROR(VLOOKUP($B57, Paste!$J$3:$L$933, 3, FALSE), "") -> 80 | F57: =IFERROR(VLOOKUP($B57, Paste!$J$3:$L$933, 2, FALSE), "") -> 110 | G57: =VLOOKUP($B57, Paste!$A$3:$H$933, 8, FALSE) -> MTL | H57: =VLOOKUP($B57, Paste!$A$3:$H$933, 2, FALSE) -> 82 | I57: =VLOOKUP($B57, Paste!$A$3:$H$933, 3, FALSE) -> 27.881102 | J57: =K57-I57 -> 47.588134 | K57: =VLOOKUP($B57, Paste!$A$3:$H$933, 4, FALSE) -> 75.469236 | L57: =IF(ISBLANK(VLOOKUP(B57, 'SOG&PlusMinus'!$B$7:$E$912, 3, FALSE)), "", VLOOKUP(B57,'SOG&PlusMinus'!$B$7:$E$912, 3, FALSE)) -> C | M57: =IF(ISBLANK(VLOOKUP(B57, 'SOG&PlusMinus'!$B$7:$E$912, 4, FALSE)), "", VLOOKUP(B57, 'SOG&PlusMinus'!$B$7:$E$912, 4, FALSE)) -> 1 | N57: =VLOOKUP($B57, Paste!$A$3:$H$933, 5, FALSE) -> 22.126984 | O57: =IF(ISERROR(VLOOKUP(B57, Paste!$AB$3:$AE$2349, 3, FALSE)), "", VLOOKUP(B57, Paste!$AB$3:$AE$2349, 3, FALSE)) -> 32 | P57: =IF(ISERROR(VLOOKUP(B57, Paste!$AB$3:$AC$2343, 2, FALSE)), "", VLOOKUP(B57, Paste!$AB$3:$AC$2343, 2, FALSE)) -> 29 | Q57: =IF(ISERROR(VLOOKUP(B57, Paste!$AB$3:$AE$2349, 4, FALSE)), "", VLOOKUP(B57, Paste!$AB$3:$AE$2349, 4, FALSE)) -> 156 | R57: =IF(ISERROR(VLOOKUP(B57, Paste!$N$3:$N$250, 1, FALSE)), "", VLOOKUP(B57, Paste!$N$3:$O$250, 2, FALSE)) | S57: =VLOOKUP($B57, Paste!$W$3:$Z$10064, IF($H$4="Cap Hit",3, IF($H$4="AAV", 4, 2)), FALSE) -> 2.634167 | T57: =IF(ISERROR(VLOOKUP(B57, Paste!$Q$3:$Q$245, 1, FALSE)), "", VLOOKUP(B57, Paste!$Q$3:$R$245, 2, FALSE)) | U57: =IF(VLOOKUP(B57, 'Points&Potential'!$B$7:$O$943, 14, FALSE)=0, "", VLOOKUP(B57, 'Points&Potential'!$B$7:$O$943, 14, FALSE)) | V57: =IF(ISERROR(VLOOKUP(B57, Paste!$T$3:$T$1045, 1, FALSE)), "", VLOOKUP(B57, Paste!$T$3:$U$1144, 2, FALSE))
A58: 52 | B58: Rasmus Dahlin | C58: =VLOOKUP(B58, Paste!$AG$3:$AH$2083, 2, FALSE) -> 26.2 | D58: =VLOOKUP($B58, Paste!$A$3:$H$933, 6, FALSE) -> LD | E58: =IFERROR(VLOOKUP($B58, Paste!$J$3:$L$933, 3, FALSE), "") -> 77 | F58: =IFERROR(VLOOKUP($B58, Paste!$J$3:$L$933, 2, FALSE), "") -> 95 | G58: =VLOOKUP($B58, Paste!$A$3:$H$933, 8, FALSE) -> BUF | H58: =VLOOKUP($B58, Paste!$A$3:$H$933, 2, FALSE) -> 79 | I58: =VLOOKUP($B58, Paste!$A$3:$H$933, 3, FALSE) -> 18.751072 | J58: =K58-I58 -> 56.662537 | K58: =VLOOKUP($B58, Paste!$A$3:$H$933, 4, FALSE) -> 75.413608 | L58: =IF(ISBLANK(VLOOKUP(B58, 'SOG&PlusMinus'!$B$7:$E$912, 3, FALSE)), "", VLOOKUP(B58,'SOG&PlusMinus'!$B$7:$E$912, 3, FALSE)) -> A | M58: =IF(ISBLANK(VLOOKUP(B58, 'SOG&PlusMinus'!$B$7:$E$912, 4, FALSE)), "", VLOOKUP(B58, 'SOG&PlusMinus'!$B$7:$E$912, 4, FALSE)) -> 1 | N58: =VLOOKUP($B58, Paste!$A$3:$H$933, 5, FALSE) -> 67.030303 | O58: =IF(ISERROR(VLOOKUP(B58, Paste!$AB$3:$AE$2349, 3, FALSE)), "", VLOOKUP(B58, Paste!$AB$3:$AE$2349, 3, FALSE)) -> 82 | P58: =IF(ISERROR(VLOOKUP(B58, Paste!$AB$3:$AC$2343, 2, FALSE)), "", VLOOKUP(B58, Paste!$AB$3:$AC$2343, 2, FALSE)) -> 114 | Q58: =IF(ISERROR(VLOOKUP(B58, Paste!$AB$3:$AE$2349, 4, FALSE)), "", VLOOKUP(B58, Paste!$AB$3:$AE$2349, 4, FALSE)) -> 213 | R58: =IF(ISERROR(VLOOKUP(B58, Paste!$N$3:$N$250, 1, FALSE)), "", VLOOKUP(B58, Paste!$N$3:$O$250, 2, FALSE)) | S58: =VLOOKUP($B58, Paste!$W$3:$Z$10064, IF($H$4="Cap Hit",3, IF($H$4="AAV", 4, 2)), FALSE) -> 11 | U58: =IF(VLOOKUP(B58, 'Points&Potential'!$B$7:$O$943, 14, FALSE)=0, "", VLOOKUP(B58, 'Points&Potential'!$B$7:$O$943, 14, FALSE)) | V58: =IF(ISERROR(VLOOKUP(B58, Paste!$T$3:$T$1045, 1, FALSE)), "", VLOOKUP(B58, Paste!$T$3:$U$1144, 2, FALSE))
A59: 53 | B59: Leo Carlsson | C59: =VLOOKUP(B59, Paste!$AG$3:$AH$2083, 2, FALSE) -> 21.5 | D59: =VLOOKUP($B59, Paste!$A$3:$H$933, 6, FALSE) -> C | E59: =IFERROR(VLOOKUP($B59, Paste!$J$3:$L$933, 3, FALSE), "") -> 85 | F59: =IFERROR(VLOOKUP($B59, Paste!$J$3:$L$933, 2, FALSE), "") -> 100 | G59: =VLOOKUP($B59, Paste!$A$3:$H$933, 8, FALSE) -> ANA | H59: =VLOOKUP($B59, Paste!$A$3:$H$933, 2, FALSE) -> 72 | I59: =VLOOKUP($B59, Paste!$A$3:$H$933, 3, FALSE) -> 32.4 | J59: =K59-I59 -> 41.73705 | K59: =VLOOKUP($B59, Paste!$A$3:$H$933, 4, FALSE) -> 74.13705 | L59: =IF(ISBLANK(VLOOKUP(B59, 'SOG&PlusMinus'!$B$7:$E$912, 3, FALSE)), "", VLOOKUP(B59,'SOG&PlusMinus'!$B$7:$E$912, 3, FALSE)) -> C | M59: =IF(ISBLANK(VLOOKUP(B59, 'SOG&PlusMinus'!$B$7:$E$912, 4, FALSE)), "", VLOOKUP(B59, 'SOG&PlusMinus'!$B$7:$E$912, 4, FALSE)) -> 1 | N59: =VLOOKUP($B59, Paste!$A$3:$H$933, 5, FALSE) -> 22.567164 | O59: =IF(ISERROR(VLOOKUP(B59, Paste!$AB$3:$AE$2349, 3, FALSE)), "", VLOOKUP(B59, Paste!$AB$3:$AE$2349, 3, FALSE)) -> 22 | P59: =IF(ISERROR(VLOOKUP(B59, Paste!$AB$3:$AC$2343, 2, FALSE)), "", VLOOKUP(B59, Paste!$AB$3:$AC$2343, 2, FALSE)) -> 33 | Q59: =IF(ISERROR(VLOOKUP(B59, Paste!$AB$3:$AE$2349, 4, FALSE)), "", VLOOKUP(B59, Paste!$AB$3:$AE$2349, 4, FALSE)) -> 209 | R59: =IF(ISERROR(VLOOKUP(B59, Paste!$N$3:$N$250, 1, FALSE)), "", VLOOKUP(B59, Paste!$N$3:$O$250, 2, FALSE)) -> 85 | S59: =VLOOKUP($B59, Paste!$W$3:$Z$10064, IF($H$4="Cap Hit",3, IF($H$4="AAV", 4, 2)), FALSE) -> 18 | T59: =IF(ISERROR(VLOOKUP(B59, Paste!$Q$3:$Q$245, 1, FALSE)), "", VLOOKUP(B59, Paste!$Q$3:$R$245, 2, FALSE)) -> Y | U59: =IF(VLOOKUP(B59, 'Points&Potential'!$B$7:$O$943, 14, FALSE)=0, "", VLOOKUP(B59, 'Points&Potential'!$B$7:$O$943, 14, FALSE)) | V59: =IF(ISERROR(VLOOKUP(B59, Paste!$T$3:$T$1045, 1, FALSE)), "", VLOOKUP(B59, Paste!$T$3:$U$1144, 2, FALSE))
A60: 54 | B60: Mika Zibanejad | C60: =VLOOKUP(B60, Paste!$AG$3:$AH$2083, 2, FALSE) -> 33.2 | D60: =VLOOKUP($B60, Paste!$A$3:$H$933, 6, FALSE) -> C | E60: =IFERROR(VLOOKUP($B60, Paste!$J$3:$L$933, 3, FALSE), "") -> 67 | F60: =IFERROR(VLOOKUP($B60, Paste!$J$3:$L$933, 2, FALSE), "") -> 75 | G60: =VLOOKUP($B60, Paste!$A$3:$H$933, 8, FALSE) -> NYR | H60: =VLOOKUP($B60, Paste!$A$3:$H$933, 2, FALSE) -> 83.333333 | I60: =VLOOKUP($B60, Paste!$A$3:$H$933, 3, FALSE) -> 27.015907 | J60: =K60-I60 -> 46.780389 | K60: =VLOOKUP($B60, Paste!$A$3:$H$933, 4, FALSE) -> 73.796297 | L60: =IF(ISBLANK(VLOOKUP(B60, 'SOG&PlusMinus'!$B$7:$E$912, 3, FALSE)), "", VLOOKUP(B60,'SOG&PlusMinus'!$B$7:$E$912, 3, FALSE)) -> D | M60: =IF(ISBLANK(VLOOKUP(B60, 'SOG&PlusMinus'!$B$7:$E$912, 4, FALSE)), "", VLOOKUP(B60, 'SOG&PlusMinus'!$B$7:$E$912, 4, FALSE)) -> 1 | N60: =VLOOKUP($B60, Paste!$A$3:$H$933, 5, FALSE) -> 22.540984 | O60: =IF(ISERROR(VLOOKUP(B60, Paste!$AB$3:$AE$2349, 3, FALSE)), "", VLOOKUP(B60, Paste!$AB$3:$AE$2349, 3, FALSE)) -> 68 | P60: =IF(ISERROR(VLOOKUP(B60, Paste!$AB$3:$AC$2343, 2, FALSE)), "", VLOOKUP(B60, Paste!$AB$3:$AC$2343, 2, FALSE)) -> 52 | Q60: =IF(ISERROR(VLOOKUP(B60, Paste!$AB$3:$AE$2349, 4, FALSE)), "", VLOOKUP(B60, Paste!$AB$3:$AE$2349, 4, FALSE)) -> 208 | R60: =IF(ISERROR(VLOOKUP(B60, Paste!$N$3:$N$250, 1, FALSE)), "", VLOOKUP(B60, Paste!$N$3:$O$250, 2, FALSE)) | S60: =VLOOKUP($B60, Paste!$W$3:$Z$10064, IF($H$4="Cap Hit",3, IF($H$4="AAV", 4, 2)), FALSE) -> 8.5 | T60: =IF(ISERROR(VLOOKUP(B60, Paste!$Q$3:$Q$245, 1, FALSE)), "", VLOOKUP(B60, Paste!$Q$3:$R$245, 2, FALSE)) | U60: =IF(VLOOKUP(B60, 'Points&Potential'!$B$7:$O$943, 14, FALSE)=0, "", VLOOKUP(B60, 'Points&Potential'!$B$7:$O$943, 14, FALSE)) | V60: =IF(ISERROR(VLOOKUP(B60, Paste!$T$3:$T$1045, 1, FALSE)), "", VLOOKUP(B60, Paste!$T$3:$U$1144, 2, FALSE))
A61: 55 | B61: Cutter Gauthier | C61: =VLOOKUP(B61, Paste!$AG$3:$AH$2083, 2, FALSE) -> 22.4 | D61: =VLOOKUP($B61, Paste!$A$3:$H$933, 6, FALSE) -> RW | E61: =IFERROR(VLOOKUP($B61, Paste!$J$3:$L$933, 3, FALSE), "") -> 77 | F61: =IFERROR(VLOOKUP($B61, Paste!$J$3:$L$933, 2, FALSE), "") -> 92 | G61: =VLOOKUP($B61, Paste!$A$3:$H$933, 8, FALSE) -> ANA | H61: =VLOOKUP($B61, Paste!$A$3:$H$933, 2, FALSE) -> 79 | I61: =VLOOKUP($B61, Paste!$A$3:$H$933, 3, FALSE) -> 41.08 | J61: =K61-I61 -> 32.49902 | K61: =VLOOKUP($B61, Paste!$A$3:$H$933, 4, FALSE) -> 73.57902 | L61: =IF(ISBLANK(VLOOKUP(B61, 'SOG&PlusMinus'!$B$7:$E$912, 3, FALSE)), "", VLOOKUP(B61,'SOG&PlusMinus'!$B$7:$E$912, 3, FALSE)) -> C | M61: =IF(ISBLANK(VLOOKUP(B61, 'SOG&PlusMinus'!$B$7:$E$912, 4, FALSE)), "", VLOOKUP(B61, 'SOG&PlusMinus'!$B$7:$E$912, 4, FALSE)) -> 1 | N61: =VLOOKUP($B61, Paste!$A$3:$H$933, 5, FALSE) -> 23.849057 | O61: =IF(ISERROR(VLOOKUP(B61, Paste!$AB$3:$AE$2349, 3, FALSE)), "", VLOOKUP(B61, Paste!$AB$3:$AE$2349, 3, FALSE)) -> 67 | P61: =IF(ISERROR(VLOOKUP(B61, Paste!$AB$3:$AC$2343, 2, FALSE)), "", VLOOKUP(B61, Paste!$AB$3:$AC$2343, 2, FALSE)) -> 32 | Q61: =IF(ISERROR(VLOOKUP(B61, Paste!$AB$3:$AE$2349, 4, FALSE)), "", VLOOKUP(B61, Paste!$AB$3:$AE$2349, 4, FALSE)) -> 316 | R61: =IF(ISERROR(VLOOKUP(B61, Paste!$N$3:$N$250, 1, FALSE)), "", VLOOKUP(B61, Paste!$N$3:$O$250, 2, FALSE)) | S61: =VLOOKUP($B61, Paste!$W$3:$Z$10064, IF($H$4="Cap Hit",3, IF($H$4="AAV", 4, 2)), FALSE) -> #N/A | T61: =IF(ISERROR(VLOOKUP(B61, Paste!$Q$3:$Q$245, 1, FALSE)), "", VLOOKUP(B61, Paste!$Q$3:$R$245, 2, FALSE)) | U61: =IF(VLOOKUP(B61, 'Points&Potential'!$B$7:$O$943, 14, FALSE)=0, "", VLOOKUP(B61, 'Points&Potential'!$B$7:$O$943, 14, FALSE)) | V61: =IF(ISERROR(VLOOKUP(B61, Paste!$T$3:$T$1045, 1, FALSE)), "", VLOOKUP(B61, Paste!$T$3:$U$1144, 2, FALSE))
A62: 56 | B62: Brady Tkachuk | C62: =VLOOKUP(B62, Paste!$AG$3:$AH$2083, 2, FALSE) -> 26.7 | D62: =VLOOKUP($B62, Paste!$A$3:$H$933, 6, FALSE) -> LW | E62: =IFERROR(VLOOKUP($B62, Paste!$J$3:$L$933, 3, FALSE), "") -> 82 | F62: =IFERROR(VLOOKUP($B62, Paste!$J$3:$L$933, 2, FALSE), "") -> 97 | G62: =VLOOKUP($B62, Paste!$A$3:$H$933, 8, FALSE) -> FLA | H62: =VLOOKUP($B62, Paste!$A$3:$H$933, 2, FALSE) -> 73 | I62: =VLOOKUP($B62, Paste!$A$3:$H$933, 3, FALSE) -> 30.66 | J62: =K62-I62 -> 41.965545 | K62: =VLOOKUP($B62, Paste!$A$3:$H$933, 4, FALSE) -> 72.625545 | L62: =IF(ISBLANK(VLOOKUP(B62, 'SOG&PlusMinus'!$B$7:$E$912, 3, FALSE)), "", VLOOKUP(B62,'SOG&PlusMinus'!$B$7:$E$912, 3, FALSE)) -> C | M62: =IF(ISBLANK(VLOOKUP(B62, 'SOG&PlusMinus'!$B$7:$E$912, 4, FALSE)), "", VLOOKUP(B62, 'SOG&PlusMinus'!$B$7:$E$912, 4, FALSE)) -> 1 | N62: =VLOOKUP($B62, Paste!$A$3:$H$933, 5, FALSE) -> 124.1 | O62: =IF(ISERROR(VLOOKUP(B62, Paste!$AB$3:$AE$2349, 3, FALSE)), "", VLOOKUP(B62, Paste!$AB$3:$AE$2349, 3, FALSE)) -> 217 | P62: =IF(ISERROR(VLOOKUP(B62, Paste!$AB$3:$AC$2343, 2, FALSE)), "", VLOOKUP(B62, Paste!$AB$3:$AC$2343, 2, FALSE)) -> 29 | Q62: =IF(ISERROR(VLOOKUP(B62, Paste!$AB$3:$AE$2349, 4, FALSE)), "", VLOOKUP(B62, Paste!$AB$3:$AE$2349, 4, FALSE)) -> 263 | R62: =IF(ISERROR(VLOOKUP(B62, Paste!$N$3:$N$250, 1, FALSE)), "", VLOOKUP(B62, Paste!$N$3:$O$250, 2, FALSE)) | S62: =VLOOKUP($B62, Paste!$W$3:$Z$10064, IF($H$4="Cap Hit",3, IF($H$4="AAV", 4, 2)), FALSE) -> 8.205714 | T62: =IF(ISERROR(VLOOKUP(B62, Paste!$Q$3:$Q$245, 1, FALSE)), "", VLOOKUP(B62, Paste!$Q$3:$R$245, 2, FALSE)) -> Y | U62: =IF(VLOOKUP(B62, 'Points&Potential'!$B$7:$O$943, 14, FALSE)=0, "", VLOOKUP(B62, 'Points&Potential'!$B$7:$O$943, 14, FALSE)) | V62: =IF(ISERROR(VLOOKUP(B62, Paste!$T$3:$T$1045, 1, FALSE)), "", VLOOKUP(B62, Paste!$T$3:$U$1144, 2, FALSE))
A63: 57 | B63: Nikolaj Ehlers | C63: =VLOOKUP(B63, Paste!$AG$3:$AH$2083, 2, FALSE) -> 30.3 | D63: =VLOOKUP($B63, Paste!$A$3:$H$933, 6, FALSE) -> LW | E63: =IFERROR(VLOOKUP($B63, Paste!$J$3:$L$933, 3, FALSE), "") -> 73 | F63: =IFERROR(VLOOKUP($B63, Paste!$J$3:$L$933, 2, FALSE), "") -> 83 | G63: =VLOOKUP($B63, Paste!$A$3:$H$933, 8, FALSE) -> CAR | H63: =VLOOKUP($B63, Paste!$A$3:$H$933, 2, FALSE) -> 81 | I63: =VLOOKUP($B63, Paste!$A$3:$H$933, 3, FALSE) -> 26.73 | J63: =K63-I63 -> 45.354735 | K63: =VLOOKUP($B63, Paste!$A$3:$H$933, 4, FALSE) -> 72.084735 | L63: =IF(ISBLANK(VLOOKUP(B63, 'SOG&PlusMinus'!$B$7:$E$912, 3, FALSE)), "", VLOOKUP(B63,'SOG&PlusMinus'!$B$7:$E$912, 3, FALSE)) -> B | M63: =IF(ISBLANK(VLOOKUP(B63, 'SOG&PlusMinus'!$B$7:$E$912, 4, FALSE)), "", VLOOKUP(B63, 'SOG&PlusMinus'!$B$7:$E$912, 4, FALSE)) -> 1 | N63: =VLOOKUP($B63, Paste!$A$3:$H$933, 5, FALSE) -> 20.858369 | O63: =IF(ISERROR(VLOOKUP(B63, Paste!$AB$3:$AE$2349, 3, FALSE)), "", VLOOKUP(B63, Paste!$AB$3:$AE$2349, 3, FALSE)) -> 24 | P63: =IF(ISERROR(VLOOKUP(B63, Paste!$AB$3:$AC$2343, 2, FALSE)), "", VLOOKUP(B63, Paste!$AB$3:$AC$2343, 2, FALSE)) -> 24 | Q63: =IF(ISERROR(VLOOKUP(B63, Paste!$AB$3:$AE$2349, 4, FALSE)), "", VLOOKUP(B63, Paste!$AB$3:$AE$2349, 4, FALSE)) -> 194 | R63: =IF(ISERROR(VLOOKUP(B63, Paste!$N$3:$N$250, 1, FALSE)), "", VLOOKUP(B63, Paste!$N$3:$O$250, 2, FALSE)) | S63: =VLOOKUP($B63, Paste!$W$3:$Z$10064, IF($H$4="Cap Hit",3, IF($H$4="AAV", 4, 2)), FALSE) -> 8.5 | T63: =IF(ISERROR(VLOOKUP(B63, Paste!$Q$3:$Q$245, 1, FALSE)), "", VLOOKUP(B63, Paste!$Q$3:$R$245, 2, FALSE)) | U63: =IF(VLOOKUP(B63, 'Points&Potential'!$B$7:$O$943, 14, FALSE)=0, "", VLOOKUP(B63, 'Points&Potential'!$B$7:$O$943, 14, FALSE)) | V63: =IF(ISERROR(VLOOKUP(B63, Paste!$T$3:$T$1045, 1, FALSE)), "", VLOOKUP(B63, Paste!$T$3:$U$1144, 2, FALSE))
A64: 58 | B64: Gabriel Vilardi | C64: =VLOOKUP(B64, Paste!$AG$3:$AH$2083, 2, FALSE) -> 26.8 | D64: =VLOOKUP($B64, Paste!$A$3:$H$933, 6, FALSE) -> RW | E64: =IFERROR(VLOOKUP($B64, Paste!$J$3:$L$933, 3, FALSE), "") -> 68 | F64: =IFERROR(VLOOKUP($B64, Paste!$J$3:$L$933, 2, FALSE), "") -> 80 | G64: =VLOOKUP($B64, Paste!$A$3:$H$933, 8, FALSE) -> WPG | H64: =VLOOKUP($B64, Paste!$A$3:$H$933, 2, FALSE) -> 75 | I64: =VLOOKUP($B64, Paste!$A$3:$H$933, 3, FALSE) -> 28.890596 | J64: =K64-I64 -> 42.748763 | K64: =VLOOKUP($B64, Paste!$A$3:$H$933, 4, FALSE) -> 71.639359 | L64: =IF(ISBLANK(VLOOKUP(B64, 'SOG&PlusMinus'!$B$7:$E$912, 3, FALSE)), "", VLOOKUP(B64,'SOG&PlusMinus'!$B$7:$E$912, 3, FALSE)) -> D | M64: =IF(ISBLANK(VLOOKUP(B64, 'SOG&PlusMinus'!$B$7:$E$912, 4, FALSE)), "", VLOOKUP(B64, 'SOG&PlusMinus'!$B$7:$E$912, 4, FALSE)) -> 1 | N64: =VLOOKUP($B64, Paste!$A$3:$H$933, 5, FALSE) -> 19.5 | O64: =IF(ISERROR(VLOOKUP(B64, Paste!$AB$3:$AE$2349, 3, FALSE)), "", VLOOKUP(B64, Paste!$AB$3:$AE$2349, 3, FALSE)) -> 23 | P64: =IF(ISERROR(VLOOKUP(B64, Paste!$AB$3:$AC$2343, 2, FALSE)), "", VLOOKUP(B64, Paste!$AB$3:$AC$2343, 2, FALSE)) -> 38 | Q64: =IF(ISERROR(VLOOKUP(B64, Paste!$AB$3:$AE$2349, 4, FALSE)), "", VLOOKUP(B64, Paste!$AB$3:$AE$2349, 4, FALSE)) -> 143 | R64: =IF(ISERROR(VLOOKUP(B64, Paste!$N$3:$N$250, 1, FALSE)), "", VLOOKUP(B64, Paste!$N$3:$O$250, 2, FALSE)) | S64: =VLOOKUP($B64, Paste!$W$3:$Z$10064, IF($H$4="Cap Hit",3, IF($H$4="AAV", 4, 2)), FALSE) -> 7.5 | T64: =IF(ISERROR(VLOOKUP(B64, Paste!$Q$3:$Q$245, 1, FALSE)), "", VLOOKUP(B64, Paste!$Q$3:$R$245, 2, FALSE)) -> Y | U64: =IF(VLOOKUP(B64, 'Points&Potential'!$B$7:$O$943, 14, FALSE)=0, "", VLOOKUP(B64, 'Points&Potential'!$B$7:$O$943, 14, FALSE)) | V64: =IF(ISERROR(VLOOKUP(B64, Paste!$T$3:$T$1045, 1, FALSE)), "", VLOOKUP(B64, Paste!$T$3:$U$1144, 2, FALSE))
A65: 59 | B65: Alexis Lafreniere | C65: =VLOOKUP(B65, Paste!$AG$3:$AH$2083, 2, FALSE) -> 24.7 | D65: =VLOOKUP($B65, Paste!$A$3:$H$933, 6, FALSE) -> RW | E65: =IFERROR(VLOOKUP($B65, Paste!$J$3:$L$933, 3, FALSE), "") -> 70 | F65: =IFERROR(VLOOKUP($B65, Paste!$J$3:$L$933, 2, FALSE), "") -> 85 | G65: =VLOOKUP($B65, Paste!$A$3:$H$933, 8, FALSE) -> NYR | H65: =VLOOKUP($B65, Paste!$A$3:$H$933, 2, FALSE) -> 84 | I65: =VLOOKUP($B65, Paste!$A$3:$H$933, 3, FALSE) -> 33.6 | J65: =K65-I65 -> 38.01784 | K65: =VLOOKUP($B65, Paste!$A$3:$H$933, 4, FALSE) -> 71.61784 | L65: =IF(ISBLANK(VLOOKUP(B65, 'SOG&PlusMinus'!$B$7:$E$912, 3, FALSE)), "", VLOOKUP(B65,'SOG&PlusMinus'!$B$7:$E$912, 3, FALSE)) -> C | M65: =IF(ISBLANK(VLOOKUP(B65, 'SOG&PlusMinus'!$B$7:$E$912, 4, FALSE)), "", VLOOKUP(B65, 'SOG&PlusMinus'!$B$7:$E$912, 4, FALSE)) -> 1 | N65: =VLOOKUP($B65, Paste!$A$3:$H$933, 5, FALSE) -> 33.463415 | O65: =IF(ISERROR(VLOOKUP(B65, Paste!$AB$3:$AE$2349, 3, FALSE)), "", VLOOKUP(B65, Paste!$AB$3:$AE$2349, 3, FALSE)) -> 94 | P65: =IF(ISERROR(VLOOKUP(B65, Paste!$AB$3:$AC$2343, 2, FALSE)), "", VLOOKUP(B65, Paste!$AB$3:$AC$2343, 2, FALSE)) -> 42 | Q65: =IF(ISERROR(VLOOKUP(B65, Paste!$AB$3:$AE$2349, 4, FALSE)), "", VLOOKUP(B65, Paste!$AB$3:$AE$2349, 4, FALSE)) -> 218 | R65: =IF(ISERROR(VLOOKUP(B65, Paste!$N$3:$N$250, 1, FALSE)), "", VLOOKUP(B65, Paste!$N$3:$O$250, 2, FALSE)) -> 80 | S65: =VLOOKUP($B65, Paste!$W$3:$Z$10064, IF($H$4="Cap Hit",3, IF($H$4="AAV", 4, 2)), FALSE) -> 7.45 | T65: =IF(ISERROR(VLOOKUP(B65, Paste!$Q$3:$Q$245, 1, FALSE)), "", VLOOKUP(B65, Paste!$Q$3:$R$245, 2, FALSE)) | U65: =IF(VLOOKUP(B65, 'Points&Potential'!$B$7:$O$943, 14, FALSE)=0, "", VLOOKUP(B65, 'Points&Potential'!$B$7:$O$943, 14, FALSE)) | V65: =IF(ISERROR(VLOOKUP(B65, Paste!$T$3:$T$1045, 1, FALSE)), "", VLOOKUP(B65, Paste!$T$3:$U$1144, 2, FALSE))
A66: 60 | B66: Dylan Larkin | C66: =VLOOKUP(B66, Paste!$AG$3:$AH$2083, 2, FALSE) -> 29.9 | D66: =VLOOKUP($B66, Paste!$A$3:$H$933, 6, FALSE) -> C | E66: =IFERROR(VLOOKUP($B66, Paste!$J$3:$L$933, 3, FALSE), "") -> 75 | F66: =IFERROR(VLOOKUP($B66, Paste!$J$3:$L$933, 2, FALSE), "") -> 85 | G66: =VLOOKUP($B66, Paste!$A$3:$H$933, 8, FALSE) -> DET | H66: =VLOOKUP($B66, Paste!$A$3:$H$933, 2, FALSE) -> 77 | I66: =VLOOKUP($B66, Paste!$A$3:$H$933, 3, FALSE) -> 33.239642 | J66: =K66-I66 -> 38.324892 | K66: =VLOOKUP($B66, Paste!$A$3:$H$933, 4, FALSE) -> 71.564535 | L66: =IF(ISBLANK(VLOOKUP(B66, 'SOG&PlusMinus'!$B$7:$E$912, 3, FALSE)), "", VLOOKUP(B66,'SOG&PlusMinus'!$B$7:$E$912, 3, FALSE)) -> C | M66: =IF(ISBLANK(VLOOKUP(B66, 'SOG&PlusMinus'!$B$7:$E$912, 4, FALSE)), "", VLOOKUP(B66, 'SOG&PlusMinus'!$B$7:$E$912, 4, FALSE)) -> 1 | N66: =VLOOKUP($B66, Paste!$A$3:$H$933, 5, FALSE) -> 43.65625 | O66: =IF(ISERROR(VLOOKUP(B66, Paste!$AB$3:$AE$2349, 3, FALSE)), "", VLOOKUP(B66, Paste!$AB$3:$AE$2349, 3, FALSE)) -> 46 | P66: =IF(ISERROR(VLOOKUP(B66, Paste!$AB$3:$AC$2343, 2, FALSE)), "", VLOOKUP(B66, Paste!$AB$3:$AC$2343, 2, FALSE)) -> 35 | Q66: =IF(ISERROR(VLOOKUP(B66, Paste!$AB$3:$AE$2349, 4, FALSE)), "", VLOOKUP(B66, Paste!$AB$3:$AE$2349, 4, FALSE)) -> 239 | R66: =IF(ISERROR(VLOOKUP(B66, Paste!$N$3:$N$250, 1, FALSE)), "", VLOOKUP(B66, Paste!$N$3:$O$250, 2, FALSE)) | S66: =VLOOKUP($B66, Paste!$W$3:$Z$10064, IF($H$4="Cap Hit",3, IF($H$4="AAV", 4, 2)), FALSE) -> 8.7 | T66: =IF(ISERROR(VLOOKUP(B66, Paste!$Q$3:$Q$245, 1, FALSE)), "", VLOOKUP(B66, Paste!$Q$3:$R$245, 2, FALSE)) | U66: =IF(VLOOKUP(B66, 'Points&Potential'!$B$7:$O$943, 14, FALSE)=0, "", VLOOKUP(B66, 'Points&Potential'!$B$7:$O$943, 14, FALSE)) | V66: =IF(ISERROR(VLOOKUP(B66, Paste!$T$3:$T$1045, 1, FALSE)), "", VLOOKUP(B66, Paste!$T$3:$U$1144, 2, FALSE))
A67: 61 | B67: Dylan Strome | C67: =VLOOKUP(B67, Paste!$AG$3:$AH$2083, 2, FALSE) -> 29.3 | D67: =VLOOKUP($B67, Paste!$A$3:$H$933, 6, FALSE) -> C | E67: =IFERROR(VLOOKUP($B67, Paste!$J$3:$L$933, 3, FALSE), "") -> 67 | F67: =IFERROR(VLOOKUP($B67, Paste!$J$3:$L$933, 2, FALSE), "") -> 85 | G67: =VLOOKUP($B67, Paste!$A$3:$H$933, 8, FALSE) -> WAS | H67: =VLOOKUP($B67, Paste!$A$3:$H$933, 2, FALSE) -> 83.333333 | I67: =VLOOKUP($B67, Paste!$A$3:$H$933, 3, FALSE) -> 24.956373 | J67: =K67-I67 -> 46.086908 | K67: =VLOOKUP($B67, Paste!$A$3:$H$933, 4, FALSE) -> 71.043281 | L67: =IF(ISBLANK(VLOOKUP(B67, 'SOG&PlusMinus'!$B$7:$E$912, 3, FALSE)), "", VLOOKUP(B67,'SOG&PlusMinus'!$B$7:$E$912, 3, FALSE)) -> C | M67: =IF(ISBLANK(VLOOKUP(B67, 'SOG&PlusMinus'!$B$7:$E$912, 4, FALSE)), "", VLOOKUP(B67, 'SOG&PlusMinus'!$B$7:$E$912, 4, FALSE)) -> 1 | N67: =VLOOKUP($B67, Paste!$A$3:$H$933, 5, FALSE) -> 34.836066 | O67: =IF(ISERROR(VLOOKUP(B67, Paste!$AB$3:$AE$2349, 3, FALSE)), "", VLOOKUP(B67, Paste!$AB$3:$AE$2349, 3, FALSE)) -> 15 | P67: =IF(ISERROR(VLOOKUP(B67, Paste!$AB$3:$AC$2343, 2, FALSE)), "", VLOOKUP(B67, Paste!$AB$3:$AC$2343, 2, FALSE)) -> 55 | Q67: =IF(ISERROR(VLOOKUP(B67, Paste!$AB$3:$AE$2349, 4, FALSE)), "", VLOOKUP(B67, Paste!$AB$3:$AE$2349, 4, FALSE)) -> 150 | R67: =IF(ISERROR(VLOOKUP(B67, Paste!$N$3:$N$250, 1, FALSE)), "", VLOOKUP(B67, Paste!$N$3:$O$250, 2, FALSE)) | S67: =VLOOKUP($B67, Paste!$W$3:$Z$10064, IF($H$4="Cap Hit",3, IF($H$4="AAV", 4, 2)), FALSE) -> 5 | T67: =IF(ISERROR(VLOOKUP(B67, Paste!$Q$3:$Q$245, 1, FALSE)), "", VLOOKUP(B67, Paste!$Q$3:$R$245, 2, FALSE)) | U67: =IF(VLOOKUP(B67, 'Points&Potential'!$B$7:$O$943, 14, FALSE)=0, "", VLOOKUP(B67, 'Points&Potential'!$B$7:$O$943, 14, FALSE)) | V67: =IF(ISERROR(VLOOKUP(B67, Paste!$T$3:$T$1045, 1, FALSE)), "", VLOOKUP(B67, Paste!$T$3:$U$1144, 2, FALSE))
A68: 62 | B68: Nick Schmaltz | C68: =VLOOKUP(B68, Paste!$AG$3:$AH$2083, 2, FALSE) -> 30.3 | D68: =VLOOKUP($B68, Paste!$A$3:$H$933, 6, FALSE) -> RW | E68: =IFERROR(VLOOKUP($B68, Paste!$J$3:$L$933, 3, FALSE), "") -> 70 | F68: =IFERROR(VLOOKUP($B68, Paste!$J$3:$L$933, 2, FALSE), "") -> 75 | G68: =VLOOKUP($B68, Paste!$A$3:$H$933, 8, FALSE) -> UTA | H68: =VLOOKUP($B68, Paste!$A$3:$H$933, 2, FALSE) -> 83 | I68: =VLOOKUP($B68, Paste!$A$3:$H$933, 3, FALSE) -> 30.71 | J68: =K68-I68 -> 40.250642 | K68: =VLOOKUP($B68, Paste!$A$3:$H$933, 4, FALSE) -> 70.960642 | L68: =IF(ISBLANK(VLOOKUP(B68, 'SOG&PlusMinus'!$B$7:$E$912, 3, FALSE)), "", VLOOKUP(B68,'SOG&PlusMinus'!$B$7:$E$912, 3, FALSE)) -> A | M68: =IF(ISBLANK(VLOOKUP(B68, 'SOG&PlusMinus'!$B$7:$E$912, 4, FALSE)), "", VLOOKUP(B68, 'SOG&PlusMinus'!$B$7:$E$912, 4, FALSE)) -> 1 | N68: =VLOOKUP($B68, Paste!$A$3:$H$933, 5, FALSE) -> 17.761317 | O68: =IF(ISERROR(VLOOKUP(B68, Paste!$AB$3:$AE$2349, 3, FALSE)), "", VLOOKUP(B68, Paste!$AB$3:$AE$2349, 3, FALSE)) -> 18 | P68: =IF(ISERROR(VLOOKUP(B68, Paste!$AB$3:$AC$2343, 2, FALSE)), "", VLOOKUP(B68, Paste!$AB$3:$AC$2343, 2, FALSE)) -> 46 | Q68: =IF(ISERROR(VLOOKUP(B68, Paste!$AB$3:$AE$2349, 4, FALSE)), "", VLOOKUP(B68, Paste!$AB$3:$AE$2349, 4, FALSE)) -> 191 | R68: =IF(ISERROR(VLOOKUP(B68, Paste!$N$3:$N$250, 1, FALSE)), "", VLOOKUP(B68, Paste!$N$3:$O$250, 2, FALSE)) | S68: =VLOOKUP($B68, Paste!$W$3:$Z$10064, IF($H$4="Cap Hit",3, IF($H$4="AAV", 4, 2)), FALSE) -> 8 | T68: =IF(ISERROR(VLOOKUP(B68, Paste!$Q$3:$Q$245, 1, FALSE)), "", VLOOKUP(B68, Paste!$Q$3:$R$245, 2, FALSE)) | U68: =IF(VLOOKUP(B68, 'Points&Potential'!$B$7:$O$943, 14, FALSE)=0, "", VLOOKUP(B68, 'Points&Potential'!$B$7:$O$943, 14, FALSE)) | V68: =IF(ISERROR(VLOOKUP(B68, Paste!$T$3:$T$1045, 1, FALSE)), "", VLOOKUP(B68, Paste!$T$3:$U$1144, 2, FALSE))
A69: 63 | B69: Travis Konecny | C69: =VLOOKUP(B69, Paste!$AG$3:$AH$2083, 2, FALSE) -> 29.3 | D69: =VLOOKUP($B69, Paste!$A$3:$H$933, 6, FALSE) -> RW | E69: =IFERROR(VLOOKUP($B69, Paste!$J$3:$L$933, 3, FALSE), "") -> 80 | F69: =IFERROR(VLOOKUP($B69, Paste!$J$3:$L$933, 2, FALSE), "") -> 90 | G69: =VLOOKUP($B69, Paste!$A$3:$H$933, 8, FALSE) -> PHI | H69: =VLOOKUP($B69, Paste!$A$3:$H$933, 2, FALSE) -> 80.333333 | I69: =VLOOKUP($B69, Paste!$A$3:$H$933, 3, FALSE) -> 27.11374 | J69: =K69-I69 -> 43.319057 | K69: =VLOOKUP($B69, Paste!$A$3:$H$933, 4, FALSE) -> 70.432797 | L69: =IF(ISBLANK(VLOOKUP(B69, 'SOG&PlusMinus'!$B$7:$E$912, 3, FALSE)), "", VLOOKUP(B69,'SOG&PlusMinus'!$B$7:$E$912, 3, FALSE)) -> B | M69: =IF(ISBLANK(VLOOKUP(B69, 'SOG&PlusMinus'!$B$7:$E$912, 4, FALSE)), "", VLOOKUP(B69, 'SOG&PlusMinus'!$B$7:$E$912, 4, FALSE)) -> 1 | N69: =VLOOKUP($B69, Paste!$A$3:$H$933, 5, FALSE) -> 61.190071 | O69: =IF(ISERROR(VLOOKUP(B69, Paste!$AB$3:$AE$2349, 3, FALSE)), "", VLOOKUP(B69, Paste!$AB$3:$AE$2349, 3, FALSE)) -> 100 | P69: =IF(ISERROR(VLOOKUP(B69, Paste!$AB$3:$AC$2343, 2, FALSE)), "", VLOOKUP(B69, Paste!$AB$3:$AC$2343, 2, FALSE)) -> 40 | Q69: =IF(ISERROR(VLOOKUP(B69, Paste!$AB$3:$AE$2349, 4, FALSE)), "", VLOOKUP(B69, Paste!$AB$3:$AE$2349, 4, FALSE)) -> 185 | R69: =IF(ISERROR(VLOOKUP(B69, Paste!$N$3:$N$250, 1, FALSE)), "", VLOOKUP(B69, Paste!$N$3:$O$250, 2, FALSE)) | S69: =VLOOKUP($B69, Paste!$W$3:$Z$10064, IF($H$4="Cap Hit",3, IF($H$4="AAV", 4, 2)), FALSE) -> 8.75 | T69: =IF(ISERROR(VLOOKUP(B69, Paste!$Q$3:$Q$245, 1, FALSE)), "", VLOOKUP(B69, Paste!$Q$3:$R$245, 2, FALSE)) | U69: =IF(VLOOKUP(B69, 'Points&Potential'!$B$7:$O$943, 14, FALSE)=0, "", VLOOKUP(B69, 'Points&Potential'!$B$7:$O$943, 14, FALSE)) | V69: =IF(ISERROR(VLOOKUP(B69, Paste!$T$3:$T$1045, 1, FALSE)), "", VLOOKUP(B69, Paste!$T$3:$U$1144, 2, FALSE))
A70: 64 | B70: Andrei Svechnikov | C70: =VLOOKUP(B70, Paste!$AG$3:$AH$2083, 2, FALSE) -> 26.2 | D70: =VLOOKUP($B70, Paste!$A$3:$H$933, 6, FALSE) -> LW | E70: =IFERROR(VLOOKUP($B70, Paste!$J$3:$L$933, 3, FALSE), "") -> 73 | F70: =IFERROR(VLOOKUP($B70, Paste!$J$3:$L$933, 2, FALSE), "") -> 85 | G70: =VLOOKUP($B70, Paste!$A$3:$H$933, 8, FALSE) -> CAR | H70: =VLOOKUP($B70, Paste!$A$3:$H$933, 2, FALSE) -> 77 | I70: =VLOOKUP($B70, Paste!$A$3:$H$933, 3, FALSE) -> 30.8 | J70: =K70-I70 -> 39.524734 | K70: =VLOOKUP($B70, Paste!$A$3:$H$933, 4, FALSE) -> 70.324734 | L70: =IF(ISBLANK(VLOOKUP(B70, 'SOG&PlusMinus'!$B$7:$E$912, 3, FALSE)), "", VLOOKUP(B70,'SOG&PlusMinus'!$B$7:$E$912, 3, FALSE)) -> C | M70: =IF(ISBLANK(VLOOKUP(B70, 'SOG&PlusMinus'!$B$7:$E$912, 4, FALSE)), "", VLOOKUP(B70, 'SOG&PlusMinus'!$B$7:$E$912, 4, FALSE)) -> 1 | N70: =VLOOKUP($B70, Paste!$A$3:$H$933, 5, FALSE) -> 67.1 | O70: =IF(ISERROR(VLOOKUP(B70, Paste!$AB$3:$AE$2349, 3, FALSE)), "", VLOOKUP(B70, Paste!$AB$3:$AE$2349, 3, FALSE)) -> 159 | P70: =IF(ISERROR(VLOOKUP(B70, Paste!$AB$3:$AC$2343, 2, FALSE)), "", VLOOKUP(B70, Paste!$AB$3:$AC$2343, 2, FALSE)) -> 23 | Q70: =IF(ISERROR(VLOOKUP(B70, Paste!$AB$3:$AE$2349, 4, FALSE)), "", VLOOKUP(B70, Paste!$AB$3:$AE$2349, 4, FALSE)) -> 200 | R70: =IF(ISERROR(VLOOKUP(B70, Paste!$N$3:$N$250, 1, FALSE)), "", VLOOKUP(B70, Paste!$N$3:$O$250, 2, FALSE)) | S70: =VLOOKUP($B70, Paste!$W$3:$Z$10064, IF($H$4="Cap Hit",3, IF($H$4="AAV", 4, 2)), FALSE) -> 7.75 | T70: =IF(ISERROR(VLOOKUP(B70, Paste!$Q$3:$Q$245, 1, FALSE)), "", VLOOKUP(B70, Paste!$Q$3:$R$245, 2, FALSE)) -> Y | U70: =IF(VLOOKUP(B70, 'Points&Potential'!$B$7:$O$943, 14, FALSE)=0, "", VLOOKUP(B70, 'Points&Potential'!$B$7:$O$943, 14, FALSE)) | V70: =IF(ISERROR(VLOOKUP(B70, Paste!$T$3:$T$1045, 1, FALSE)), "", VLOOKUP(B70, Paste!$T$3:$U$1144, 2, FALSE))
... A99: 93 | B99: Matthew Schaefer | C99: =VLOOKUP(B99, Paste!$AG$3:$AH$2083, 2, FALSE) -> 18.8 | D99: =VLOOKUP($B99, Paste!$A$3:$H$933, 6, FALSE) -> LD | E99: =IFERROR(VLOOKUP($B99, Paste!$J$3:$L$933, 3, FALSE), "") -> 70 | F99: =IFERROR(VLOOKUP($B99, Paste!$J$3:$L$933, 2, FALSE), "") -> 82 | G99: =VLOOKUP($B99, Paste!$A$3:$H$933, 8, FALSE) -> NYI | H99: =VLOOKUP($B99, Paste!$A$3:$H$933, 2, FALSE) -> 84 | I99: =VLOOKUP($B99, Paste!$A$3:$H$933, 3, FALSE) -> 23.071307 | J99: =K99-I99 -> 38.717614 | K99: =VLOOKUP($B99, Paste!$A$3:$H$933, 4, FALSE) -> 61.78892 | L99: =IF(ISBLANK(VLOOKUP(B99, 'SOG&PlusMinus'!$B$7:$E$912, 3, FALSE)), "", VLOOKUP(B99,'SOG&PlusMinus'!$B$7:$E$912, 3, FALSE)) -> A | M99: =IF(ISBLANK(VLOOKUP(B99, 'SOG&PlusMinus'!$B$7:$E$912, 4, FALSE)), "", VLOOKUP(B99, 'SOG&PlusMinus'!$B$7:$E$912, 4, FALSE)) -> 1 | N99: =VLOOKUP($B99, Paste!$A$3:$H$933, 5, FALSE) -> 42 | O99: =IF(ISERROR(VLOOKUP(B99, Paste!$AB$3:$AE$2349, 3, FALSE)), "", VLOOKUP(B99, Paste!$AB$3:$AE$2349, 3, FALSE)) -> 45 | P99: =IF(ISERROR(VLOOKUP(B99, Paste!$AB$3:$AC$2343, 2, FALSE)), "", VLOOKUP(B99, Paste!$AB$3:$AC$2343, 2, FALSE)) -> 119 | Q99: =IF(ISERROR(VLOOKUP(B99, Paste!$AB$3:$AE$2349, 4, FALSE)), "", VLOOKUP(B99, Paste!$AB$3:$AE$2349, 4, FALSE)) -> 235 | R99: =IF(ISERROR(VLOOKUP(B99, Paste!$N$3:$N$250, 1, FALSE)), "", VLOOKUP(B99, Paste!$N$3:$O$250, 2, FALSE)) | S99: =VLOOKUP($B99, Paste!$W$3:$Z$10064, IF($H$4="Cap Hit",3, IF($H$4="AAV", 4, 2)), FALSE) -> 4.475 | T99: =IF(ISERROR(VLOOKUP(B99, Paste!$Q$3:$Q$245, 1, FALSE)), "", VLOOKUP(B99, Paste!$Q$3:$R$245, 2, FALSE)) | U99: =IF(VLOOKUP(B99, 'Points&Potential'!$B$7:$O$943, 14, FALSE)=0, "", VLOOKUP(B99, 'Points&Potential'!$B$7:$O$943, 14, FALSE)) | V99: =IF(ISERROR(VLOOKUP(B99, Paste!$T$3:$T$1045, 1, FALSE)), "", VLOOKUP(B99, Paste!$T$3:$U$1144, 2, FALSE))
A100: 94 | B100: Bo Horvat | C100: =VLOOKUP(B100, Paste!$AG$3:$AH$2083, 2, FALSE) -> 31.2 | D100: =VLOOKUP($B100, Paste!$A$3:$H$933, 6, FALSE) -> C | E100: =IFERROR(VLOOKUP($B100, Paste!$J$3:$L$933, 3, FALSE), "") -> 63 | F100: =IFERROR(VLOOKUP($B100, Paste!$J$3:$L$933, 2, FALSE), "") -> 78 | G100: =VLOOKUP($B100, Paste!$A$3:$H$933, 8, FALSE) -> NYI | H100: =VLOOKUP($B100, Paste!$A$3:$H$933, 2, FALSE) -> 78.666667 | I100: =VLOOKUP($B100, Paste!$A$3:$H$933, 3, FALSE) -> 32.061813 | J100: =K100-I100 -> 29.691741 | K100: =VLOOKUP($B100, Paste!$A$3:$H$933, 4, FALSE) -> 61.753555 | L100: =IF(ISBLANK(VLOOKUP(B100, 'SOG&PlusMinus'!$B$7:$E$912, 3, FALSE)), "", VLOOKUP(B100,'SOG&PlusMinus'!$B$7:$E$912, 3, FALSE)) -> B | M100: =IF(ISBLANK(VLOOKUP(B100, 'SOG&PlusMinus'!$B$7:$E$912, 4, FALSE)), "", VLOOKUP(B100, 'SOG&PlusMinus'!$B$7:$E$912, 4, FALSE)) -> 1 | N100: =VLOOKUP($B100, Paste!$A$3:$H$933, 5, FALSE) -> 32.492754 | O100: =IF(ISERROR(VLOOKUP(B100, Paste!$AB$3:$AE$2349, 3, FALSE)), "", VLOOKUP(B100, Paste!$AB$3:$AE$2349, 3, FALSE)) -> 59 | P100: =IF(ISERROR(VLOOKUP(B100, Paste!$AB$3:$AC$2343, 2, FALSE)), "", VLOOKUP(B100, Paste!$AB$3:$AC$2343, 2, FALSE)) -> 41 | Q100: =IF(ISERROR(VLOOKUP(B100, Paste!$AB$3:$AE$2349, 4, FALSE)), "", VLOOKUP(B100, Paste!$AB$3:$AE$2349, 4, FALSE)) -> 244 | R100: =IF(ISERROR(VLOOKUP(B100, Paste!$N$3:$N$250, 1, FALSE)), "", VLOOKUP(B100, Paste!$N$3:$O$250, 2, FALSE)) | S100: =VLOOKUP($B100, Paste!$W$3:$Z$10064, IF($H$4="Cap Hit",3, IF($H$4="AAV", 4, 2)), FALSE) -> 8.5 | U100: =IF(VLOOKUP(B100, 'Points&Potential'!$B$7:$O$943, 14, FALSE)=0, "", VLOOKUP(B100, 'Points&Potential'!$B$7:$O$943, 14, FALSE)) | V100: =IF(ISERROR(VLOOKUP(B100, Paste!$T$3:$T$1045, 1, FALSE)), "", VLOOKUP(B100, Paste!$T$3:$U$1144, 2, FALSE))
A101: 95 | B101: Jake Sanderson | C101: =VLOOKUP(B101, Paste!$AG$3:$AH$2083, 2, FALSE) -> 23.9 | D101: =VLOOKUP($B101, Paste!$A$3:$H$933, 6, FALSE) -> LD | E101: =IFERROR(VLOOKUP($B101, Paste!$J$3:$L$933, 3, FALSE), "") -> 65 | F101: =IFERROR(VLOOKUP($B101, Paste!$J$3:$L$933, 2, FALSE), "") -> 75 | G101: =VLOOKUP($B101, Paste!$A$3:$H$933, 8, FALSE) -> OTT | H101: =VLOOKUP($B101, Paste!$A$3:$H$933, 2, FALSE) -> 78 | I101: =VLOOKUP($B101, Paste!$A$3:$H$933, 3, FALSE) -> 12.540464 | J101: =K101-I101 -> 48.79164 | K101: =VLOOKUP($B101, Paste!$A$3:$H$933, 4, FALSE) -> 61.332104 | L101: =IF(ISBLANK(VLOOKUP(B101, 'SOG&PlusMinus'!$B$7:$E$912, 3, FALSE)), "", VLOOKUP(B101,'SOG&PlusMinus'!$B$7:$E$912, 3, FALSE)) -> A | M101: =IF(ISBLANK(VLOOKUP(B101, 'SOG&PlusMinus'!$B$7:$E$912, 4, FALSE)), "", VLOOKUP(B101, 'SOG&PlusMinus'!$B$7:$E$912, 4, FALSE)) -> 1 | N101: =VLOOKUP($B101, Paste!$A$3:$H$933, 5, FALSE) -> 14.04 | O101: =IF(ISERROR(VLOOKUP(B101, Paste!$AB$3:$AE$2349, 3, FALSE)), "", VLOOKUP(B101, Paste!$AB$3:$AE$2349, 3, FALSE)) -> 37 | P101: =IF(ISERROR(VLOOKUP(B101, Paste!$AB$3:$AC$2343, 2, FALSE)), "", VLOOKUP(B101, Paste!$AB$3:$AC$2343, 2, FALSE)) -> 154 | Q101: =IF(ISERROR(VLOOKUP(B101, Paste!$AB$3:$AE$2349, 4, FALSE)), "", VLOOKUP(B101, Paste!$AB$3:$AE$2349, 4, FALSE)) -> 179 | R101: =IF(ISERROR(VLOOKUP(B101, Paste!$N$3:$N$250, 1, FALSE)), "", VLOOKUP(B101, Paste!$N$3:$O$250, 2, FALSE)) | S101: =VLOOKUP($B101, Paste!$W$3:$Z$10064, IF($H$4="Cap Hit",3, IF($H$4="AAV", 4, 2)), FALSE) -> 8.05 | T101: =IF(ISERROR(VLOOKUP(B101, Paste!$Q$3:$Q$245, 1, FALSE)), "", VLOOKUP(B101, Paste!$Q$3:$R$245, 2, FALSE)) | U101: =IF(VLOOKUP(B101, 'Points&Potential'!$B$7:$O$943, 14, FALSE)=0, "", VLOOKUP(B101, 'Points&Potential'!$B$7:$O$943, 14, FALSE)) | V101: =IF(ISERROR(VLOOKUP(B101, Paste!$T$3:$T$1045, 1, FALSE)), "", VLOOKUP(B101, Paste!$T$3:$U$1144, 2, FALSE))
A102: 96 | B102: Jared McCann | C102: =VLOOKUP(B102, Paste!$AG$3:$AH$2083, 2, FALSE) -> 30 | D102: =VLOOKUP($B102, Paste!$A$3:$H$933, 6, FALSE) -> LW | E102: =IFERROR(VLOOKUP($B102, Paste!$J$3:$L$933, 3, FALSE), "") -> 65 | F102: =IFERROR(VLOOKUP($B102, Paste!$J$3:$L$933, 2, FALSE), "") -> 73 | G102: =VLOOKUP($B102, Paste!$A$3:$H$933, 8, FALSE) -> SEA | H102: =VLOOKUP($B102, Paste!$A$3:$H$933, 2, FALSE) -> 76 | I102: =VLOOKUP($B102, Paste!$A$3:$H$933, 3, FALSE) -> 25.137394 | J102: =K102-I102 -> 36.093119 | K102: =VLOOKUP($B102, Paste!$A$3:$H$933, 4, FALSE) -> 61.230514 | L102: =IF(ISBLANK(VLOOKUP(B102, 'SOG&PlusMinus'!$B$7:$E$912, 3, FALSE)), "", VLOOKUP(B102,'SOG&PlusMinus'!$B$7:$E$912, 3, FALSE)) -> C | M102: =IF(ISBLANK(VLOOKUP(B102, 'SOG&PlusMinus'!$B$7:$E$912, 4, FALSE)), "", VLOOKUP(B102, 'SOG&PlusMinus'!$B$7:$E$912, 4, FALSE)) -> 1 | N102: =VLOOKUP($B102, Paste!$A$3:$H$933, 5, FALSE) -> 21.308411 | O102: =IF(ISERROR(VLOOKUP(B102, Paste!$AB$3:$AE$2349, 3, FALSE)), "", VLOOKUP(B102, Paste!$AB$3:$AE$2349, 3, FALSE)) -> 47 | P102: =IF(ISERROR(VLOOKUP(B102, Paste!$AB$3:$AC$2343, 2, FALSE)), "", VLOOKUP(B102, Paste!$AB$3:$AC$2343, 2, FALSE)) -> 37 | Q102: =IF(ISERROR(VLOOKUP(B102, Paste!$AB$3:$AE$2349, 4, FALSE)), "", VLOOKUP(B102, Paste!$AB$3:$AE$2349, 4, FALSE)) -> 182 | R102: =IF(ISERROR(VLOOKUP(B102, Paste!$N$3:$N$250, 1, FALSE)), "", VLOOKUP(B102, Paste!$N$3:$O$250, 2, FALSE)) | S102: =VLOOKUP($B102, Paste!$W$3:$Z$10064, IF($H$4="Cap Hit",3, IF($H$4="AAV", 4, 2)), FALSE) -> 5 | T102: =IF(ISERROR(VLOOKUP(B102, Paste!$Q$3:$Q$245, 1, FALSE)), "", VLOOKUP(B102, Paste!$Q$3:$R$245, 2, FALSE)) | U102: =IF(VLOOKUP(B102, 'Points&Potential'!$B$7:$O$943, 14, FALSE)=0, "", VLOOKUP(B102, 'Points&Potential'!$B$7:$O$943, 14, FALSE)) | V102: =IF(ISERROR(VLOOKUP(B102, Paste!$T$3:$T$1045, 1, FALSE)), "", VLOOKUP(B102, Paste!$T$3:$U$1144, 2, FALSE))
A103: 97 | B103: Shea Theodore | C103: =VLOOKUP(B103, Paste!$AG$3:$AH$2083, 2, FALSE) -> 30.9 | D103: =VLOOKUP($B103, Paste!$A$3:$H$933, 6, FALSE) -> LD | E103: =IFERROR(VLOOKUP($B103, Paste!$J$3:$L$933, 3, FALSE), "") -> 58 | F103: =IFERROR(VLOOKUP($B103, Paste!$J$3:$L$933, 2, FALSE), "") -> 75 | G103: =VLOOKUP($B103, Paste!$A$3:$H$933, 8, FALSE) -> VGK | H103: =VLOOKUP($B103, Paste!$A$3:$H$933, 2, FALSE) -> 69 | I103: =VLOOKUP($B103, Paste!$A$3:$H$933, 3, FALSE) -> 10.35 | J103: =K103-I103 -> 50.718514 | K103: =VLOOKUP($B103, Paste!$A$3:$H$933, 4, FALSE) -> 61.068514 | L103: =IF(ISBLANK(VLOOKUP(B103, 'SOG&PlusMinus'!$B$7:$E$912, 3, FALSE)), "", VLOOKUP(B103,'SOG&PlusMinus'!$B$7:$E$912, 3, FALSE)) -> A | M103: =IF(ISBLANK(VLOOKUP(B103, 'SOG&PlusMinus'!$B$7:$E$912, 4, FALSE)), "", VLOOKUP(B103, 'SOG&PlusMinus'!$B$7:$E$912, 4, FALSE)) -> 1 | N103: =VLOOKUP($B103, Paste!$A$3:$H$933, 5, FALSE) -> 21 | O103: =IF(ISERROR(VLOOKUP(B103, Paste!$AB$3:$AE$2349, 3, FALSE)), "", VLOOKUP(B103, Paste!$AB$3:$AE$2349, 3, FALSE)) -> 4 | P103: =IF(ISERROR(VLOOKUP(B103, Paste!$AB$3:$AC$2343, 2, FALSE)), "", VLOOKUP(B103, Paste!$AB$3:$AC$2343, 2, FALSE)) -> 85 | Q103: =IF(ISERROR(VLOOKUP(B103, Paste!$AB$3:$AE$2349, 4, FALSE)), "", VLOOKUP(B103, Paste!$AB$3:$AE$2349, 4, FALSE)) -> 138 | R103: =IF(ISERROR(VLOOKUP(B103, Paste!$N$3:$N$250, 1, FALSE)), "", VLOOKUP(B103, Paste!$N$3:$O$250, 2, FALSE)) -> 60 | S103: =VLOOKUP($B103, Paste!$W$3:$Z$10064, IF($H$4="Cap Hit",3, IF($H$4="AAV", 4, 2)), FALSE) -> 7.425 | T103: =IF(ISERROR(VLOOKUP(B103, Paste!$Q$3:$Q$245, 1, FALSE)), "", VLOOKUP(B103, Paste!$Q$3:$R$245, 2, FALSE)) -> Y | U103: =IF(VLOOKUP(B103, 'Points&Potential'!$B$7:$O$943, 14, FALSE)=0, "", VLOOKUP(B103, 'Points&Potential'!$B$7:$O$943, 14, FALSE)) | V103: =IF(ISERROR(VLOOKUP(B103, Paste!$T$3:$T$1045, 1, FALSE)), "", VLOOKUP(B103, Paste!$T$3:$U$1144, 2, FALSE))
A104: 98 | B104: Marco Rossi | C104: =VLOOKUP(B104, Paste!$AG$3:$AH$2083, 2, FALSE) -> 24.7 | D104: =VLOOKUP($B104, Paste!$A$3:$H$933, 6, FALSE) -> C | E104: =IFERROR(VLOOKUP($B104, Paste!$J$3:$L$933, 3, FALSE), "") -> 70 | F104: =IFERROR(VLOOKUP($B104, Paste!$J$3:$L$933, 2, FALSE), "") -> 95 | G104: =VLOOKUP($B104, Paste!$A$3:$H$933, 8, FALSE) -> VAN | H104: =VLOOKUP($B104, Paste!$A$3:$H$933, 2, FALSE) -> 79 | I104: =VLOOKUP($B104, Paste!$A$3:$H$933, 3, FALSE) -> 19.785804 | J104: =K104-I104 -> 41.189029 | K104: =VLOOKUP($B104, Paste!$A$3:$H$933, 4, FALSE) -> 60.974833 | L104: =IF(ISBLANK(VLOOKUP(B104, 'SOG&PlusMinus'!$B$7:$E$912, 3, FALSE)), "", VLOOKUP(B104,'SOG&PlusMinus'!$B$7:$E$912, 3, FALSE)) -> D | M104: =IF(ISBLANK(VLOOKUP(B104, 'SOG&PlusMinus'!$B$7:$E$912, 4, FALSE)), "", VLOOKUP(B104, 'SOG&PlusMinus'!$B$7:$E$912, 4, FALSE)) -> 1 | N104: =VLOOKUP($B104, Paste!$A$3:$H$933, 5, FALSE) -> 30.640187 | O104: =IF(ISERROR(VLOOKUP(B104, Paste!$AB$3:$AE$2349, 3, FALSE)), "", VLOOKUP(B104, Paste!$AB$3:$AE$2349, 3, FALSE)) -> 71 | P104: =IF(ISERROR(VLOOKUP(B104, Paste!$AB$3:$AC$2343, 2, FALSE)), "", VLOOKUP(B104, Paste!$AB$3:$AC$2343, 2, FALSE)) -> 43 | Q104: =IF(ISERROR(VLOOKUP(B104, Paste!$AB$3:$AE$2349, 4, FALSE)), "", VLOOKUP(B104, Paste!$AB$3:$AE$2349, 4, FALSE)) -> 126 | R104: =IF(ISERROR(VLOOKUP(B104, Paste!$N$3:$N$250, 1, FALSE)), "", VLOOKUP(B104, Paste!$N$3:$O$250, 2, FALSE)) -> 80 | S104: =VLOOKUP($B104, Paste!$W$3:$Z$10064, IF($H$4="Cap Hit",3, IF($H$4="AAV", 4, 2)), FALSE) -> 5 | T104: =IF(ISERROR(VLOOKUP(B104, Paste!$Q$3:$Q$245, 1, FALSE)), "", VLOOKUP(B104, Paste!$Q$3:$R$245, 2, FALSE)) | U104: =IF(VLOOKUP(B104, 'Points&Potential'!$B$7:$O$943, 14, FALSE)=0, "", VLOOKUP(B104, 'Points&Potential'!$B$7:$O$943, 14, FALSE)) | V104: =IF(ISERROR(VLOOKUP(B104, Paste!$T$3:$T$1045, 1, FALSE)), "", VLOOKUP(B104, Paste!$T$3:$U$1144, 2, FALSE))
A105: 99 | B105: Dylan Cozens | C105: =VLOOKUP(B105, Paste!$AG$3:$AH$2083, 2, FALSE) -> 25.3 | D105: =VLOOKUP($B105, Paste!$A$3:$H$933, 6, FALSE) -> C | E105: =IFERROR(VLOOKUP($B105, Paste!$J$3:$L$933, 3, FALSE), "") -> 65 | F105: =IFERROR(VLOOKUP($B105, Paste!$J$3:$L$933, 2, FALSE), "") -> 83 | G105: =VLOOKUP($B105, Paste!$A$3:$H$933, 8, FALSE) -> OTT | H105: =VLOOKUP($B105, Paste!$A$3:$H$933, 2, FALSE) -> 83 | I105: =VLOOKUP($B105, Paste!$A$3:$H$933, 3, FALSE) -> 24.9 | J105: =K105-I105 -> 35.932192 | K105: =VLOOKUP($B105, Paste!$A$3:$H$933, 4, FALSE) -> 60.832192 | L105: =IF(ISBLANK(VLOOKUP(B105, 'SOG&PlusMinus'!$B$7:$E$912, 3, FALSE)), "", VLOOKUP(B105,'SOG&PlusMinus'!$B$7:$E$912, 3, FALSE)) -> C | M105: =IF(ISBLANK(VLOOKUP(B105, 'SOG&PlusMinus'!$B$7:$E$912, 4, FALSE)), "", VLOOKUP(B105, 'SOG&PlusMinus'!$B$7:$E$912, 4, FALSE)) -> 1 | N105: =VLOOKUP($B105, Paste!$A$3:$H$933, 5, FALSE) -> 57.72428 | O105: =IF(ISERROR(VLOOKUP(B105, Paste!$AB$3:$AE$2349, 3, FALSE)), "", VLOOKUP(B105, Paste!$AB$3:$AE$2349, 3, FALSE)) -> 208 | P105: =IF(ISERROR(VLOOKUP(B105, Paste!$AB$3:$AC$2343, 2, FALSE)), "", VLOOKUP(B105, Paste!$AB$3:$AC$2343, 2, FALSE)) -> 29 | Q105: =IF(ISERROR(VLOOKUP(B105, Paste!$AB$3:$AE$2349, 4, FALSE)), "", VLOOKUP(B105, Paste!$AB$3:$AE$2349, 4, FALSE)) -> 199 | R105: =IF(ISERROR(VLOOKUP(B105, Paste!$N$3:$N$250, 1, FALSE)), "", VLOOKUP(B105, Paste!$N$3:$O$250, 2, FALSE)) | S105: =VLOOKUP($B105, Paste!$W$3:$Z$10064, IF($H$4="Cap Hit",3, IF($H$4="AAV", 4, 2)), FALSE) -> 7.1 | T105: =IF(ISERROR(VLOOKUP(B105, Paste!$Q$3:$Q$245, 1, FALSE)), "", VLOOKUP(B105, Paste!$Q$3:$R$245, 2, FALSE)) | U105: =IF(VLOOKUP(B105, 'Points&Potential'!$B$7:$O$943, 14, FALSE)=0, "", VLOOKUP(B105, 'Points&Potential'!$B$7:$O$943, 14, FALSE)) | V105: =IF(ISERROR(VLOOKUP(B105, Paste!$T$3:$T$1045, 1, FALSE)), "", VLOOKUP(B105, Paste!$T$3:$U$1144, 2, FALSE))
A106: 100 | B106: Darren Raddysh | C106: =VLOOKUP(B106, Paste!$AG$3:$AH$2083, 2, FALSE) -> 30.3 | D106: =VLOOKUP($B106, Paste!$A$3:$H$933, 6, FALSE) -> RD | E106: =IFERROR(VLOOKUP($B106, Paste!$J$3:$L$933, 3, FALSE), "") -> 53 | F106: =IFERROR(VLOOKUP($B106, Paste!$J$3:$L$933, 2, FALSE), "") -> 74 | G106: =VLOOKUP($B106, Paste!$A$3:$H$933, 8, FALSE) -> TOR | H106: =VLOOKUP($B106, Paste!$A$3:$H$933, 2, FALSE) -> 78 | I106: =VLOOKUP($B106, Paste!$A$3:$H$933, 3, FALSE) -> 13.26 | J106: =K106-I106 -> 47.374207 | K106: =VLOOKUP($B106, Paste!$A$3:$H$933, 4, FALSE) -> 60.634207 | L106: =IF(ISBLANK(VLOOKUP(B106, 'SOG&PlusMinus'!$B$7:$E$912, 3, FALSE)), "", VLOOKUP(B106,'SOG&PlusMinus'!$B$7:$E$912, 3, FALSE)) -> D | M106: =IF(ISBLANK(VLOOKUP(B106, 'SOG&PlusMinus'!$B$7:$E$912, 4, FALSE)), "", VLOOKUP(B106, 'SOG&PlusMinus'!$B$7:$E$912, 4, FALSE)) -> 1 | N106: =VLOOKUP($B106, Paste!$A$3:$H$933, 5, FALSE) -> 36.605263 | O106: =IF(ISERROR(VLOOKUP(B106, Paste!$AB$3:$AE$2349, 3, FALSE)), "", VLOOKUP(B106, Paste!$AB$3:$AE$2349, 3, FALSE)) -> 62 | P106: =IF(ISERROR(VLOOKUP(B106, Paste!$AB$3:$AC$2343, 2, FALSE)), "", VLOOKUP(B106, Paste!$AB$3:$AC$2343, 2, FALSE)) -> 83 | Q106: =IF(ISERROR(VLOOKUP(B106, Paste!$AB$3:$AE$2349, 4, FALSE)), "", VLOOKUP(B106, Paste!$AB$3:$AE$2349, 4, FALSE)) -> 218 | R106: =IF(ISERROR(VLOOKUP(B106, Paste!$N$3:$N$250, 1, FALSE)), "", VLOOKUP(B106, Paste!$N$3:$O$250, 2, FALSE)) | S106: =VLOOKUP($B106, Paste!$W$3:$Z$10064, IF($H$4="Cap Hit",3, IF($H$4="AAV", 4, 2)), FALSE) -> 8.5 | T106: =IF(ISERROR(VLOOKUP(B106, Paste!$Q$3:$Q$245, 1, FALSE)), "", VLOOKUP(B106, Paste!$Q$3:$R$245, 2, FALSE)) | U106: =IF(VLOOKUP(B106, 'Points&Potential'!$B$7:$O$943, 14, FALSE)=0, "", VLOOKUP(B106, 'Points&Potential'!$B$7:$O$943, 14, FALSE)) | V106: =IF(ISERROR(VLOOKUP(B106, Paste!$T$3:$T$1045, 1, FALSE)), "", VLOOKUP(B106, Paste!$T$3:$U$1144, 2, FALSE))
A107: 101 | B107: Josh Morrissey | C107: =VLOOKUP(B107, Paste!$AG$3:$AH$2083, 2, FALSE) -> 31.2 | D107: =VLOOKUP($B107, Paste!$A$3:$H$933, 6, FALSE) -> LD | E107: =IFERROR(VLOOKUP($B107, Paste!$J$3:$L$933, 3, FALSE), "") -> 62 | F107: =IFERROR(VLOOKUP($B107, Paste!$J$3:$L$933, 2, FALSE), "") -> 82 | G107: =VLOOKUP($B107, Paste!$A$3:$H$933, 8, FALSE) -> WPG | H107: =VLOOKUP($B107, Paste!$A$3:$H$933, 2, FALSE) -> 81.333333 | I107: =VLOOKUP($B107, Paste!$A$3:$H$933, 3, FALSE) -> 12.799144 | J107: =K107-I107 -> 47.37872 | K107: =VLOOKUP($B107, Paste!$A$3:$H$933, 4, FALSE) -> 60.177865 | L107: =IF(ISBLANK(VLOOKUP(B107, 'SOG&PlusMinus'!$B$7:$E$912, 3, FALSE)), "", VLOOKUP(B107,'SOG&PlusMinus'!$B$7:$E$912, 3, FALSE)) -> B | M107: =IF(ISBLANK(VLOOKUP(B107, 'SOG&PlusMinus'!$B$7:$E$912, 4, FALSE)), "", VLOOKUP(B107, 'SOG&PlusMinus'!$B$7:$E$912, 4, FALSE)) -> 1 | N107: =VLOOKUP($B107, Paste!$A$3:$H$933, 5, FALSE) -> 32.806723 | O107: =IF(ISERROR(VLOOKUP(B107, Paste!$AB$3:$AE$2349, 3, FALSE)), "", VLOOKUP(B107, Paste!$AB$3:$AE$2349, 3, FALSE)) -> 44 | P107: =IF(ISERROR(VLOOKUP(B107, Paste!$AB$3:$AC$2343, 2, FALSE)), "", VLOOKUP(B107, Paste!$AB$3:$AC$2343, 2, FALSE)) -> 122 | Q107: =IF(ISERROR(VLOOKUP(B107, Paste!$AB$3:$AE$2349, 4, FALSE)), "", VLOOKUP(B107, Paste!$AB$3:$AE$2349, 4, FALSE)) -> 163 | R107: =IF(ISERROR(VLOOKUP(B107, Paste!$N$3:$N$250, 1, FALSE)), "", VLOOKUP(B107, Paste!$N$3:$O$250, 2, FALSE)) | S107: =VLOOKUP($B107, Paste!$W$3:$Z$10064, IF($H$4="Cap Hit",3, IF($H$4="AAV", 4, 2)), FALSE) -> 6.25 | T107: =IF(ISERROR(VLOOKUP(B107, Paste!$Q$3:$Q$245, 1, FALSE)), "", VLOOKUP(B107, Paste!$Q$3:$R$245, 2, FALSE)) | U107: =IF(VLOOKUP(B107, 'Points&Potential'!$B$7:$O$943, 14, FALSE)=0, "", VLOOKUP(B107, 'Points&Potential'!$B$7:$O$943, 14, FALSE)) | V107: =IF(ISERROR(VLOOKUP(B107, Paste!$T$3:$T$1045, 1, FALSE)), "", VLOOKUP(B107, Paste!$T$3:$U$1144, 2, FALSE))
A108: 102 | B108: Brad Marchand | C108: =VLOOKUP(B108, Paste!$AG$3:$AH$2083, 2, FALSE) -> 38.1 | D108: =VLOOKUP($B108, Paste!$A$3:$H$933, 6, FALSE) -> RW | E108: =IFERROR(VLOOKUP($B108, Paste!$J$3:$L$933, 3, FALSE), "") -> 60 | F108: =IFERROR(VLOOKUP($B108, Paste!$J$3:$L$933, 2, FALSE), "") -> 80 | G108: =VLOOKUP($B108, Paste!$A$3:$H$933, 8, FALSE) -> FLA | H108: =VLOOKUP($B108, Paste!$A$3:$H$933, 2, FALSE) -> 72 | I108: =VLOOKUP($B108, Paste!$A$3:$H$933, 3, FALSE) -> 27.36 | J108: =K108-I108 -> 32.444952 | K108: =VLOOKUP($B108, Paste!$A$3:$H$933, 4, FALSE) -> 59.804952 | L108: =IF(ISBLANK(VLOOKUP(B108, 'SOG&PlusMinus'!$B$7:$E$912, 3, FALSE)), "", VLOOKUP(B108,'SOG&PlusMinus'!$B$7:$E$912, 3, FALSE)) -> C | M108: =IF(ISBLANK(VLOOKUP(B108, 'SOG&PlusMinus'!$B$7:$E$912, 4, FALSE)), "", VLOOKUP(B108, 'SOG&PlusMinus'!$B$7:$E$912, 4, FALSE)) -> 2 | N108: =VLOOKUP($B108, Paste!$A$3:$H$933, 5, FALSE) -> 63.219512 | O108: =IF(ISERROR(VLOOKUP(B108, Paste!$AB$3:$AE$2349, 3, FALSE)), "", VLOOKUP(B108, Paste!$AB$3:$AE$2349, 3, FALSE)) -> 54 | P108: =IF(ISERROR(VLOOKUP(B108, Paste!$AB$3:$AC$2343, 2, FALSE)), "", VLOOKUP(B108, Paste!$AB$3:$AC$2343, 2, FALSE)) -> 25 | Q108: =IF(ISERROR(VLOOKUP(B108, Paste!$AB$3:$AE$2349, 4, FALSE)), "", VLOOKUP(B108, Paste!$AB$3:$AE$2349, 4, FALSE)) -> 180 | R108: =IF(ISERROR(VLOOKUP(B108, Paste!$N$3:$N$250, 1, FALSE)), "", VLOOKUP(B108, Paste!$N$3:$O$250, 2, FALSE)) | S108: =VLOOKUP($B108, Paste!$W$3:$Z$10064, IF($H$4="Cap Hit",3, IF($H$4="AAV", 4, 2)), FALSE) -> 5.25 | T108: =IF(ISERROR(VLOOKUP(B108, Paste!$Q$3:$Q$245, 1, FALSE)), "", VLOOKUP(B108, Paste!$Q$3:$R$245, 2, FALSE)) -> Y | U108: =IF(VLOOKUP(B108, 'Points&Potential'!$B$7:$O$943, 14, FALSE)=0, "", VLOOKUP(B108, 'Points&Potential'!$B$7:$O$943, 14, FALSE)) | V108: =IF(ISERROR(VLOOKUP(B108, Paste!$T$3:$T$1045, 1, FALSE)), "", VLOOKUP(B108, Paste!$T$3:$U$1144, 2, FALSE))
A109: 103 | B109: Mikhail Sergachev | C109: =VLOOKUP(B109, Paste!$AG$3:$AH$2083, 2, FALSE) -> 28 | D109: =VLOOKUP($B109, Paste!$A$3:$H$933, 6, FALSE) -> LD | E109: =IFERROR(VLOOKUP($B109, Paste!$J$3:$L$933, 3, FALSE), "") -> 62 | F109: =IFERROR(VLOOKUP($B109, Paste!$J$3:$L$933, 2, FALSE), "") -> 73 | G109: =VLOOKUP($B109, Paste!$A$3:$H$933, 8, FALSE) -> UTA | H109: =VLOOKUP($B109, Paste!$A$3:$H$933, 2, FALSE) -> 79 | I109: =VLOOKUP($B109, Paste!$A$3:$H$933, 3, FALSE) -> 10.440905 | J109: =K109-I109 -> 49.105075 | K109: =VLOOKUP($B109, Paste!$A$3:$H$933, 4, FALSE) -> 59.54598 | L109: =IF(ISBLANK(VLOOKUP(B109, 'SOG&PlusMinus'!$B$7:$E$912, 3, FALSE)), "", VLOOKUP(B109,'SOG&PlusMinus'!$B$7:$E$912, 3, FALSE)) -> C | M109: =IF(ISBLANK(VLOOKUP(B109, 'SOG&PlusMinus'!$B$7:$E$912, 4, FALSE)), "", VLOOKUP(B109, 'SOG&PlusMinus'!$B$7:$E$912, 4, FALSE)) -> 1 | N109: =VLOOKUP($B109, Paste!$A$3:$H$933, 5, FALSE) -> 38.455026 | O109: =IF(ISERROR(VLOOKUP(B109, Paste!$AB$3:$AE$2349, 3, FALSE)), "", VLOOKUP(B109, Paste!$AB$3:$AE$2349, 3, FALSE)) -> 47 | P109: =IF(ISERROR(VLOOKUP(B109, Paste!$AB$3:$AC$2343, 2, FALSE)), "", VLOOKUP(B109, Paste!$AB$3:$AC$2343, 2, FALSE)) -> 134 | Q109: =IF(ISERROR(VLOOKUP(B109, Paste!$AB$3:$AE$2349, 4, FALSE)), "", VLOOKUP(B109, Paste!$AB$3:$AE$2349, 4, FALSE)) -> 150 | R109: =IF(ISERROR(VLOOKUP(B109, Paste!$N$3:$N$250, 1, FALSE)), "", VLOOKUP(B109, Paste!$N$3:$O$250, 2, FALSE)) | S109: =VLOOKUP($B109, Paste!$W$3:$Z$10064, IF($H$4="Cap Hit",3, IF($H$4="AAV", 4, 2)), FALSE) -> 8.5 | T109: =IF(ISERROR(VLOOKUP(B109, Paste!$Q$3:$Q$245, 1, FALSE)), "", VLOOKUP(B109, Paste!$Q$3:$R$245, 2, FALSE)) | U109: =IF(VLOOKUP(B109, 'Points&Potential'!$B$7:$O$943, 14, FALSE)=0, "", VLOOKUP(B109, 'Points&Potential'!$B$7:$O$943, 14, FALSE)) | V109: =IF(ISERROR(VLOOKUP(B109, Paste!$T$3:$T$1045, 1, FALSE)), "", VLOOKUP(B109, Paste!$T$3:$U$1144, 2, FALSE))
A110: 104 | B110: Miro Heiskanen | C110: =VLOOKUP(B110, Paste!$AG$3:$AH$2083, 2, FALSE) -> 26.9 | D110: =VLOOKUP($B110, Paste!$A$3:$H$933, 6, FALSE) -> LD | E110: =IFERROR(VLOOKUP($B110, Paste!$J$3:$L$933, 3, FALSE), "") -> 65 | F110: =IFERROR(VLOOKUP($B110, Paste!$J$3:$L$933, 2, FALSE), "") -> 75 | G110: =VLOOKUP($B110, Paste!$A$3:$H$933, 8, FALSE) -> DAL | H110: =VLOOKUP($B110, Paste!$A$3:$H$933, 2, FALSE) -> 72 | I110: =VLOOKUP($B110, Paste!$A$3:$H$933, 3, FALSE) -> 8.0471977 | J110: =K110-I110 -> 51.492216 | K110: =VLOOKUP($B110, Paste!$A$3:$H$933, 4, FALSE) -> 59.539414 | L110: =IF(ISBLANK(VLOOKUP(B110, 'SOG&PlusMinus'!$B$7:$E$912, 3, FALSE)), "", VLOOKUP(B110,'SOG&PlusMinus'!$B$7:$E$912, 3, FALSE)) -> B | M110: =IF(ISBLANK(VLOOKUP(B110, 'SOG&PlusMinus'!$B$7:$E$912, 4, FALSE)), "", VLOOKUP(B110, 'SOG&PlusMinus'!$B$7:$E$912, 4, FALSE)) -> 1 | N110: =VLOOKUP($B110, Paste!$A$3:$H$933, 5, FALSE) -> 27.636364 | O110: =IF(ISERROR(VLOOKUP(B110, Paste!$AB$3:$AE$2349, 3, FALSE)), "", VLOOKUP(B110, Paste!$AB$3:$AE$2349, 3, FALSE)) -> 22 | P110: =IF(ISERROR(VLOOKUP(B110, Paste!$AB$3:$AC$2343, 2, FALSE)), "", VLOOKUP(B110, Paste!$AB$3:$AC$2343, 2, FALSE)) -> 122 | Q110: =IF(ISERROR(VLOOKUP(B110, Paste!$AB$3:$AE$2349, 4, FALSE)), "", VLOOKUP(B110, Paste!$AB$3:$AE$2349, 4, FALSE)) -> 151 | R110: =IF(ISERROR(VLOOKUP(B110, Paste!$N$3:$N$250, 1, FALSE)), "", VLOOKUP(B110, Paste!$N$3:$O$250, 2, FALSE)) | S110: =VLOOKUP($B110, Paste!$W$3:$Z$10064, IF($H$4="Cap Hit",3, IF($H$4="AAV", 4, 2)), FALSE) -> 8.45 | T110: =IF(ISERROR(VLOOKUP(B110, Paste!$Q$3:$Q$245, 1, FALSE)), "", VLOOKUP(B110, Paste!$Q$3:$R$245, 2, FALSE)) -> Y | U110: =IF(VLOOKUP(B110, 'Points&Potential'!$B$7:$O$943, 14, FALSE)=0, "", VLOOKUP(B110, 'Points&Potential'!$B$7:$O$943, 14, FALSE)) | V110: =IF(ISERROR(VLOOKUP(B110, Paste!$T$3:$T$1045, 1, FALSE)), "", VLOOKUP(B110, Paste!$T$3:$U$1144, 2, FALSE))
A111: 105 | B111: Mark Stone | C111: =VLOOKUP(B111, Paste!$AG$3:$AH$2083, 2, FALSE) -> 34.1 | D111: =VLOOKUP($B111, Paste!$A$3:$H$933, 6, FALSE) -> RW | E111: =IFERROR(VLOOKUP($B111, Paste!$J$3:$L$933, 3, FALSE), "") -> 68 | F111: =IFERROR(VLOOKUP($B111, Paste!$J$3:$L$933, 2, FALSE), "") -> 92 | G111: =VLOOKUP($B111, Paste!$A$3:$H$933, 8, FALSE) -> VGK | H111: =VLOOKUP($B111, Paste!$A$3:$H$933, 2, FALSE) -> 62.666667 | I111: =VLOOKUP($B111, Paste!$A$3:$H$933, 3, FALSE) -> 21.738409 | J111: =K111-I111 -> 37.799951 | K111: =VLOOKUP($B111, Paste!$A$3:$H$933, 4, FALSE) -> 59.538361 | L111: =IF(ISBLANK(VLOOKUP(B111, 'SOG&PlusMinus'!$B$7:$E$912, 3, FALSE)), "", VLOOKUP(B111,'SOG&PlusMinus'!$B$7:$E$912, 3, FALSE)) -> A | M111: =IF(ISBLANK(VLOOKUP(B111, 'SOG&PlusMinus'!$B$7:$E$912, 4, FALSE)), "", VLOOKUP(B111, 'SOG&PlusMinus'!$B$7:$E$912, 4, FALSE)) -> 1 | N111: =VLOOKUP($B111, Paste!$A$3:$H$933, 5, FALSE) -> 15.494505 | O111: =IF(ISERROR(VLOOKUP(B111, Paste!$AB$3:$AE$2349, 3, FALSE)), "", VLOOKUP(B111, Paste!$AB$3:$AE$2349, 3, FALSE)) -> 30 | P111: =IF(ISERROR(VLOOKUP(B111, Paste!$AB$3:$AC$2343, 2, FALSE)), "", VLOOKUP(B111, Paste!$AB$3:$AC$2343, 2, FALSE)) -> 40 | Q111: =IF(ISERROR(VLOOKUP(B111, Paste!$AB$3:$AE$2349, 4, FALSE)), "", VLOOKUP(B111, Paste!$AB$3:$AE$2349, 4, FALSE)) -> 132 | R111: =IF(ISERROR(VLOOKUP(B111, Paste!$N$3:$N$250, 1, FALSE)), "", VLOOKUP(B111, Paste!$N$3:$O$250, 2, FALSE)) | S111: =VLOOKUP($B111, Paste!$W$3:$Z$10064, IF($H$4="Cap Hit",3, IF($H$4="AAV", 4, 2)), FALSE) -> 9.5 | T111: =IF(ISERROR(VLOOKUP(B111, Paste!$Q$3:$Q$245, 1, FALSE)), "", VLOOKUP(B111, Paste!$Q$3:$R$245, 2, FALSE)) -> Y | U111: =IF(VLOOKUP(B111, 'Points&Potential'!$B$7:$O$943, 14, FALSE)=0, "", VLOOKUP(B111, 'Points&Potential'!$B$7:$O$943, 14, FALSE)) | V111: =IF(ISERROR(VLOOKUP(B111, Paste!$T$3:$T$1045, 1, FALSE)), "", VLOOKUP(B111, Paste!$T$3:$U$1144, 2, FALSE))
A112: 106 | B112: Josh Doan | C112: =VLOOKUP(B112, Paste!$AG$3:$AH$2083, 2, FALSE) -> 24.4 | D112: =VLOOKUP($B112, Paste!$A$3:$H$933, 6, FALSE) -> RW | E112: =IFERROR(VLOOKUP($B112, Paste!$J$3:$L$933, 3, FALSE), "") -> 58 | F112: =IFERROR(VLOOKUP($B112, Paste!$J$3:$L$933, 2, FALSE), "") -> 70 | G112: =VLOOKUP($B112, Paste!$A$3:$H$933, 8, FALSE) -> BUF | H112: =VLOOKUP($B112, Paste!$A$3:$H$933, 2, FALSE) -> 83 | I112: =VLOOKUP($B112, Paste!$A$3:$H$933, 3, FALSE) -> 24 | J112: =K112-I112 -> 35.222866 | K112: =VLOOKUP($B112, Paste!$A$3:$H$933, 4, FALSE) -> 59.222866 | L112: =IF(ISBLANK(VLOOKUP(B112, 'SOG&PlusMinus'!$B$7:$E$912, 3, FALSE)), "", VLOOKUP(B112,'SOG&PlusMinus'!$B$7:$E$912, 3, FALSE)) -> C | M112: =IF(ISBLANK(VLOOKUP(B112, 'SOG&PlusMinus'!$B$7:$E$912, 4, FALSE)), "", VLOOKUP(B112, 'SOG&PlusMinus'!$B$7:$E$912, 4, FALSE)) -> 1 | N112: =VLOOKUP($B112, Paste!$A$3:$H$933, 5, FALSE) -> 26 | O112: =IF(ISERROR(VLOOKUP(B112, Paste!$AB$3:$AE$2349, 3, FALSE)), "", VLOOKUP(B112, Paste!$AB$3:$AE$2349, 3, FALSE)) -> 87 | P112: =IF(ISERROR(VLOOKUP(B112, Paste!$AB$3:$AC$2343, 2, FALSE)), "", VLOOKUP(B112, Paste!$AB$3:$AC$2343, 2, FALSE)) -> 33 | Q112: =IF(ISERROR(VLOOKUP(B112, Paste!$AB$3:$AE$2349, 4, FALSE)), "", VLOOKUP(B112, Paste!$AB$3:$AE$2349, 4, FALSE)) -> 183 | R112: =IF(ISERROR(VLOOKUP(B112, Paste!$N$3:$N$250, 1, FALSE)), "", VLOOKUP(B112, Paste!$N$3:$O$250, 2, FALSE)) | S112: =VLOOKUP($B112, Paste!$W$3:$Z$10064, IF($H$4="Cap Hit",3, IF($H$4="AAV", 4, 2)), FALSE) -> 6.95 | T112: =IF(ISERROR(VLOOKUP(B112, Paste!$Q$3:$Q$245, 1, FALSE)), "", VLOOKUP(B112, Paste!$Q$3:$R$245, 2, FALSE)) | U112: =IF(VLOOKUP(B112, 'Points&Potential'!$B$7:$O$943, 14, FALSE)=0, "", VLOOKUP(B112, 'Points&Potential'!$B$7:$O$943, 14, FALSE)) | V112: =IF(ISERROR(VLOOKUP(B112, Paste!$T$3:$T$1045, 1, FALSE)), "", VLOOKUP(B112, Paste!$T$3:$U$1144, 2, FALSE))
... A128: 122 | B128: Ryan Leonard | C128: =VLOOKUP(B128, Paste!$AG$3:$AH$2083, 2, FALSE) -> 21.4 | D128: =VLOOKUP($B128, Paste!$A$3:$H$933, 6, FALSE) -> RW | E128: =IFERROR(VLOOKUP($B128, Paste!$J$3:$L$933, 3, FALSE), "") -> 67 | F128: =IFERROR(VLOOKUP($B128, Paste!$J$3:$L$933, 2, FALSE), "") -> 80 | G128: =VLOOKUP($B128, Paste!$A$3:$H$933, 8, FALSE) -> WAS | H128: =VLOOKUP($B128, Paste!$A$3:$H$933, 2, FALSE) -> 78 | I128: =VLOOKUP($B128, Paste!$A$3:$H$933, 3, FALSE) -> 23.4 | J128: =K128-I128 -> 33.529641 | K128: =VLOOKUP($B128, Paste!$A$3:$H$933, 4, FALSE) -> 56.929641 | L128: =IF(ISBLANK(VLOOKUP(B128, 'SOG&PlusMinus'!$B$7:$E$912, 3, FALSE)), "", VLOOKUP(B128,'SOG&PlusMinus'!$B$7:$E$912, 3, FALSE)) -> C | M128: =IF(ISBLANK(VLOOKUP(B128, 'SOG&PlusMinus'!$B$7:$E$912, 4, FALSE)), "", VLOOKUP(B128, 'SOG&PlusMinus'!$B$7:$E$912, 4, FALSE)) -> 2 | N128: =VLOOKUP($B128, Paste!$A$3:$H$933, 5, FALSE) -> 35.904762 | O128: =IF(ISERROR(VLOOKUP(B128, Paste!$AB$3:$AE$2349, 3, FALSE)), "", VLOOKUP(B128, Paste!$AB$3:$AE$2349, 3, FALSE)) -> 133 | P128: =IF(ISERROR(VLOOKUP(B128, Paste!$AB$3:$AC$2343, 2, FALSE)), "", VLOOKUP(B128, Paste!$AB$3:$AC$2343, 2, FALSE)) -> 27 | Q128: =IF(ISERROR(VLOOKUP(B128, Paste!$AB$3:$AE$2349, 4, FALSE)), "", VLOOKUP(B128, Paste!$AB$3:$AE$2349, 4, FALSE)) -> 164 | R128: =IF(ISERROR(VLOOKUP(B128, Paste!$N$3:$N$250, 1, FALSE)), "", VLOOKUP(B128, Paste!$N$3:$O$250, 2, FALSE)) -> 70 | S128: =VLOOKUP($B128, Paste!$W$3:$Z$10064, IF($H$4="Cap Hit",3, IF($H$4="AAV", 4, 2)), FALSE) -> 2.208333 | T128: =IF(ISERROR(VLOOKUP(B128, Paste!$Q$3:$Q$245, 1, FALSE)), "", VLOOKUP(B128, Paste!$Q$3:$R$245, 2, FALSE)) | U128: =IF(VLOOKUP(B128, 'Points&Potential'!$B$7:$O$943, 14, FALSE)=0, "", VLOOKUP(B128, 'Points&Potential'!$B$7:$O$943, 14, FALSE)) | V128: =IF(ISERROR(VLOOKUP(B128, Paste!$T$3:$T$1045, 1, FALSE)), "", VLOOKUP(B128, Paste!$T$3:$U$1144, 2, FALSE))
A129: 123 | B129: Erik Karlsson | C129: =VLOOKUP(B129, Paste!$AG$3:$AH$2083, 2, FALSE) -> 36 | D129: =VLOOKUP($B129, Paste!$A$3:$H$933, 6, FALSE) -> RD | E129: =IFERROR(VLOOKUP($B129, Paste!$J$3:$L$933, 3, FALSE), "") -> 57 | F129: =IFERROR(VLOOKUP($B129, Paste!$J$3:$L$933, 2, FALSE), "") -> 73 | G129: =VLOOKUP($B129, Paste!$A$3:$H$933, 8, FALSE) -> PIT | H129: =VLOOKUP($B129, Paste!$A$3:$H$933, 2, FALSE) -> 81.666667 | I129: =VLOOKUP($B129, Paste!$A$3:$H$933, 3, FALSE) -> 12.613185 | J129: =K129-I129 -> 44.149188 | K129: =VLOOKUP($B129, Paste!$A$3:$H$933, 4, FALSE) -> 56.762373 | L129: =IF(ISBLANK(VLOOKUP(B129, 'SOG&PlusMinus'!$B$7:$E$912, 3, FALSE)), "", VLOOKUP(B129,'SOG&PlusMinus'!$B$7:$E$912, 3, FALSE)) -> B | M129: =IF(ISBLANK(VLOOKUP(B129, 'SOG&PlusMinus'!$B$7:$E$912, 4, FALSE)), "", VLOOKUP(B129, 'SOG&PlusMinus'!$B$7:$E$912, 4, FALSE)) -> 1 | N129: =VLOOKUP($B129, Paste!$A$3:$H$933, 5, FALSE) -> 29.386332 | O129: =IF(ISERROR(VLOOKUP(B129, Paste!$AB$3:$AE$2349, 3, FALSE)), "", VLOOKUP(B129, Paste!$AB$3:$AE$2349, 3, FALSE)) -> 20 | P129: =IF(ISERROR(VLOOKUP(B129, Paste!$AB$3:$AC$2343, 2, FALSE)), "", VLOOKUP(B129, Paste!$AB$3:$AC$2343, 2, FALSE)) -> 77 | Q129: =IF(ISERROR(VLOOKUP(B129, Paste!$AB$3:$AE$2349, 4, FALSE)), "", VLOOKUP(B129, Paste!$AB$3:$AE$2349, 4, FALSE)) -> 180 | R129: =IF(ISERROR(VLOOKUP(B129, Paste!$N$3:$N$250, 1, FALSE)), "", VLOOKUP(B129, Paste!$N$3:$O$250, 2, FALSE)) | S129: =VLOOKUP($B129, Paste!$W$3:$Z$10064, IF($H$4="Cap Hit",3, IF($H$4="AAV", 4, 2)), FALSE) -> 11.5 | U129: =IF(VLOOKUP(B129, 'Points&Potential'!$B$7:$O$943, 14, FALSE)=0, "", VLOOKUP(B129, 'Points&Potential'!$B$7:$O$943, 14, FALSE)) | V129: =IF(ISERROR(VLOOKUP(B129, Paste!$T$3:$T$1045, 1, FALSE)), "", VLOOKUP(B129, Paste!$T$3:$U$1144, 2, FALSE))
A130: 124 | B130: Matt Coronato | C130: =VLOOKUP(B130, Paste!$AG$3:$AH$2083, 2, FALSE) -> 23.6 | D130: =VLOOKUP($B130, Paste!$A$3:$H$933, 6, FALSE) -> RW | E130: =IFERROR(VLOOKUP($B130, Paste!$J$3:$L$933, 3, FALSE), "") -> 58 | F130: =IFERROR(VLOOKUP($B130, Paste!$J$3:$L$933, 2, FALSE), "") -> 83 | G130: =VLOOKUP($B130, Paste!$A$3:$H$933, 8, FALSE) -> CGY | H130: =VLOOKUP($B130, Paste!$A$3:$H$933, 2, FALSE) -> 82 | I130: =VLOOKUP($B130, Paste!$A$3:$H$933, 3, FALSE) -> 24.6 | J130: =K130-I130 -> 32.098464 | K130: =VLOOKUP($B130, Paste!$A$3:$H$933, 4, FALSE) -> 56.698464 | L130: =IF(ISBLANK(VLOOKUP(B130, 'SOG&PlusMinus'!$B$7:$E$912, 3, FALSE)), "", VLOOKUP(B130,'SOG&PlusMinus'!$B$7:$E$912, 3, FALSE)) -> D | M130: =IF(ISBLANK(VLOOKUP(B130, 'SOG&PlusMinus'!$B$7:$E$912, 4, FALSE)), "", VLOOKUP(B130, 'SOG&PlusMinus'!$B$7:$E$912, 4, FALSE)) -> 1 | N130: =VLOOKUP($B130, Paste!$A$3:$H$933, 5, FALSE) -> 26.188482 | O130: =IF(ISERROR(VLOOKUP(B130, Paste!$AB$3:$AE$2349, 3, FALSE)), "", VLOOKUP(B130, Paste!$AB$3:$AE$2349, 3, FALSE)) -> 33 | P130: =IF(ISERROR(VLOOKUP(B130, Paste!$AB$3:$AC$2343, 2, FALSE)), "", VLOOKUP(B130, Paste!$AB$3:$AC$2343, 2, FALSE)) -> 33 | Q130: =IF(ISERROR(VLOOKUP(B130, Paste!$AB$3:$AE$2349, 4, FALSE)), "", VLOOKUP(B130, Paste!$AB$3:$AE$2349, 4, FALSE)) -> 205 | R130: =IF(ISERROR(VLOOKUP(B130, Paste!$N$3:$N$250, 1, FALSE)), "", VLOOKUP(B130, Paste!$N$3:$O$250, 2, FALSE)) -> 60 | S130: =VLOOKUP($B130, Paste!$W$3:$Z$10064, IF($H$4="Cap Hit",3, IF($H$4="AAV", 4, 2)), FALSE) -> 6.5 | T130: =IF(ISERROR(VLOOKUP(B130, Paste!$Q$3:$Q$245, 1, FALSE)), "", VLOOKUP(B130, Paste!$Q$3:$R$245, 2, FALSE)) | U130: =IF(VLOOKUP(B130, 'Points&Potential'!$B$7:$O$943, 14, FALSE)=0, "", VLOOKUP(B130, 'Points&Potential'!$B$7:$O$943, 14, FALSE)) | V130: =IF(ISERROR(VLOOKUP(B130, Paste!$T$3:$T$1045, 1, FALSE)), "", VLOOKUP(B130, Paste!$T$3:$U$1144, 2, FALSE))
A131: 125 | B131: William Eklund | C131: =VLOOKUP(B131, Paste!$AG$3:$AH$2083, 2, FALSE) -> 23.7 | D131: =VLOOKUP($B131, Paste!$A$3:$H$933, 6, FALSE) -> LW | E131: =IFERROR(VLOOKUP($B131, Paste!$J$3:$L$933, 3, FALSE), "") -> 70 | F131: =IFERROR(VLOOKUP($B131, Paste!$J$3:$L$933, 2, FALSE), "") -> 82 | G131: =VLOOKUP($B131, Paste!$A$3:$H$933, 8, FALSE) -> OTT | H131: =VLOOKUP($B131, Paste!$A$3:$H$933, 2, FALSE) -> 80.333333 | I131: =VLOOKUP($B131, Paste!$A$3:$H$933, 3, FALSE) -> 17.707957 | J131: =K131-I131 -> 38.956903 | K131: =VLOOKUP($B131, Paste!$A$3:$H$933, 4, FALSE) -> 56.66486 | L131: =IF(ISBLANK(VLOOKUP(B131, 'SOG&PlusMinus'!$B$7:$E$912, 3, FALSE)), "", VLOOKUP(B131,'SOG&PlusMinus'!$B$7:$E$912, 3, FALSE)) -> C | M131: =IF(ISBLANK(VLOOKUP(B131, 'SOG&PlusMinus'!$B$7:$E$912, 4, FALSE)), "", VLOOKUP(B131, 'SOG&PlusMinus'!$B$7:$E$912, 4, FALSE)) -> 1 | N131: =VLOOKUP($B131, Paste!$A$3:$H$933, 5, FALSE) -> 31.107801 | O131: =IF(ISERROR(VLOOKUP(B131, Paste!$AB$3:$AE$2349, 3, FALSE)), "", VLOOKUP(B131, Paste!$AB$3:$AE$2349, 3, FALSE)) -> 81 | P131: =IF(ISERROR(VLOOKUP(B131, Paste!$AB$3:$AC$2343, 2, FALSE)), "", VLOOKUP(B131, Paste!$AB$3:$AC$2343, 2, FALSE)) -> 48 | Q131: =IF(ISERROR(VLOOKUP(B131, Paste!$AB$3:$AE$2349, 4, FALSE)), "", VLOOKUP(B131, Paste!$AB$3:$AE$2349, 4, FALSE)) -> 193 | R131: =IF(ISERROR(VLOOKUP(B131, Paste!$N$3:$N$250, 1, FALSE)), "", VLOOKUP(B131, Paste!$N$3:$O$250, 2, FALSE)) -> 70 | S131: =VLOOKUP($B131, Paste!$W$3:$Z$10064, IF($H$4="Cap Hit",3, IF($H$4="AAV", 4, 2)), FALSE) -> 5.6 | T131: =IF(ISERROR(VLOOKUP(B131, Paste!$Q$3:$Q$245, 1, FALSE)), "", VLOOKUP(B131, Paste!$Q$3:$R$245, 2, FALSE)) | U131: =IF(VLOOKUP(B131, 'Points&Potential'!$B$7:$O$943, 14, FALSE)=0, "", VLOOKUP(B131, 'Points&Potential'!$B$7:$O$943, 14, FALSE)) | V131: =IF(ISERROR(VLOOKUP(B131, Paste!$T$3:$T$1045, 1, FALSE)), "", VLOOKUP(B131, Paste!$T$3:$U$1144, 2, FALSE))
A132: 126 | B132: Mats Zuccarello | C132: =VLOOKUP(B132, Paste!$AG$3:$AH$2083, 2, FALSE) -> 38.8 | D132: =VLOOKUP($B132, Paste!$A$3:$H$933, 6, FALSE) -> RW | E132: =IFERROR(VLOOKUP($B132, Paste!$J$3:$L$933, 3, FALSE), "") -> 52 | F132: =IFERROR(VLOOKUP($B132, Paste!$J$3:$L$933, 2, FALSE), "") -> 65 | G132: =VLOOKUP($B132, Paste!$A$3:$H$933, 8, FALSE) -> LAK | H132: =VLOOKUP($B132, Paste!$A$3:$H$933, 2, FALSE) -> 67.666667 | I132: =VLOOKUP($B132, Paste!$A$3:$H$933, 3, FALSE) -> 15.64619 | J132: =K132-I132 -> 41.000484 | K132: =VLOOKUP($B132, Paste!$A$3:$H$933, 4, FALSE) -> 56.646674 | L132: =IF(ISBLANK(VLOOKUP(B132, 'SOG&PlusMinus'!$B$7:$E$912, 3, FALSE)), "", VLOOKUP(B132,'SOG&PlusMinus'!$B$7:$E$912, 3, FALSE)) -> C | M132: =IF(ISBLANK(VLOOKUP(B132, 'SOG&PlusMinus'!$B$7:$E$912, 4, FALSE)), "", VLOOKUP(B132, 'SOG&PlusMinus'!$B$7:$E$912, 4, FALSE)) -> 1 | N132: =VLOOKUP($B132, Paste!$A$3:$H$933, 5, FALSE) -> 24.730964 | O132: =IF(ISERROR(VLOOKUP(B132, Paste!$AB$3:$AE$2349, 3, FALSE)), "", VLOOKUP(B132, Paste!$AB$3:$AE$2349, 3, FALSE)) -> 14 | P132: =IF(ISERROR(VLOOKUP(B132, Paste!$AB$3:$AC$2343, 2, FALSE)), "", VLOOKUP(B132, Paste!$AB$3:$AC$2343, 2, FALSE)) -> 27 | Q132: =IF(ISERROR(VLOOKUP(B132, Paste!$AB$3:$AE$2349, 4, FALSE)), "", VLOOKUP(B132, Paste!$AB$3:$AE$2349, 4, FALSE)) -> 135 | R132: =IF(ISERROR(VLOOKUP(B132, Paste!$N$3:$N$250, 1, FALSE)), "", VLOOKUP(B132, Paste!$N$3:$O$250, 2, FALSE)) | S132: =VLOOKUP($B132, Paste!$W$3:$Z$10064, IF($H$4="Cap Hit",3, IF($H$4="AAV", 4, 2)), FALSE) -> 6.5 | T132: =IF(ISERROR(VLOOKUP(B132, Paste!$Q$3:$Q$245, 1, FALSE)), "", VLOOKUP(B132, Paste!$Q$3:$R$245, 2, FALSE)) -> Y | U132: =IF(VLOOKUP(B132, 'Points&Potential'!$B$7:$O$943, 14, FALSE)=0, "", VLOOKUP(B132, 'Points&Potential'!$B$7:$O$943, 14, FALSE)) | V132: =IF(ISERROR(VLOOKUP(B132, Paste!$T$3:$T$1045, 1, FALSE)), "", VLOOKUP(B132, Paste!$T$3:$U$1144, 2, FALSE))
A133: 127 | B133: Pierre-Luc Dubois | C133: =VLOOKUP(B133, Paste!$AG$3:$AH$2083, 2, FALSE) -> 28 | D133: =VLOOKUP($B133, Paste!$A$3:$H$933, 6, FALSE) -> C | E133: =IFERROR(VLOOKUP($B133, Paste!$J$3:$L$933, 3, FALSE), "") -> 63 | F133: =IFERROR(VLOOKUP($B133, Paste!$J$3:$L$933, 2, FALSE), "") -> 78 | G133: =VLOOKUP($B133, Paste!$A$3:$H$933, 8, FALSE) -> WAS | H133: =VLOOKUP($B133, Paste!$A$3:$H$933, 2, FALSE) -> 75 | I133: =VLOOKUP($B133, Paste!$A$3:$H$933, 3, FALSE) -> 17.25 | J133: =K133-I133 -> 39.391895 | K133: =VLOOKUP($B133, Paste!$A$3:$H$933, 4, FALSE) -> 56.641895 | L133: =IF(ISBLANK(VLOOKUP(B133, 'SOG&PlusMinus'!$B$7:$E$912, 3, FALSE)), "", VLOOKUP(B133,'SOG&PlusMinus'!$B$7:$E$912, 3, FALSE)) -> C | M133: =IF(ISBLANK(VLOOKUP(B133, 'SOG&PlusMinus'!$B$7:$E$912, 4, FALSE)), "", VLOOKUP(B133, 'SOG&PlusMinus'!$B$7:$E$912, 4, FALSE)) -> 2 | N133: =VLOOKUP($B133, Paste!$A$3:$H$933, 5, FALSE) -> 64.119171 | O133: =IF(ISERROR(VLOOKUP(B133, Paste!$AB$3:$AE$2349, 3, FALSE)), "", VLOOKUP(B133, Paste!$AB$3:$AE$2349, 3, FALSE)) -> 59 | P133: =IF(ISERROR(VLOOKUP(B133, Paste!$AB$3:$AC$2343, 2, FALSE)), "", VLOOKUP(B133, Paste!$AB$3:$AC$2343, 2, FALSE)) -> 41 | Q133: =IF(ISERROR(VLOOKUP(B133, Paste!$AB$3:$AE$2349, 4, FALSE)), "", VLOOKUP(B133, Paste!$AB$3:$AE$2349, 4, FALSE)) -> 120 | R133: =IF(ISERROR(VLOOKUP(B133, Paste!$N$3:$N$250, 1, FALSE)), "", VLOOKUP(B133, Paste!$N$3:$O$250, 2, FALSE)) | S133: =VLOOKUP($B133, Paste!$W$3:$Z$10064, IF($H$4="Cap Hit",3, IF($H$4="AAV", 4, 2)), FALSE) -> 8.5 | T133: =IF(ISERROR(VLOOKUP(B133, Paste!$Q$3:$Q$245, 1, FALSE)), "", VLOOKUP(B133, Paste!$Q$3:$R$245, 2, FALSE)) | U133: =IF(VLOOKUP(B133, 'Points&Potential'!$B$7:$O$943, 14, FALSE)=0, "", VLOOKUP(B133, 'Points&Potential'!$B$7:$O$943, 14, FALSE)) | V133: =IF(ISERROR(VLOOKUP(B133, Paste!$T$3:$T$1045, 1, FALSE)), "", VLOOKUP(B133, Paste!$T$3:$U$1144, 2, FALSE))
A134: 128 | B134: Michael Misa | C134: =VLOOKUP(B134, Paste!$AG$3:$AH$2083, 2, FALSE) -> 19.3 | D134: =VLOOKUP($B134, Paste!$A$3:$H$933, 6, FALSE) -> C | E134: =IFERROR(VLOOKUP($B134, Paste!$J$3:$L$933, 3, FALSE), "") -> 73 | F134: =IFERROR(VLOOKUP($B134, Paste!$J$3:$L$933, 2, FALSE), "") -> 97 | G134: =VLOOKUP($B134, Paste!$A$3:$H$933, 8, FALSE) -> SJS | H134: =VLOOKUP($B134, Paste!$A$3:$H$933, 2, FALSE) -> 74 | I134: =VLOOKUP($B134, Paste!$A$3:$H$933, 3, FALSE) -> 18.5 | J134: =K134-I134 -> 37.95904 | K134: =VLOOKUP($B134, Paste!$A$3:$H$933, 4, FALSE) -> 56.45904 | L134: =IF(ISBLANK(VLOOKUP(B134, 'SOG&PlusMinus'!$B$7:$E$912, 3, FALSE)), "", VLOOKUP(B134,'SOG&PlusMinus'!$B$7:$E$912, 3, FALSE)) -> C | M134: =IF(ISBLANK(VLOOKUP(B134, 'SOG&PlusMinus'!$B$7:$E$912, 4, FALSE)), "", VLOOKUP(B134, 'SOG&PlusMinus'!$B$7:$E$912, 4, FALSE)) -> 2 | N134: =VLOOKUP($B134, Paste!$A$3:$H$933, 5, FALSE) -> 29.6 | O134: =IF(ISERROR(VLOOKUP(B134, Paste!$AB$3:$AE$2349, 3, FALSE)), "", VLOOKUP(B134, Paste!$AB$3:$AE$2349, 3, FALSE)) -> 26 | P134: =IF(ISERROR(VLOOKUP(B134, Paste!$AB$3:$AC$2343, 2, FALSE)), "", VLOOKUP(B134, Paste!$AB$3:$AC$2343, 2, FALSE)) -> 41 | Q134: =IF(ISERROR(VLOOKUP(B134, Paste!$AB$3:$AE$2349, 4, FALSE)), "", VLOOKUP(B134, Paste!$AB$3:$AE$2349, 4, FALSE)) -> 111 | R134: =IF(ISERROR(VLOOKUP(B134, Paste!$N$3:$N$250, 1, FALSE)), "", VLOOKUP(B134, Paste!$N$3:$O$250, 2, FALSE)) -> 70 | S134: =VLOOKUP($B134, Paste!$W$3:$Z$10064, IF($H$4="Cap Hit",3, IF($H$4="AAV", 4, 2)), FALSE) -> 4.225 | T134: =IF(ISERROR(VLOOKUP(B134, Paste!$Q$3:$Q$245, 1, FALSE)), "", VLOOKUP(B134, Paste!$Q$3:$R$245, 2, FALSE)) | U134: =IF(VLOOKUP(B134, 'Points&Potential'!$B$7:$O$943, 14, FALSE)=0, "", VLOOKUP(B134, 'Points&Potential'!$B$7:$O$943, 14, FALSE)) | V134: =IF(ISERROR(VLOOKUP(B134, Paste!$T$3:$T$1045, 1, FALSE)), "", VLOOKUP(B134, Paste!$T$3:$U$1144, 2, FALSE))
A135: 129 | B135: Ivan Barbashev | C135: =VLOOKUP(B135, Paste!$AG$3:$AH$2083, 2, FALSE) -> 30.5 | D135: =VLOOKUP($B135, Paste!$A$3:$H$933, 6, FALSE) -> LW | E135: =IFERROR(VLOOKUP($B135, Paste!$J$3:$L$933, 3, FALSE), "") -> 60 | F135: =IFERROR(VLOOKUP($B135, Paste!$J$3:$L$933, 2, FALSE), "") -> 70 | G135: =VLOOKUP($B135, Paste!$A$3:$H$933, 8, FALSE) -> VGK | H135: =VLOOKUP($B135, Paste!$A$3:$H$933, 2, FALSE) -> 80 | I135: =VLOOKUP($B135, Paste!$A$3:$H$933, 3, FALSE) -> 22.685677 | J135: =K135-I135 -> 33.701685 | K135: =VLOOKUP($B135, Paste!$A$3:$H$933, 4, FALSE) -> 56.387363 | L135: =IF(ISBLANK(VLOOKUP(B135, 'SOG&PlusMinus'!$B$7:$E$912, 3, FALSE)), "", VLOOKUP(B135,'SOG&PlusMinus'!$B$7:$E$912, 3, FALSE)) -> A | M135: =IF(ISBLANK(VLOOKUP(B135, 'SOG&PlusMinus'!$B$7:$E$912, 4, FALSE)), "", VLOOKUP(B135, 'SOG&PlusMinus'!$B$7:$E$912, 4, FALSE)) -> 2 | N135: =VLOOKUP($B135, Paste!$A$3:$H$933, 5, FALSE) -> 22.564103 | O135: =IF(ISERROR(VLOOKUP(B135, Paste!$AB$3:$AE$2349, 3, FALSE)), "", VLOOKUP(B135, Paste!$AB$3:$AE$2349, 3, FALSE)) -> 126 | P135: =IF(ISERROR(VLOOKUP(B135, Paste!$AB$3:$AC$2343, 2, FALSE)), "", VLOOKUP(B135, Paste!$AB$3:$AC$2343, 2, FALSE)) -> 37 | Q135: =IF(ISERROR(VLOOKUP(B135, Paste!$AB$3:$AE$2349, 4, FALSE)), "", VLOOKUP(B135, Paste!$AB$3:$AE$2349, 4, FALSE)) -> 128 | R135: =IF(ISERROR(VLOOKUP(B135, Paste!$N$3:$N$250, 1, FALSE)), "", VLOOKUP(B135, Paste!$N$3:$O$250, 2, FALSE)) | S135: =VLOOKUP($B135, Paste!$W$3:$Z$10064, IF($H$4="Cap Hit",3, IF($H$4="AAV", 4, 2)), FALSE) -> 5 | T135: =IF(ISERROR(VLOOKUP(B135, Paste!$Q$3:$Q$245, 1, FALSE)), "", VLOOKUP(B135, Paste!$Q$3:$R$245, 2, FALSE)) | U135: =IF(VLOOKUP(B135, 'Points&Potential'!$B$7:$O$943, 14, FALSE)=0, "", VLOOKUP(B135, 'Points&Potential'!$B$7:$O$943, 14, FALSE)) | V135: =IF(ISERROR(VLOOKUP(B135, Paste!$T$3:$T$1045, 1, FALSE)), "", VLOOKUP(B135, Paste!$T$3:$U$1144, 2, FALSE))
A136: 130 | B136: Brock Nelson | C136: =VLOOKUP(B136, Paste!$AG$3:$AH$2083, 2, FALSE) -> 34.7 | D136: =VLOOKUP($B136, Paste!$A$3:$H$933, 6, FALSE) -> C | E136: =IFERROR(VLOOKUP($B136, Paste!$J$3:$L$933, 3, FALSE), "") -> 57 | F136: =IFERROR(VLOOKUP($B136, Paste!$J$3:$L$933, 2, FALSE), "") -> 70 | G136: =VLOOKUP($B136, Paste!$A$3:$H$933, 8, FALSE) -> COL | H136: =VLOOKUP($B136, Paste!$A$3:$H$933, 2, FALSE) -> 83 | I136: =VLOOKUP($B136, Paste!$A$3:$H$933, 3, FALSE) -> 30.505542 | J136: =K136-I136 -> 25.75367 | K136: =VLOOKUP($B136, Paste!$A$3:$H$933, 4, FALSE) -> 56.259212 | L136: =IF(ISBLANK(VLOOKUP(B136, 'SOG&PlusMinus'!$B$7:$E$912, 3, FALSE)), "", VLOOKUP(B136,'SOG&PlusMinus'!$B$7:$E$912, 3, FALSE)) -> A | M136: =IF(ISBLANK(VLOOKUP(B136, 'SOG&PlusMinus'!$B$7:$E$912, 4, FALSE)), "", VLOOKUP(B136, 'SOG&PlusMinus'!$B$7:$E$912, 4, FALSE)) -> 2 | N136: =VLOOKUP($B136, Paste!$A$3:$H$933, 5, FALSE) -> 28.00823 | O136: =IF(ISERROR(VLOOKUP(B136, Paste!$AB$3:$AE$2349, 3, FALSE)), "", VLOOKUP(B136, Paste!$AB$3:$AE$2349, 3, FALSE)) -> 37 | P136: =IF(ISERROR(VLOOKUP(B136, Paste!$AB$3:$AC$2343, 2, FALSE)), "", VLOOKUP(B136, Paste!$AB$3:$AC$2343, 2, FALSE)) -> 54 | Q136: =IF(ISERROR(VLOOKUP(B136, Paste!$AB$3:$AE$2349, 4, FALSE)), "", VLOOKUP(B136, Paste!$AB$3:$AE$2349, 4, FALSE)) -> 191 | R136: =IF(ISERROR(VLOOKUP(B136, Paste!$N$3:$N$250, 1, FALSE)), "", VLOOKUP(B136, Paste!$N$3:$O$250, 2, FALSE)) | S136: =VLOOKUP($B136, Paste!$W$3:$Z$10064, IF($H$4="Cap Hit",3, IF($H$4="AAV", 4, 2)), FALSE) -> 7.5 | T136: =IF(ISERROR(VLOOKUP(B136, Paste!$Q$3:$Q$245, 1, FALSE)), "", VLOOKUP(B136, Paste!$Q$3:$R$245, 2, FALSE)) | U136: =IF(VLOOKUP(B136, 'Points&Potential'!$B$7:$O$943, 14, FALSE)=0, "", VLOOKUP(B136, 'Points&Potential'!$B$7:$O$943, 14, FALSE)) | V136: =IF(ISERROR(VLOOKUP(B136, Paste!$T$3:$T$1045, 1, FALSE)), "", VLOOKUP(B136, Paste!$T$3:$U$1144, 2, FALSE))
A137: 131 | B137: Sam Bennett | C137: =VLOOKUP(B137, Paste!$AG$3:$AH$2083, 2, FALSE) -> 30 | D137: =VLOOKUP($B137, Paste!$A$3:$H$933, 6, FALSE) -> C | E137: =IFERROR(VLOOKUP($B137, Paste!$J$3:$L$933, 3, FALSE), "") -> 53 | F137: =IFERROR(VLOOKUP($B137, Paste!$J$3:$L$933, 2, FALSE), "") -> 70 | G137: =VLOOKUP($B137, Paste!$A$3:$H$933, 8, FALSE) -> FLA | H137: =VLOOKUP($B137, Paste!$A$3:$H$933, 2, FALSE) -> 75.666667 | I137: =VLOOKUP($B137, Paste!$A$3:$H$933, 3, FALSE) -> 24.637739 | J137: =K137-I137 -> 31.601235 | K137: =VLOOKUP($B137, Paste!$A$3:$H$933, 4, FALSE) -> 56.238974 | L137: =IF(ISBLANK(VLOOKUP(B137, 'SOG&PlusMinus'!$B$7:$E$912, 3, FALSE)), "", VLOOKUP(B137,'SOG&PlusMinus'!$B$7:$E$912, 3, FALSE)) -> C | M137: =IF(ISBLANK(VLOOKUP(B137, 'SOG&PlusMinus'!$B$7:$E$912, 4, FALSE)), "", VLOOKUP(B137, 'SOG&PlusMinus'!$B$7:$E$912, 4, FALSE)) -> 2 | N137: =VLOOKUP($B137, Paste!$A$3:$H$933, 5, FALSE) -> 93.128205 | O137: =IF(ISERROR(VLOOKUP(B137, Paste!$AB$3:$AE$2349, 3, FALSE)), "", VLOOKUP(B137, Paste!$AB$3:$AE$2349, 3, FALSE)) -> 129 | P137: =IF(ISERROR(VLOOKUP(B137, Paste!$AB$3:$AC$2343, 2, FALSE)), "", VLOOKUP(B137, Paste!$AB$3:$AC$2343, 2, FALSE)) -> 38 | Q137: =IF(ISERROR(VLOOKUP(B137, Paste!$AB$3:$AE$2349, 4, FALSE)), "", VLOOKUP(B137, Paste!$AB$3:$AE$2349, 4, FALSE)) -> 204 | R137: =IF(ISERROR(VLOOKUP(B137, Paste!$N$3:$N$250, 1, FALSE)), "", VLOOKUP(B137, Paste!$N$3:$O$250, 2, FALSE)) | S137: =VLOOKUP($B137, Paste!$W$3:$Z$10064, IF($H$4="Cap Hit",3, IF($H$4="AAV", 4, 2)), FALSE) -> 8 | T137: =IF(ISERROR(VLOOKUP(B137, Paste!$Q$3:$Q$245, 1, FALSE)), "", VLOOKUP(B137, Paste!$Q$3:$R$245, 2, FALSE)) | U137: =IF(VLOOKUP(B137, 'Points&Potential'!$B$7:$O$943, 14, FALSE)=0, "", VLOOKUP(B137, 'Points&Potential'!$B$7:$O$943, 14, FALSE)) | V137: =IF(ISERROR(VLOOKUP(B137, Paste!$T$3:$T$1045, 1, FALSE)), "", VLOOKUP(B137, Paste!$T$3:$U$1144, 2, FALSE))
A138: 132 | B138: Rickard Rakell | C138: =VLOOKUP(B138, Paste!$AG$3:$AH$2083, 2, FALSE) -> 33.1 | D138: =VLOOKUP($B138, Paste!$A$3:$H$933, 6, FALSE) -> LW | E138: =IFERROR(VLOOKUP($B138, Paste!$J$3:$L$933, 3, FALSE), "") -> 52 | F138: =IFERROR(VLOOKUP($B138, Paste!$J$3:$L$933, 2, FALSE), "") -> 67 | G138: =VLOOKUP($B138, Paste!$A$3:$H$933, 8, FALSE) -> PIT | H138: =VLOOKUP($B138, Paste!$A$3:$H$933, 2, FALSE) -> 72.333333 | I138: =VLOOKUP($B138, Paste!$A$3:$H$933, 3, FALSE) -> 25.684776 | J138: =K138-I138 -> 30.408124 | K138: =VLOOKUP($B138, Paste!$A$3:$H$933, 4, FALSE) -> 56.0929 | L138: =IF(ISBLANK(VLOOKUP(B138, 'SOG&PlusMinus'!$B$7:$E$912, 3, FALSE)), "", VLOOKUP(B138,'SOG&PlusMinus'!$B$7:$E$912, 3, FALSE)) -> C | M138: =IF(ISBLANK(VLOOKUP(B138, 'SOG&PlusMinus'!$B$7:$E$912, 4, FALSE)), "", VLOOKUP(B138, 'SOG&PlusMinus'!$B$7:$E$912, 4, FALSE)) -> 1 | N138: =VLOOKUP($B138, Paste!$A$3:$H$933, 5, FALSE) -> 15.083728 | O138: =IF(ISERROR(VLOOKUP(B138, Paste!$AB$3:$AE$2349, 3, FALSE)), "", VLOOKUP(B138, Paste!$AB$3:$AE$2349, 3, FALSE)) -> 87 | P138: =IF(ISERROR(VLOOKUP(B138, Paste!$AB$3:$AC$2343, 2, FALSE)), "", VLOOKUP(B138, Paste!$AB$3:$AC$2343, 2, FALSE)) -> 47 | Q138: =IF(ISERROR(VLOOKUP(B138, Paste!$AB$3:$AE$2349, 4, FALSE)), "", VLOOKUP(B138, Paste!$AB$3:$AE$2349, 4, FALSE)) -> 195 | R138: =IF(ISERROR(VLOOKUP(B138, Paste!$N$3:$N$250, 1, FALSE)), "", VLOOKUP(B138, Paste!$N$3:$O$250, 2, FALSE)) | S138: =VLOOKUP($B138, Paste!$W$3:$Z$10064, IF($H$4="Cap Hit",3, IF($H$4="AAV", 4, 2)), FALSE) -> 5 | U138: =IF(VLOOKUP(B138, 'Points&Potential'!$B$7:$O$943, 14, FALSE)=0, "", VLOOKUP(B138, 'Points&Potential'!$B$7:$O$943, 14, FALSE)) | V138: =IF(ISERROR(VLOOKUP(B138, Paste!$T$3:$T$1045, 1, FALSE)), "", VLOOKUP(B138, Paste!$T$3:$U$1144, 2, FALSE))
A139: 133 | B139: Jakob Chychrun | C139: =VLOOKUP(B139, Paste!$AG$3:$AH$2083, 2, FALSE) -> 28.2 | D139: =VLOOKUP($B139, Paste!$A$3:$H$933, 6, FALSE) -> LD | E139: =IFERROR(VLOOKUP($B139, Paste!$J$3:$L$933, 3, FALSE), "") -> 57 | F139: =IFERROR(VLOOKUP($B139, Paste!$J$3:$L$933, 2, FALSE), "") -> 70 | G139: =VLOOKUP($B139, Paste!$A$3:$H$933, 8, FALSE) -> WAS | H139: =VLOOKUP($B139, Paste!$A$3:$H$933, 2, FALSE) -> 80.666667 | I139: =VLOOKUP($B139, Paste!$A$3:$H$933, 3, FALSE) -> 20.851508 | J139: =K139-I139 -> 35.21453 | K139: =VLOOKUP($B139, Paste!$A$3:$H$933, 4, FALSE) -> 56.066038 | L139: =IF(ISBLANK(VLOOKUP(B139, 'SOG&PlusMinus'!$B$7:$E$912, 3, FALSE)), "", VLOOKUP(B139,'SOG&PlusMinus'!$B$7:$E$912, 3, FALSE)) -> A | M139: =IF(ISBLANK(VLOOKUP(B139, 'SOG&PlusMinus'!$B$7:$E$912, 4, FALSE)), "", VLOOKUP(B139, 'SOG&PlusMinus'!$B$7:$E$912, 4, FALSE)) -> 1 | N139: =VLOOKUP($B139, Paste!$A$3:$H$933, 5, FALSE) -> 59.474576 | O139: =IF(ISERROR(VLOOKUP(B139, Paste!$AB$3:$AE$2349, 3, FALSE)), "", VLOOKUP(B139, Paste!$AB$3:$AE$2349, 3, FALSE)) -> 65 | P139: =IF(ISERROR(VLOOKUP(B139, Paste!$AB$3:$AC$2343, 2, FALSE)), "", VLOOKUP(B139, Paste!$AB$3:$AC$2343, 2, FALSE)) -> 113 | Q139: =IF(ISERROR(VLOOKUP(B139, Paste!$AB$3:$AE$2349, 4, FALSE)), "", VLOOKUP(B139, Paste!$AB$3:$AE$2349, 4, FALSE)) -> 218 | R139: =IF(ISERROR(VLOOKUP(B139, Paste!$N$3:$N$250, 1, FALSE)), "", VLOOKUP(B139, Paste!$N$3:$O$250, 2, FALSE)) | S139: =VLOOKUP($B139, Paste!$W$3:$Z$10064, IF($H$4="Cap Hit",3, IF($H$4="AAV", 4, 2)), FALSE) -> 9 | T139: =IF(ISERROR(VLOOKUP(B139, Paste!$Q$3:$Q$245, 1, FALSE)), "", VLOOKUP(B139, Paste!$Q$3:$R$245, 2, FALSE)) | U139: =IF(VLOOKUP(B139, 'Points&Potential'!$B$7:$O$943, 14, FALSE)=0, "", VLOOKUP(B139, 'Points&Potential'!$B$7:$O$943, 14, FALSE)) | V139: =IF(ISERROR(VLOOKUP(B139, Paste!$T$3:$T$1045, 1, FALSE)), "", VLOOKUP(B139, Paste!$T$3:$U$1144, 2, FALSE))
A140: 134 | B140: Ryan Nugent-Hopkins | C140: =VLOOKUP(B140, Paste!$AG$3:$AH$2083, 2, FALSE) -> 33.2 | D140: =VLOOKUP($B140, Paste!$A$3:$H$933, 6, FALSE) -> LW | E140: =IFERROR(VLOOKUP($B140, Paste!$J$3:$L$933, 3, FALSE), "") -> 62 | F140: =IFERROR(VLOOKUP($B140, Paste!$J$3:$L$933, 2, FALSE), "") -> 85 | G140: =VLOOKUP($B140, Paste!$A$3:$H$933, 8, FALSE) -> EDM | H140: =VLOOKUP($B140, Paste!$A$3:$H$933, 2, FALSE) -> 78 | I140: =VLOOKUP($B140, Paste!$A$3:$H$933, 3, FALSE) -> 19.333417 | J140: =K140-I140 -> 36.666917 | K140: =VLOOKUP($B140, Paste!$A$3:$H$933, 4, FALSE) -> 56.000334 | L140: =IF(ISBLANK(VLOOKUP(B140, 'SOG&PlusMinus'!$B$7:$E$912, 3, FALSE)), "", VLOOKUP(B140,'SOG&PlusMinus'!$B$7:$E$912, 3, FALSE)) -> D | M140: =IF(ISBLANK(VLOOKUP(B140, 'SOG&PlusMinus'!$B$7:$E$912, 4, FALSE)), "", VLOOKUP(B140, 'SOG&PlusMinus'!$B$7:$E$912, 4, FALSE)) -> 1 | N140: =VLOOKUP($B140, Paste!$A$3:$H$933, 5, FALSE) -> 27.469565 | O140: =IF(ISERROR(VLOOKUP(B140, Paste!$AB$3:$AE$2349, 3, FALSE)), "", VLOOKUP(B140, Paste!$AB$3:$AE$2349, 3, FALSE)) -> 23 | P140: =IF(ISERROR(VLOOKUP(B140, Paste!$AB$3:$AC$2343, 2, FALSE)), "", VLOOKUP(B140, Paste!$AB$3:$AC$2343, 2, FALSE)) -> 35 | Q140: =IF(ISERROR(VLOOKUP(B140, Paste!$AB$3:$AE$2349, 4, FALSE)), "", VLOOKUP(B140, Paste!$AB$3:$AE$2349, 4, FALSE)) -> 148 | R140: =IF(ISERROR(VLOOKUP(B140, Paste!$N$3:$N$250, 1, FALSE)), "", VLOOKUP(B140, Paste!$N$3:$O$250, 2, FALSE)) | S140: =VLOOKUP($B140, Paste!$W$3:$Z$10064, IF($H$4="Cap Hit",3, IF($H$4="AAV", 4, 2)), FALSE) -> 5.125 | T140: =IF(ISERROR(VLOOKUP(B140, Paste!$Q$3:$Q$245, 1, FALSE)), "", VLOOKUP(B140, Paste!$Q$3:$R$245, 2, FALSE)) | U140: =IF(VLOOKUP(B140, 'Points&Potential'!$B$7:$O$943, 14, FALSE)=0, "", VLOOKUP(B140, 'Points&Potential'!$B$7:$O$943, 14, FALSE)) | V140: =IF(ISERROR(VLOOKUP(B140, Paste!$T$3:$T$1045, 1, FALSE)), "", VLOOKUP(B140, Paste!$T$3:$U$1144, 2, FALSE))
A141: 135 | B141: Evgeni Malkin | C141: =VLOOKUP(B141, Paste!$AG$3:$AH$2083, 2, FALSE) -> 39.9 | D141: =VLOOKUP($B141, Paste!$A$3:$H$933, 6, FALSE) -> RW | E141: =IFERROR(VLOOKUP($B141, Paste!$J$3:$L$933, 3, FALSE), "") -> 53 | F141: =IFERROR(VLOOKUP($B141, Paste!$J$3:$L$933, 2, FALSE), "") -> 73 | G141: =VLOOKUP($B141, Paste!$A$3:$H$933, 8, FALSE) -> PIT | H141: =VLOOKUP($B141, Paste!$A$3:$H$933, 2, FALSE) -> 70.666667 | I141: =VLOOKUP($B141, Paste!$A$3:$H$933, 3, FALSE) -> 21.609133 | J141: =K141-I141 -> 34.141072 | K141: =VLOOKUP($B141, Paste!$A$3:$H$933, 4, FALSE) -> 55.750205 | L141: =IF(ISBLANK(VLOOKUP(B141, 'SOG&PlusMinus'!$B$7:$E$912, 3, FALSE)), "", VLOOKUP(B141,'SOG&PlusMinus'!$B$7:$E$912, 3, FALSE)) -> C | M141: =IF(ISBLANK(VLOOKUP(B141, 'SOG&PlusMinus'!$B$7:$E$912, 4, FALSE)), "", VLOOKUP(B141, 'SOG&PlusMinus'!$B$7:$E$912, 4, FALSE)) -> 1 | N141: =VLOOKUP($B141, Paste!$A$3:$H$933, 5, FALSE) -> 59.346278 | O141: =IF(ISERROR(VLOOKUP(B141, Paste!$AB$3:$AE$2349, 3, FALSE)), "", VLOOKUP(B141, Paste!$AB$3:$AE$2349, 3, FALSE)) -> 25 | P141: =IF(ISERROR(VLOOKUP(B141, Paste!$AB$3:$AC$2343, 2, FALSE)), "", VLOOKUP(B141, Paste!$AB$3:$AC$2343, 2, FALSE)) -> 18 | Q141: =IF(ISERROR(VLOOKUP(B141, Paste!$AB$3:$AE$2349, 4, FALSE)), "", VLOOKUP(B141, Paste!$AB$3:$AE$2349, 4, FALSE)) -> 163 | R141: =IF(ISERROR(VLOOKUP(B141, Paste!$N$3:$N$250, 1, FALSE)), "", VLOOKUP(B141, Paste!$N$3:$O$250, 2, FALSE)) | S141: =VLOOKUP($B141, Paste!$W$3:$Z$10064, IF($H$4="Cap Hit",3, IF($H$4="AAV", 4, 2)), FALSE) -> 9 | T141: =IF(ISERROR(VLOOKUP(B141, Paste!$Q$3:$Q$245, 1, FALSE)), "", VLOOKUP(B141, Paste!$Q$3:$R$245, 2, FALSE)) -> Y | U141: =IF(VLOOKUP(B141, 'Points&Potential'!$B$7:$O$943, 14, FALSE)=0, "", VLOOKUP(B141, 'Points&Potential'!$B$7:$O$943, 14, FALSE)) | V141: =IF(ISERROR(VLOOKUP(B141, Paste!$T$3:$T$1045, 1, FALSE)), "", VLOOKUP(B141, Paste!$T$3:$U$1144, 2, FALSE))
A142: 136 | B142: Roman Kantserov | C142: =VLOOKUP(B142, Paste!$AG$3:$AH$2083, 2, FALSE) -> 21.7 | D142: =VLOOKUP($B142, Paste!$A$3:$H$933, 6, FALSE) -> LW | E142: =IFERROR(VLOOKUP($B142, Paste!$J$3:$L$933, 3, FALSE), "") -> 60 | F142: =IFERROR(VLOOKUP($B142, Paste!$J$3:$L$933, 2, FALSE), "") -> 82 | G142: =VLOOKUP($B142, Paste!$A$3:$H$933, 8, FALSE) -> CHI | H142: =VLOOKUP($B142, Paste!$A$3:$H$933, 2, FALSE) -> 82.333333 | I142: =VLOOKUP($B142, Paste!$A$3:$H$933, 3, FALSE) -> 26.226353 | J142: =K142-I142 -> 29.162302 | K142: =VLOOKUP($B142, Paste!$A$3:$H$933, 4, FALSE) -> 55.388656 | L142: =IF(ISBLANK(VLOOKUP(B142, 'SOG&PlusMinus'!$B$7:$E$912, 3, FALSE)), "", VLOOKUP(B142,'SOG&PlusMinus'!$B$7:$E$912, 3, FALSE)) -> D | M142: =IF(ISBLANK(VLOOKUP(B142, 'SOG&PlusMinus'!$B$7:$E$912, 4, FALSE)), "", VLOOKUP(B142, 'SOG&PlusMinus'!$B$7:$E$912, 4, FALSE)) -> 1 | N142: =VLOOKUP($B142, Paste!$A$3:$H$933, 5, FALSE) -> 41.166667 | O142: =IF(ISERROR(VLOOKUP(B142, Paste!$AB$3:$AE$2349, 3, FALSE)), "", VLOOKUP(B142, Paste!$AB$3:$AE$2349, 3, FALSE)) -> 66 | P142: =IF(ISERROR(VLOOKUP(B142, Paste!$AB$3:$AC$2343, 2, FALSE)), "", VLOOKUP(B142, Paste!$AB$3:$AC$2343, 2, FALSE)) -> 33 | Q142: =IF(ISERROR(VLOOKUP(B142, Paste!$AB$3:$AE$2349, 4, FALSE)), "", VLOOKUP(B142, Paste!$AB$3:$AE$2349, 4, FALSE)) -> 173 | R142: =IF(ISERROR(VLOOKUP(B142, Paste!$N$3:$N$250, 1, FALSE)), "", VLOOKUP(B142, Paste!$N$3:$O$250, 2, FALSE)) -> 65 | S142: =VLOOKUP($B142, Paste!$W$3:$Z$10064, IF($H$4="Cap Hit",3, IF($H$4="AAV", 4, 2)), FALSE) -> 4.575 | T142: =IF(ISERROR(VLOOKUP(B142, Paste!$Q$3:$Q$245, 1, FALSE)), "", VLOOKUP(B142, Paste!$Q$3:$R$245, 2, FALSE)) | U142: =IF(VLOOKUP(B142, 'Points&Potential'!$B$7:$O$943, 14, FALSE)=0, "", VLOOKUP(B142, 'Points&Potential'!$B$7:$O$943, 14, FALSE)) | V142: =IF(ISERROR(VLOOKUP(B142, Paste!$T$3:$T$1045, 1, FALSE)), "", VLOOKUP(B142, Paste!$T$3:$U$1144, 2, FALSE)) -> Y
A143: 137 | B143: Matvei Gridin | C143: =VLOOKUP(B143, Paste!$AG$3:$AH$2083, 2, FALSE) -> 20.3 | D143: =VLOOKUP($B143, Paste!$A$3:$H$933, 6, FALSE) -> LW | E143: =IFERROR(VLOOKUP($B143, Paste!$J$3:$L$933, 3, FALSE), "") -> 63 | F143: =IFERROR(VLOOKUP($B143, Paste!$J$3:$L$933, 2, FALSE), "") -> 78 | G143: =VLOOKUP($B143, Paste!$A$3:$H$933, 8, FALSE) -> CGY | H143: =VLOOKUP($B143, Paste!$A$3:$H$933, 2, FALSE) -> 81 | I143: =VLOOKUP($B143, Paste!$A$3:$H$933, 3, FALSE) -> 18.63 | J143: =K143-I143 -> 36.723375 | K143: =VLOOKUP($B143, Paste!$A$3:$H$933, 4, FALSE) -> 55.353375 | L143: =IF(ISBLANK(VLOOKUP(B143, 'SOG&PlusMinus'!$B$7:$E$912, 3, FALSE)), "", VLOOKUP(B143,'SOG&PlusMinus'!$B$7:$E$912, 3, FALSE)) -> D | M143: =IF(ISBLANK(VLOOKUP(B143, 'SOG&PlusMinus'!$B$7:$E$912, 4, FALSE)), "", VLOOKUP(B143, 'SOG&PlusMinus'!$B$7:$E$912, 4, FALSE)) -> 1 | N143: =VLOOKUP($B143, Paste!$A$3:$H$933, 5, FALSE) -> 28.35 | O143: =IF(ISERROR(VLOOKUP(B143, Paste!$AB$3:$AE$2349, 3, FALSE)), "", VLOOKUP(B143, Paste!$AB$3:$AE$2349, 3, FALSE)) -> 29 | P143: =IF(ISERROR(VLOOKUP(B143, Paste!$AB$3:$AC$2343, 2, FALSE)), "", VLOOKUP(B143, Paste!$AB$3:$AC$2343, 2, FALSE)) -> 57 | Q143: =IF(ISERROR(VLOOKUP(B143, Paste!$AB$3:$AE$2349, 4, FALSE)), "", VLOOKUP(B143, Paste!$AB$3:$AE$2349, 4, FALSE)) -> 170 | R143: =IF(ISERROR(VLOOKUP(B143, Paste!$N$3:$N$250, 1, FALSE)), "", VLOOKUP(B143, Paste!$N$3:$O$250, 2, FALSE)) -> 60 | S143: =VLOOKUP($B143, Paste!$W$3:$Z$10064, IF($H$4="Cap Hit",3, IF($H$4="AAV", 4, 2)), FALSE) -> 0.9425 | T143: =IF(ISERROR(VLOOKUP(B143, Paste!$Q$3:$Q$245, 1, FALSE)), "", VLOOKUP(B143, Paste!$Q$3:$R$245, 2, FALSE)) | U143: =IF(VLOOKUP(B143, 'Points&Potential'!$B$7:$O$943, 14, FALSE)=0, "", VLOOKUP(B143, 'Points&Potential'!$B$7:$O$943, 14, FALSE)) | V143: =IF(ISERROR(VLOOKUP(B143, Paste!$T$3:$T$1045, 1, FALSE)), "", VLOOKUP(B143, Paste!$T$3:$U$1144, 2, FALSE))
A144: 138 | B144: Alex Tuch | C144: =VLOOKUP(B144, Paste!$AG$3:$AH$2083, 2, FALSE) -> 30.1 | D144: =VLOOKUP($B144, Paste!$A$3:$H$933, 6, FALSE) -> RW | E144: =IFERROR(VLOOKUP($B144, Paste!$J$3:$L$933, 3, FALSE), "") -> 62 | F144: =IFERROR(VLOOKUP($B144, Paste!$J$3:$L$933, 2, FALSE), "") -> 80 | G144: =VLOOKUP($B144, Paste!$A$3:$H$933, 8, FALSE) -> WAS | H144: =VLOOKUP($B144, Paste!$A$3:$H$933, 2, FALSE) -> 80.666667 | I144: =VLOOKUP($B144, Paste!$A$3:$H$933, 3, FALSE) -> 32.266667 | J144: =K144-I144 -> 22.836733 | K144: =VLOOKUP($B144, Paste!$A$3:$H$933, 4, FALSE) -> 55.1034 | L144: =IF(ISBLANK(VLOOKUP(B144, 'SOG&PlusMinus'!$B$7:$E$912, 3, FALSE)), "", VLOOKUP(B144,'SOG&PlusMinus'!$B$7:$E$912, 3, FALSE)) -> C | M144: =IF(ISBLANK(VLOOKUP(B144, 'SOG&PlusMinus'!$B$7:$E$912, 4, FALSE)), "", VLOOKUP(B144, 'SOG&PlusMinus'!$B$7:$E$912, 4, FALSE)) -> 2 | N144: =VLOOKUP($B144, Paste!$A$3:$H$933, 5, FALSE) -> 54.00565 | O144: =IF(ISERROR(VLOOKUP(B144, Paste!$AB$3:$AE$2349, 3, FALSE)), "", VLOOKUP(B144, Paste!$AB$3:$AE$2349, 3, FALSE)) -> 81 | P144: =IF(ISERROR(VLOOKUP(B144, Paste!$AB$3:$AC$2343, 2, FALSE)), "", VLOOKUP(B144, Paste!$AB$3:$AC$2343, 2, FALSE)) -> 97 | Q144: =IF(ISERROR(VLOOKUP(B144, Paste!$AB$3:$AE$2349, 4, FALSE)), "", VLOOKUP(B144, Paste!$AB$3:$AE$2349, 4, FALSE)) -> 202 | R144: =IF(ISERROR(VLOOKUP(B144, Paste!$N$3:$N$250, 1, FALSE)), "", VLOOKUP(B144, Paste!$N$3:$O$250, 2, FALSE)) | S144: =VLOOKUP($B144, Paste!$W$3:$Z$10064, IF($H$4="Cap Hit",3, IF($H$4="AAV", 4, 2)), FALSE) -> 10.5 | T144: =IF(ISERROR(VLOOKUP(B144, Paste!$Q$3:$Q$245, 1, FALSE)), "", VLOOKUP(B144, Paste!$Q$3:$R$245, 2, FALSE)) | U144: =IF(VLOOKUP(B144, 'Points&Potential'!$B$7:$O$943, 14, FALSE)=0, "", VLOOKUP(B144, 'Points&Potential'!$B$7:$O$943, 14, FALSE)) | V144: =IF(ISERROR(VLOOKUP(B144, Paste!$T$3:$T$1045, 1, FALSE)), "", VLOOKUP(B144, Paste!$T$3:$U$1144, 2, FALSE))
A145: 139 | B145: Alex Ovechkin | C145: =VLOOKUP(B145, Paste!$AG$3:$AH$2083, 2, FALSE) -> 40.7 | D145: =VLOOKUP($B145, Paste!$A$3:$H$933, 6, FALSE) -> LW | E145: =IFERROR(VLOOKUP($B145, Paste!$J$3:$L$933, 3, FALSE), "") -> 58 | F145: =IFERROR(VLOOKUP($B145, Paste!$J$3:$L$933, 2, FALSE), "") -> 70 | G145: =VLOOKUP($B145, Paste!$A$3:$H$933, 8, FALSE) -> WAS | H145: =VLOOKUP($B145, Paste!$A$3:$H$933, 2, FALSE) -> 77.333333 | I145: =VLOOKUP($B145, Paste!$A$3:$H$933, 3, FALSE) -> 28.613333 | J145: =K145-I145 -> 26.301776 | K145: =VLOOKUP($B145, Paste!$A$3:$H$933, 4, FALSE) -> 54.915109 | L145: =IF(ISBLANK(VLOOKUP(B145, 'SOG&PlusMinus'!$B$7:$E$912, 3, FALSE)), "", VLOOKUP(B145,'SOG&PlusMinus'!$B$7:$E$912, 3, FALSE)) -> C | M145: =IF(ISBLANK(VLOOKUP(B145, 'SOG&PlusMinus'!$B$7:$E$912, 4, FALSE)), "", VLOOKUP(B145, 'SOG&PlusMinus'!$B$7:$E$912, 4, FALSE)) -> 1 | N145: =VLOOKUP($B145, Paste!$A$3:$H$933, 5, FALSE) -> 20.530973 | O145: =IF(ISERROR(VLOOKUP(B145, Paste!$AB$3:$AE$2349, 3, FALSE)), "", VLOOKUP(B145, Paste!$AB$3:$AE$2349, 3, FALSE)) -> 120 | P145: =IF(ISERROR(VLOOKUP(B145, Paste!$AB$3:$AC$2343, 2, FALSE)), "", VLOOKUP(B145, Paste!$AB$3:$AC$2343, 2, FALSE)) -> 15 | Q145: =IF(ISERROR(VLOOKUP(B145, Paste!$AB$3:$AE$2349, 4, FALSE)), "", VLOOKUP(B145, Paste!$AB$3:$AE$2349, 4, FALSE)) -> 224 | R145: =IF(ISERROR(VLOOKUP(B145, Paste!$N$3:$N$250, 1, FALSE)), "", VLOOKUP(B145, Paste!$N$3:$O$250, 2, FALSE)) | S145: =VLOOKUP($B145, Paste!$W$3:$Z$10064, IF($H$4="Cap Hit",3, IF($H$4="AAV", 4, 2)), FALSE) -> 9 | T145: =IF(ISERROR(VLOOKUP(B145, Paste!$Q$3:$Q$245, 1, FALSE)), "", VLOOKUP(B145, Paste!$Q$3:$R$245, 2, FALSE)) | U145: =IF(VLOOKUP(B145, 'Points&Potential'!$B$7:$O$943, 14, FALSE)=0, "", VLOOKUP(B145, 'Points&Potential'!$B$7:$O$943, 14, FALSE)) | V145: =IF(ISERROR(VLOOKUP(B145, Paste!$T$3:$T$1045, 1, FALSE)), "", VLOOKUP(B145, Paste!$T$3:$U$1144, 2, FALSE))
A146: 140 | B146: Tomas Hertl | C146: =VLOOKUP(B146, Paste!$AG$3:$AH$2083, 2, FALSE) -> 32.6 | D146: =VLOOKUP($B146, Paste!$A$3:$H$933, 6, FALSE) -> C | E146: =IFERROR(VLOOKUP($B146, Paste!$J$3:$L$933, 3, FALSE), "") -> 65 | F146: =IFERROR(VLOOKUP($B146, Paste!$J$3:$L$933, 2, FALSE), "") -> 77 | G146: =VLOOKUP($B146, Paste!$A$3:$H$933, 8, FALSE) -> VGK | H146: =VLOOKUP($B146, Paste!$A$3:$H$933, 2, FALSE) -> 75 | I146: =VLOOKUP($B146, Paste!$A$3:$H$933, 3, FALSE) -> 26.461423 | J146: =K146-I146 -> 28.394111 | K146: =VLOOKUP($B146, Paste!$A$3:$H$933, 4, FALSE) -> 54.855533 | L146: =IF(ISBLANK(VLOOKUP(B146, 'SOG&PlusMinus'!$B$7:$E$912, 3, FALSE)), "", VLOOKUP(B146,'SOG&PlusMinus'!$B$7:$E$912, 3, FALSE)) -> D | M146: =IF(ISBLANK(VLOOKUP(B146, 'SOG&PlusMinus'!$B$7:$E$912, 4, FALSE)), "", VLOOKUP(B146, 'SOG&PlusMinus'!$B$7:$E$912, 4, FALSE)) -> 1 | N146: =VLOOKUP($B146, Paste!$A$3:$H$933, 5, FALSE) -> 29.066986 | O146: =IF(ISERROR(VLOOKUP(B146, Paste!$AB$3:$AE$2349, 3, FALSE)), "", VLOOKUP(B146, Paste!$AB$3:$AE$2349, 3, FALSE)) -> 98 | P146: =IF(ISERROR(VLOOKUP(B146, Paste!$AB$3:$AC$2343, 2, FALSE)), "", VLOOKUP(B146, Paste!$AB$3:$AC$2343, 2, FALSE)) -> 45 | Q146: =IF(ISERROR(VLOOKUP(B146, Paste!$AB$3:$AE$2349, 4, FALSE)), "", VLOOKUP(B146, Paste!$AB$3:$AE$2349, 4, FALSE)) -> 180 | R146: =IF(ISERROR(VLOOKUP(B146, Paste!$N$3:$N$250, 1, FALSE)), "", VLOOKUP(B146, Paste!$N$3:$O$250, 2, FALSE)) | S146: =VLOOKUP($B146, Paste!$W$3:$Z$10064, IF($H$4="Cap Hit",3, IF($H$4="AAV", 4, 2)), FALSE) -> 8.1375 | T146: =IF(ISERROR(VLOOKUP(B146, Paste!$Q$3:$Q$245, 1, FALSE)), "", VLOOKUP(B146, Paste!$Q$3:$R$245, 2, FALSE)) | U146: =IF(VLOOKUP(B146, 'Points&Potential'!$B$7:$O$943, 14, FALSE)=0, "", VLOOKUP(B146, 'Points&Potential'!$B$7:$O$943, 14, FALSE)) | V146: =IF(ISERROR(VLOOKUP(B146, Paste!$T$3:$T$1045, 1, FALSE)), "", VLOOKUP(B146, Paste!$T$3:$U$1144, 2, FALSE))
A147: 141 | B147: Igor Chernyshov | C147: =VLOOKUP(B147, Paste!$AG$3:$AH$2083, 2, FALSE) -> 20.5 | D147: =VLOOKUP($B147, Paste!$A$3:$H$933, 6, FALSE) -> LW | E147: =IFERROR(VLOOKUP($B147, Paste!$J$3:$L$933, 3, FALSE), "") -> 65 | F147: =IFERROR(VLOOKUP($B147, Paste!$J$3:$L$933, 2, FALSE), "") -> 85 | G147: =VLOOKUP($B147, Paste!$A$3:$H$933, 8, FALSE) -> SJS | H147: =VLOOKUP($B147, Paste!$A$3:$H$933, 2, FALSE) -> 77 | I147: =VLOOKUP($B147, Paste!$A$3:$H$933, 3, FALSE) -> 16.751034 | J147: =K147-I147 -> 37.943038 | K147: =VLOOKUP($B147, Paste!$A$3:$H$933, 4, FALSE) -> 54.694072 | L147: =IF(ISBLANK(VLOOKUP(B147, 'SOG&PlusMinus'!$B$7:$E$912, 3, FALSE)), "", VLOOKUP(B147,'SOG&PlusMinus'!$B$7:$E$912, 3, FALSE)) -> C | M147: =IF(ISBLANK(VLOOKUP(B147, 'SOG&PlusMinus'!$B$7:$E$912, 4, FALSE)), "", VLOOKUP(B147, 'SOG&PlusMinus'!$B$7:$E$912, 4, FALSE)) -> 2 | N147: =VLOOKUP($B147, Paste!$A$3:$H$933, 5, FALSE) -> 34.65 | O147: =IF(ISERROR(VLOOKUP(B147, Paste!$AB$3:$AE$2349, 3, FALSE)), "", VLOOKUP(B147, Paste!$AB$3:$AE$2349, 3, FALSE)) -> 52 | P147: =IF(ISERROR(VLOOKUP(B147, Paste!$AB$3:$AC$2343, 2, FALSE)), "", VLOOKUP(B147, Paste!$AB$3:$AC$2343, 2, FALSE)) -> 39 | Q147: =IF(ISERROR(VLOOKUP(B147, Paste!$AB$3:$AE$2349, 4, FALSE)), "", VLOOKUP(B147, Paste!$AB$3:$AE$2349, 4, FALSE)) -> 139 | R147: =IF(ISERROR(VLOOKUP(B147, Paste!$N$3:$N$250, 1, FALSE)), "", VLOOKUP(B147, Paste!$N$3:$O$250, 2, FALSE)) -> 65 | S147: =VLOOKUP($B147, Paste!$W$3:$Z$10064, IF($H$4="Cap Hit",3, IF($H$4="AAV", 4, 2)), FALSE) -> 0.9425 | T147: =IF(ISERROR(VLOOKUP(B147, Paste!$Q$3:$Q$245, 1, FALSE)), "", VLOOKUP(B147, Paste!$Q$3:$R$245, 2, FALSE)) | U147: =IF(VLOOKUP(B147, 'Points&Potential'!$B$7:$O$943, 14, FALSE)=0, "", VLOOKUP(B147, 'Points&Potential'!$B$7:$O$943, 14, FALSE)) | V147: =IF(ISERROR(VLOOKUP(B147, Paste!$T$3:$T$1045, 1, FALSE)), "", VLOOKUP(B147, Paste!$T$3:$U$1144, 2, FALSE))
A148: 142 | B148: Tyler Bertuzzi | C148: =VLOOKUP(B148, Paste!$AG$3:$AH$2083, 2, FALSE) -> 31.3 | D148: =VLOOKUP($B148, Paste!$A$3:$H$933, 6, FALSE) -> RW | E148: =IFERROR(VLOOKUP($B148, Paste!$J$3:$L$933, 3, FALSE), "") -> 50 | F148: =IFERROR(VLOOKUP($B148, Paste!$J$3:$L$933, 2, FALSE), "") -> 65 | G148: =VLOOKUP($B148, Paste!$A$3:$H$933, 8, FALSE) -> CHI | H148: =VLOOKUP($B148, Paste!$A$3:$H$933, 2, FALSE) -> 82.333333 | I148: =VLOOKUP($B148, Paste!$A$3:$H$933, 3, FALSE) -> 32.933333 | J148: =K148-I148 -> 21.682921 | K148: =VLOOKUP($B148, Paste!$A$3:$H$933, 4, FALSE) -> 54.616254 | L148: =IF(ISBLANK(VLOOKUP(B148, 'SOG&PlusMinus'!$B$7:$E$912, 3, FALSE)), "", VLOOKUP(B148,'SOG&PlusMinus'!$B$7:$E$912, 3, FALSE)) -> D | M148: =IF(ISBLANK(VLOOKUP(B148, 'SOG&PlusMinus'!$B$7:$E$912, 4, FALSE)), "", VLOOKUP(B148, 'SOG&PlusMinus'!$B$7:$E$912, 4, FALSE)) -> 1 | N148: =VLOOKUP($B148, Paste!$A$3:$H$933, 5, FALSE) -> 49.878285 | O148: =IF(ISERROR(VLOOKUP(B148, Paste!$AB$3:$AE$2349, 3, FALSE)), "", VLOOKUP(B148, Paste!$AB$3:$AE$2349, 3, FALSE)) -> 58 | P148: =IF(ISERROR(VLOOKUP(B148, Paste!$AB$3:$AC$2343, 2, FALSE)), "", VLOOKUP(B148, Paste!$AB$3:$AC$2343, 2, FALSE)) -> 26 | Q148: =IF(ISERROR(VLOOKUP(B148, Paste!$AB$3:$AE$2349, 4, FALSE)), "", VLOOKUP(B148, Paste!$AB$3:$AE$2349, 4, FALSE)) -> 173 | R148: =IF(ISERROR(VLOOKUP(B148, Paste!$N$3:$N$250, 1, FALSE)), "", VLOOKUP(B148, Paste!$N$3:$O$250, 2, FALSE)) | S148: =VLOOKUP($B148, Paste!$W$3:$Z$10064, IF($H$4="Cap Hit",3, IF($H$4="AAV", 4, 2)), FALSE) -> 5.5 | T148: =IF(ISERROR(VLOOKUP(B148, Paste!$Q$3:$Q$245, 1, FALSE)), "", VLOOKUP(B148, Paste!$Q$3:$R$245, 2, FALSE)) | U148: =IF(VLOOKUP(B148, 'Points&Potential'!$B$7:$O$943, 14, FALSE)=0, "", VLOOKUP(B148, 'Points&Potential'!$B$7:$O$943, 14, FALSE)) | V148: =IF(ISERROR(VLOOKUP(B148, Paste!$T$3:$T$1045, 1, FALSE)), "", VLOOKUP(B148, Paste!$T$3:$U$1144, 2, FALSE))
A149: 143 | B149: Charlie McAvoy | C149: =VLOOKUP(B149, Paste!$AG$3:$AH$2083, 2, FALSE) -> 28.5 | D149: =VLOOKUP($B149, Paste!$A$3:$H$933, 6, FALSE) -> RD | E149: =IFERROR(VLOOKUP($B149, Paste!$J$3:$L$933, 3, FALSE), "") -> 58 | F149: =IFERROR(VLOOKUP($B149, Paste!$J$3:$L$933, 2, FALSE), "") -> 73 | G149: =VLOOKUP($B149, Paste!$A$3:$H$933, 8, FALSE) -> BOS | H149: =VLOOKUP($B149, Paste!$A$3:$H$933, 2, FALSE) -> 66.333333 | I149: =VLOOKUP($B149, Paste!$A$3:$H$933, 3, FALSE) -> 10.141688 | J149: =K149-I149 -> 44.263292 | K149: =VLOOKUP($B149, Paste!$A$3:$H$933, 4, FALSE) -> 54.40498 | L149: =IF(ISBLANK(VLOOKUP(B149, 'SOG&PlusMinus'!$B$7:$E$912, 3, FALSE)), "", VLOOKUP(B149,'SOG&PlusMinus'!$B$7:$E$912, 3, FALSE)) -> B | M149: =IF(ISBLANK(VLOOKUP(B149, 'SOG&PlusMinus'!$B$7:$E$912, 4, FALSE)), "", VLOOKUP(B149, 'SOG&PlusMinus'!$B$7:$E$912, 4, FALSE)) -> 1 | N149: =VLOOKUP($B149, Paste!$A$3:$H$933, 5, FALSE) -> 66.677029 | O149: =IF(ISERROR(VLOOKUP(B149, Paste!$AB$3:$AE$2349, 3, FALSE)), "", VLOOKUP(B149, Paste!$AB$3:$AE$2349, 3, FALSE)) -> 86 | P149: =IF(ISERROR(VLOOKUP(B149, Paste!$AB$3:$AC$2343, 2, FALSE)), "", VLOOKUP(B149, Paste!$AB$3:$AC$2343, 2, FALSE)) -> 127 | Q149: =IF(ISERROR(VLOOKUP(B149, Paste!$AB$3:$AE$2349, 4, FALSE)), "", VLOOKUP(B149, Paste!$AB$3:$AE$2349, 4, FALSE)) -> 119 | R149: =IF(ISERROR(VLOOKUP(B149, Paste!$N$3:$N$250, 1, FALSE)), "", VLOOKUP(B149, Paste!$N$3:$O$250, 2, FALSE)) | S149: =VLOOKUP($B149, Paste!$W$3:$Z$10064, IF($H$4="Cap Hit",3, IF($H$4="AAV", 4, 2)), FALSE) -> 9.5 | T149: =IF(ISERROR(VLOOKUP(B149, Paste!$Q$3:$Q$245, 1, FALSE)), "", VLOOKUP(B149, Paste!$Q$3:$R$245, 2, FALSE)) -> Y | U149: =IF(VLOOKUP(B149, 'Points&Potential'!$B$7:$O$943, 14, FALSE)=0, "", VLOOKUP(B149, 'Points&Potential'!$B$7:$O$943, 14, FALSE)) | V149: =IF(ISERROR(VLOOKUP(B149, Paste!$T$3:$T$1045, 1, FALSE)), "", VLOOKUP(B149, Paste!$T$3:$U$1144, 2, FALSE))
A150: 144 | B150: Moritz Seider | C150: =VLOOKUP(B150, Paste!$AG$3:$AH$2083, 2, FALSE) -> 25.2 | D150: =VLOOKUP($B150, Paste!$A$3:$H$933, 6, FALSE) -> RD | E150: =IFERROR(VLOOKUP($B150, Paste!$J$3:$L$933, 3, FALSE), "") -> 57 | F150: =IFERROR(VLOOKUP($B150, Paste!$J$3:$L$933, 2, FALSE), "") -> 73 | G150: =VLOOKUP($B150, Paste!$A$3:$H$933, 8, FALSE) -> DET | H150: =VLOOKUP($B150, Paste!$A$3:$H$933, 2, FALSE) -> 84 | I150: =VLOOKUP($B150, Paste!$A$3:$H$933, 3, FALSE) -> 9.840738 | J150: =K150-I150 -> 44.509801 | K150: =VLOOKUP($B150, Paste!$A$3:$H$933, 4, FALSE) -> 54.350539 | L150: =IF(ISBLANK(VLOOKUP(B150, 'SOG&PlusMinus'!$B$7:$E$912, 3, FALSE)), "", VLOOKUP(B150,'SOG&PlusMinus'!$B$7:$E$912, 3, FALSE)) -> A | M150: =IF(ISBLANK(VLOOKUP(B150, 'SOG&PlusMinus'!$B$7:$E$912, 4, FALSE)), "", VLOOKUP(B150, 'SOG&PlusMinus'!$B$7:$E$912, 4, FALSE)) -> 1 | N150: =VLOOKUP($B150, Paste!$A$3:$H$933, 5, FALSE) -> 50.536585 | O150: =IF(ISERROR(VLOOKUP(B150, Paste!$AB$3:$AE$2349, 3, FALSE)), "", VLOOKUP(B150, Paste!$AB$3:$AE$2349, 3, FALSE)) -> 151 | P150: =IF(ISERROR(VLOOKUP(B150, Paste!$AB$3:$AC$2343, 2, FALSE)), "", VLOOKUP(B150, Paste!$AB$3:$AC$2343, 2, FALSE)) -> 180 | Q150: =IF(ISERROR(VLOOKUP(B150, Paste!$AB$3:$AE$2349, 4, FALSE)), "", VLOOKUP(B150, Paste!$AB$3:$AE$2349, 4, FALSE)) -> 202 | R150: =IF(ISERROR(VLOOKUP(B150, Paste!$N$3:$N$250, 1, FALSE)), "", VLOOKUP(B150, Paste!$N$3:$O$250, 2, FALSE)) | S150: =VLOOKUP($B150, Paste!$W$3:$Z$10064, IF($H$4="Cap Hit",3, IF($H$4="AAV", 4, 2)), FALSE) -> 8.55 | T150: =IF(ISERROR(VLOOKUP(B150, Paste!$Q$3:$Q$245, 1, FALSE)), "", VLOOKUP(B150, Paste!$Q$3:$R$245, 2, FALSE)) | U150: =IF(VLOOKUP(B150, 'Points&Potential'!$B$7:$O$943, 14, FALSE)=0, "", VLOOKUP(B150, 'Points&Potential'!$B$7:$O$943, 14, FALSE)) | V150: =IF(ISERROR(VLOOKUP(B150, Paste!$T$3:$T$1045, 1, FALSE)), "", VLOOKUP(B150, Paste!$T$3:$U$1144, 2, FALSE))
... A162: 156 | B162: Roman Josi | C162: =VLOOKUP(B162, Paste!$AG$3:$AH$2083, 2, FALSE) -> 36 | D162: =VLOOKUP($B162, Paste!$A$3:$H$933, 6, FALSE) -> LD | E162: =IFERROR(VLOOKUP($B162, Paste!$J$3:$L$933, 3, FALSE), "") -> 48 | F162: =IFERROR(VLOOKUP($B162, Paste!$J$3:$L$933, 2, FALSE), "") -> 68 | G162: =VLOOKUP($B162, Paste!$A$3:$H$933, 8, FALSE) -> NSH | H162: =VLOOKUP($B162, Paste!$A$3:$H$933, 2, FALSE) -> 69.666667 | I162: =VLOOKUP($B162, Paste!$A$3:$H$933, 3, FALSE) -> 14.247702 | J162: =K162-I162 -> 37.997491 | K162: =VLOOKUP($B162, Paste!$A$3:$H$933, 4, FALSE) -> 52.245193 | L162: =IF(ISBLANK(VLOOKUP(B162, 'SOG&PlusMinus'!$B$7:$E$912, 3, FALSE)), "", VLOOKUP(B162,'SOG&PlusMinus'!$B$7:$E$912, 3, FALSE)) -> D | M162: =IF(ISBLANK(VLOOKUP(B162, 'SOG&PlusMinus'!$B$7:$E$912, 4, FALSE)), "", VLOOKUP(B162, 'SOG&PlusMinus'!$B$7:$E$912, 4, FALSE)) -> 1 | N162: =VLOOKUP($B162, Paste!$A$3:$H$933, 5, FALSE) -> 31.916256 | O162: =IF(ISERROR(VLOOKUP(B162, Paste!$AB$3:$AE$2349, 3, FALSE)), "", VLOOKUP(B162, Paste!$AB$3:$AE$2349, 3, FALSE)) -> 28 | P162: =IF(ISERROR(VLOOKUP(B162, Paste!$AB$3:$AC$2343, 2, FALSE)), "", VLOOKUP(B162, Paste!$AB$3:$AC$2343, 2, FALSE)) -> 101 | Q162: =IF(ISERROR(VLOOKUP(B162, Paste!$AB$3:$AE$2349, 4, FALSE)), "", VLOOKUP(B162, Paste!$AB$3:$AE$2349, 4, FALSE)) -> 181 | R162: =IF(ISERROR(VLOOKUP(B162, Paste!$N$3:$N$250, 1, FALSE)), "", VLOOKUP(B162, Paste!$N$3:$O$250, 2, FALSE)) | S162: =VLOOKUP($B162, Paste!$W$3:$Z$10064, IF($H$4="Cap Hit",3, IF($H$4="AAV", 4, 2)), FALSE) -> 9.059 | T162: =IF(ISERROR(VLOOKUP(B162, Paste!$Q$3:$Q$245, 1, FALSE)), "", VLOOKUP(B162, Paste!$Q$3:$R$245, 2, FALSE)) -> Y | U162: =IF(VLOOKUP(B162, 'Points&Potential'!$B$7:$O$943, 14, FALSE)=0, "", VLOOKUP(B162, 'Points&Potential'!$B$7:$O$943, 14, FALSE)) | V162: =IF(ISERROR(VLOOKUP(B162, Paste!$T$3:$T$1045, 1, FALSE)), "", VLOOKUP(B162, Paste!$T$3:$U$1144, 2, FALSE))
A163: 157 | B163: Anton Lundell | C163: =VLOOKUP(B163, Paste!$AG$3:$AH$2083, 2, FALSE) -> 24.7 | D163: =VLOOKUP($B163, Paste!$A$3:$H$933, 6, FALSE) -> C | E163: =IFERROR(VLOOKUP($B163, Paste!$J$3:$L$933, 3, FALSE), "") -> 62 | F163: =IFERROR(VLOOKUP($B163, Paste!$J$3:$L$933, 2, FALSE), "") -> 82 | G163: =VLOOKUP($B163, Paste!$A$3:$H$933, 8, FALSE) -> FLA | H163: =VLOOKUP($B163, Paste!$A$3:$H$933, 2, FALSE) -> 75.666667 | I163: =VLOOKUP($B163, Paste!$A$3:$H$933, 3, FALSE) -> 18.916667 | J163: =K163-I163 -> 33.312266 | K163: =VLOOKUP($B163, Paste!$A$3:$H$933, 4, FALSE) -> 52.228932 | L163: =IF(ISBLANK(VLOOKUP(B163, 'SOG&PlusMinus'!$B$7:$E$912, 3, FALSE)), "", VLOOKUP(B163,'SOG&PlusMinus'!$B$7:$E$912, 3, FALSE)) -> C | M163: =IF(ISBLANK(VLOOKUP(B163, 'SOG&PlusMinus'!$B$7:$E$912, 4, FALSE)), "", VLOOKUP(B163, 'SOG&PlusMinus'!$B$7:$E$912, 4, FALSE)) -> 2 | N163: =VLOOKUP($B163, Paste!$A$3:$H$933, 5, FALSE) -> 39.71644 | O163: =IF(ISERROR(VLOOKUP(B163, Paste!$AB$3:$AE$2349, 3, FALSE)), "", VLOOKUP(B163, Paste!$AB$3:$AE$2349, 3, FALSE)) -> 97 | P163: =IF(ISERROR(VLOOKUP(B163, Paste!$AB$3:$AC$2343, 2, FALSE)), "", VLOOKUP(B163, Paste!$AB$3:$AC$2343, 2, FALSE)) -> 45 | Q163: =IF(ISERROR(VLOOKUP(B163, Paste!$AB$3:$AE$2349, 4, FALSE)), "", VLOOKUP(B163, Paste!$AB$3:$AE$2349, 4, FALSE)) -> 159 | R163: =IF(ISERROR(VLOOKUP(B163, Paste!$N$3:$N$250, 1, FALSE)), "", VLOOKUP(B163, Paste!$N$3:$O$250, 2, FALSE)) | S163: =VLOOKUP($B163, Paste!$W$3:$Z$10064, IF($H$4="Cap Hit",3, IF($H$4="AAV", 4, 2)), FALSE) -> 5 | U163: =IF(VLOOKUP(B163, 'Points&Potential'!$B$7:$O$943, 14, FALSE)=0, "", VLOOKUP(B163, 'Points&Potential'!$B$7:$O$943, 14, FALSE)) | V163: =IF(ISERROR(VLOOKUP(B163, Paste!$T$3:$T$1045, 1, FALSE)), "", VLOOKUP(B163, Paste!$T$3:$U$1144, 2, FALSE))
A164: 158 | B164: Mikael Granlund | C164: =VLOOKUP(B164, Paste!$AG$3:$AH$2083, 2, FALSE) -> 34.3 | D164: =VLOOKUP($B164, Paste!$A$3:$H$933, 6, FALSE) -> C | E164: =IFERROR(VLOOKUP($B164, Paste!$J$3:$L$933, 3, FALSE), "") -> 52 | F164: =IFERROR(VLOOKUP($B164, Paste!$J$3:$L$933, 2, FALSE), "") -> 65 | G164: =VLOOKUP($B164, Paste!$A$3:$H$933, 8, FALSE) -> ANA | H164: =VLOOKUP($B164, Paste!$A$3:$H$933, 2, FALSE) -> 72 | I164: =VLOOKUP($B164, Paste!$A$3:$H$933, 3, FALSE) -> 18.443338 | J164: =K164-I164 -> 33.525914 | K164: =VLOOKUP($B164, Paste!$A$3:$H$933, 4, FALSE) -> 51.969251 | L164: =IF(ISBLANK(VLOOKUP(B164, 'SOG&PlusMinus'!$B$7:$E$912, 3, FALSE)), "", VLOOKUP(B164,'SOG&PlusMinus'!$B$7:$E$912, 3, FALSE)) -> D | M164: =IF(ISBLANK(VLOOKUP(B164, 'SOG&PlusMinus'!$B$7:$E$912, 4, FALSE)), "", VLOOKUP(B164, 'SOG&PlusMinus'!$B$7:$E$912, 4, FALSE)) -> 1 | N164: =VLOOKUP($B164, Paste!$A$3:$H$933, 5, FALSE) -> 26.742857 | O164: =IF(ISERROR(VLOOKUP(B164, Paste!$AB$3:$AE$2349, 3, FALSE)), "", VLOOKUP(B164, Paste!$AB$3:$AE$2349, 3, FALSE)) -> 36 | P164: =IF(ISERROR(VLOOKUP(B164, Paste!$AB$3:$AC$2343, 2, FALSE)), "", VLOOKUP(B164, Paste!$AB$3:$AC$2343, 2, FALSE)) -> 50 | Q164: =IF(ISERROR(VLOOKUP(B164, Paste!$AB$3:$AE$2349, 4, FALSE)), "", VLOOKUP(B164, Paste!$AB$3:$AE$2349, 4, FALSE)) -> 137 | R164: =IF(ISERROR(VLOOKUP(B164, Paste!$N$3:$N$250, 1, FALSE)), "", VLOOKUP(B164, Paste!$N$3:$O$250, 2, FALSE)) | S164: =VLOOKUP($B164, Paste!$W$3:$Z$10064, IF($H$4="Cap Hit",3, IF($H$4="AAV", 4, 2)), FALSE) -> 7 | T164: =IF(ISERROR(VLOOKUP(B164, Paste!$Q$3:$Q$245, 1, FALSE)), "", VLOOKUP(B164, Paste!$Q$3:$R$245, 2, FALSE)) -> Y | U164: =IF(VLOOKUP(B164, 'Points&Potential'!$B$7:$O$943, 14, FALSE)=0, "", VLOOKUP(B164, 'Points&Potential'!$B$7:$O$943, 14, FALSE)) | V164: =IF(ISERROR(VLOOKUP(B164, Paste!$T$3:$T$1045, 1, FALSE)), "", VLOOKUP(B164, Paste!$T$3:$U$1144, 2, FALSE))
A165: 159 | B165: Gabe Perreault | C165: =VLOOKUP(B165, Paste!$AG$3:$AH$2083, 2, FALSE) -> 21.1 | D165: =VLOOKUP($B165, Paste!$A$3:$H$933, 6, FALSE) -> LW | E165: =IFERROR(VLOOKUP($B165, Paste!$J$3:$L$933, 3, FALSE), "") -> 60 | F165: =IFERROR(VLOOKUP($B165, Paste!$J$3:$L$933, 2, FALSE), "") -> 82 | G165: =VLOOKUP($B165, Paste!$A$3:$H$933, 8, FALSE) -> NYR | H165: =VLOOKUP($B165, Paste!$A$3:$H$933, 2, FALSE) -> 79 | I165: =VLOOKUP($B165, Paste!$A$3:$H$933, 3, FALSE) -> 19.75 | J165: =K165-I165 -> 31.86679 | K165: =VLOOKUP($B165, Paste!$A$3:$H$933, 4, FALSE) -> 51.61679 | L165: =IF(ISBLANK(VLOOKUP(B165, 'SOG&PlusMinus'!$B$7:$E$912, 3, FALSE)), "", VLOOKUP(B165,'SOG&PlusMinus'!$B$7:$E$912, 3, FALSE)) -> C | M165: =IF(ISBLANK(VLOOKUP(B165, 'SOG&PlusMinus'!$B$7:$E$912, 4, FALSE)), "", VLOOKUP(B165, 'SOG&PlusMinus'!$B$7:$E$912, 4, FALSE)) -> 2 | N165: =VLOOKUP($B165, Paste!$A$3:$H$933, 5, FALSE) -> 23.7 | O165: =IF(ISERROR(VLOOKUP(B165, Paste!$AB$3:$AE$2349, 3, FALSE)), "", VLOOKUP(B165, Paste!$AB$3:$AE$2349, 3, FALSE)) -> 44 | P165: =IF(ISERROR(VLOOKUP(B165, Paste!$AB$3:$AC$2343, 2, FALSE)), "", VLOOKUP(B165, Paste!$AB$3:$AC$2343, 2, FALSE)) -> 40 | Q165: =IF(ISERROR(VLOOKUP(B165, Paste!$AB$3:$AE$2349, 4, FALSE)), "", VLOOKUP(B165, Paste!$AB$3:$AE$2349, 4, FALSE)) -> 134 | R165: =IF(ISERROR(VLOOKUP(B165, Paste!$N$3:$N$250, 1, FALSE)), "", VLOOKUP(B165, Paste!$N$3:$O$250, 2, FALSE)) -> 65 | S165: =VLOOKUP($B165, Paste!$W$3:$Z$10064, IF($H$4="Cap Hit",3, IF($H$4="AAV", 4, 2)), FALSE) -> 1.233333 | T165: =IF(ISERROR(VLOOKUP(B165, Paste!$Q$3:$Q$245, 1, FALSE)), "", VLOOKUP(B165, Paste!$Q$3:$R$245, 2, FALSE)) | U165: =IF(VLOOKUP(B165, 'Points&Potential'!$B$7:$O$943, 14, FALSE)=0, "", VLOOKUP(B165, 'Points&Potential'!$B$7:$O$943, 14, FALSE)) | V165: =IF(ISERROR(VLOOKUP(B165, Paste!$T$3:$T$1045, 1, FALSE)), "", VLOOKUP(B165, Paste!$T$3:$U$1144, 2, FALSE))
A166: 160 | B166: Brett Howden | C166: =VLOOKUP(B166, Paste!$AG$3:$AH$2083, 2, FALSE) -> 28.2 | D166: =VLOOKUP($B166, Paste!$A$3:$H$933, 6, FALSE) -> LW | E166: =IFERROR(VLOOKUP($B166, Paste!$J$3:$L$933, 3, FALSE), "") -> 47 | F166: =IFERROR(VLOOKUP($B166, Paste!$J$3:$L$933, 2, FALSE), "") -> 58 | G166: =VLOOKUP($B166, Paste!$A$3:$H$933, 8, FALSE) -> VGK | H166: =VLOOKUP($B166, Paste!$A$3:$H$933, 2, FALSE) -> 75 | I166: =VLOOKUP($B166, Paste!$A$3:$H$933, 3, FALSE) -> 22.5 | J166: =K166-I166 -> 28.948556 | K166: =VLOOKUP($B166, Paste!$A$3:$H$933, 4, FALSE) -> 51.448556 | L166: =IF(ISBLANK(VLOOKUP(B166, 'SOG&PlusMinus'!$B$7:$E$912, 3, FALSE)), "", VLOOKUP(B166,'SOG&PlusMinus'!$B$7:$E$912, 3, FALSE)) -> C | M166: =IF(ISBLANK(VLOOKUP(B166, 'SOG&PlusMinus'!$B$7:$E$912, 4, FALSE)), "", VLOOKUP(B166, 'SOG&PlusMinus'!$B$7:$E$912, 4, FALSE)) -> 2 | N166: =VLOOKUP($B166, Paste!$A$3:$H$933, 5, FALSE) -> 45 | O166: =IF(ISERROR(VLOOKUP(B166, Paste!$AB$3:$AE$2349, 3, FALSE)), "", VLOOKUP(B166, Paste!$AB$3:$AE$2349, 3, FALSE)) -> 122 | P166: =IF(ISERROR(VLOOKUP(B166, Paste!$AB$3:$AC$2343, 2, FALSE)), "", VLOOKUP(B166, Paste!$AB$3:$AC$2343, 2, FALSE)) -> 34 | Q166: =IF(ISERROR(VLOOKUP(B166, Paste!$AB$3:$AE$2349, 4, FALSE)), "", VLOOKUP(B166, Paste!$AB$3:$AE$2349, 4, FALSE)) -> 113 | R166: =IF(ISERROR(VLOOKUP(B166, Paste!$N$3:$N$250, 1, FALSE)), "", VLOOKUP(B166, Paste!$N$3:$O$250, 2, FALSE)) -> 60 | S166: =VLOOKUP($B166, Paste!$W$3:$Z$10064, IF($H$4="Cap Hit",3, IF($H$4="AAV", 4, 2)), FALSE) -> 2.5 | T166: =IF(ISERROR(VLOOKUP(B166, Paste!$Q$3:$Q$245, 1, FALSE)), "", VLOOKUP(B166, Paste!$Q$3:$R$245, 2, FALSE)) -> Y | U166: =IF(VLOOKUP(B166, 'Points&Potential'!$B$7:$O$943, 14, FALSE)=0, "", VLOOKUP(B166, 'Points&Potential'!$B$7:$O$943, 14, FALSE)) | V166: =IF(ISERROR(VLOOKUP(B166, Paste!$T$3:$T$1045, 1, FALSE)), "", VLOOKUP(B166, Paste!$T$3:$U$1144, 2, FALSE))
A167: 161 | B167: Chandler Stephenson | C167: =VLOOKUP(B167, Paste!$AG$3:$AH$2083, 2, FALSE) -> 32.1 | D167: =VLOOKUP($B167, Paste!$A$3:$H$933, 6, FALSE) -> C | E167: =IFERROR(VLOOKUP($B167, Paste!$J$3:$L$933, 3, FALSE), "") -> 52 | F167: =IFERROR(VLOOKUP($B167, Paste!$J$3:$L$933, 2, FALSE), "") -> 65 | G167: =VLOOKUP($B167, Paste!$A$3:$H$933, 8, FALSE) -> SEA | H167: =VLOOKUP($B167, Paste!$A$3:$H$933, 2, FALSE) -> 79.666667 | I167: =VLOOKUP($B167, Paste!$A$3:$H$933, 3, FALSE) -> 15.933333 | J167: =K167-I167 -> 34.947028 | K167: =VLOOKUP($B167, Paste!$A$3:$H$933, 4, FALSE) -> 50.880361 | L167: =IF(ISBLANK(VLOOKUP(B167, 'SOG&PlusMinus'!$B$7:$E$912, 3, FALSE)), "", VLOOKUP(B167,'SOG&PlusMinus'!$B$7:$E$912, 3, FALSE)) -> D | M167: =IF(ISBLANK(VLOOKUP(B167, 'SOG&PlusMinus'!$B$7:$E$912, 4, FALSE)), "", VLOOKUP(B167, 'SOG&PlusMinus'!$B$7:$E$912, 4, FALSE)) -> 2 | N167: =VLOOKUP($B167, Paste!$A$3:$H$933, 5, FALSE) -> 21.540773 | O167: =IF(ISERROR(VLOOKUP(B167, Paste!$AB$3:$AE$2349, 3, FALSE)), "", VLOOKUP(B167, Paste!$AB$3:$AE$2349, 3, FALSE)) -> 24 | P167: =IF(ISERROR(VLOOKUP(B167, Paste!$AB$3:$AC$2343, 2, FALSE)), "", VLOOKUP(B167, Paste!$AB$3:$AC$2343, 2, FALSE)) -> 50 | Q167: =IF(ISERROR(VLOOKUP(B167, Paste!$AB$3:$AE$2349, 4, FALSE)), "", VLOOKUP(B167, Paste!$AB$3:$AE$2349, 4, FALSE)) -> 88 | R167: =IF(ISERROR(VLOOKUP(B167, Paste!$N$3:$N$250, 1, FALSE)), "", VLOOKUP(B167, Paste!$N$3:$O$250, 2, FALSE)) | S167: =VLOOKUP($B167, Paste!$W$3:$Z$10064, IF($H$4="Cap Hit",3, IF($H$4="AAV", 4, 2)), FALSE) -> 6.25 | T167: =IF(ISERROR(VLOOKUP(B167, Paste!$Q$3:$Q$245, 1, FALSE)), "", VLOOKUP(B167, Paste!$Q$3:$R$245, 2, FALSE)) | U167: =IF(VLOOKUP(B167, 'Points&Potential'!$B$7:$O$943, 14, FALSE)=0, "", VLOOKUP(B167, 'Points&Potential'!$B$7:$O$943, 14, FALSE)) | V167: =IF(ISERROR(VLOOKUP(B167, Paste!$T$3:$T$1045, 1, FALSE)), "", VLOOKUP(B167, Paste!$T$3:$U$1144, 2, FALSE))
A168: 162 | B168: Egor Chinakhov | C168: =VLOOKUP(B168, Paste!$AG$3:$AH$2083, 2, FALSE) -> 25.4 | D168: =VLOOKUP($B168, Paste!$A$3:$H$933, 6, FALSE) -> LW | E168: =IFERROR(VLOOKUP($B168, Paste!$J$3:$L$933, 3, FALSE), "") | F168: =IFERROR(VLOOKUP($B168, Paste!$J$3:$L$933, 2, FALSE), "") | G168: =VLOOKUP($B168, Paste!$A$3:$H$933, 8, FALSE) -> PIT | H168: =VLOOKUP($B168, Paste!$A$3:$H$933, 2, FALSE) -> 71 | I168: =VLOOKUP($B168, Paste!$A$3:$H$933, 3, FALSE) -> 21.3 | J168: =K168-I168 -> 29.338088 | K168: =VLOOKUP($B168, Paste!$A$3:$H$933, 4, FALSE) -> 50.638088 | L168: =IF(ISBLANK(VLOOKUP(B168, 'SOG&PlusMinus'!$B$7:$E$912, 3, FALSE)), "", VLOOKUP(B168,'SOG&PlusMinus'!$B$7:$E$912, 3, FALSE)) -> C | M168: =IF(ISBLANK(VLOOKUP(B168, 'SOG&PlusMinus'!$B$7:$E$912, 4, FALSE)), "", VLOOKUP(B168, 'SOG&PlusMinus'!$B$7:$E$912, 4, FALSE)) -> 2 | N168: =VLOOKUP($B168, Paste!$A$3:$H$933, 5, FALSE) -> 9.1612903 | O168: =IF(ISERROR(VLOOKUP(B168, Paste!$AB$3:$AE$2349, 3, FALSE)), "", VLOOKUP(B168, Paste!$AB$3:$AE$2349, 3, FALSE)) -> 57 | P168: =IF(ISERROR(VLOOKUP(B168, Paste!$AB$3:$AC$2343, 2, FALSE)), "", VLOOKUP(B168, Paste!$AB$3:$AC$2343, 2, FALSE)) -> 32 | Q168: =IF(ISERROR(VLOOKUP(B168, Paste!$AB$3:$AE$2349, 4, FALSE)), "", VLOOKUP(B168, Paste!$AB$3:$AE$2349, 4, FALSE)) -> 149 | R168: =IF(ISERROR(VLOOKUP(B168, Paste!$N$3:$N$250, 1, FALSE)), "", VLOOKUP(B168, Paste!$N$3:$O$250, 2, FALSE)) | S168: =VLOOKUP($B168, Paste!$W$3:$Z$10064, IF($H$4="Cap Hit",3, IF($H$4="AAV", 4, 2)), FALSE) -> 6.25 | T168: =IF(ISERROR(VLOOKUP(B168, Paste!$Q$3:$Q$245, 1, FALSE)), "", VLOOKUP(B168, Paste!$Q$3:$R$245, 2, FALSE)) -> Y | U168: =IF(VLOOKUP(B168, 'Points&Potential'!$B$7:$O$943, 14, FALSE)=0, "", VLOOKUP(B168, 'Points&Potential'!$B$7:$O$943, 14, FALSE)) | V168: =IF(ISERROR(VLOOKUP(B168, Paste!$T$3:$T$1045, 1, FALSE)), "", VLOOKUP(B168, Paste!$T$3:$U$1144, 2, FALSE))
A169: 163 | B169: Christian Dvorak | C169: =VLOOKUP(B169, Paste!$AG$3:$AH$2083, 2, FALSE) -> 30.4 | D169: =VLOOKUP($B169, Paste!$A$3:$H$933, 6, FALSE) -> C | E169: =IFERROR(VLOOKUP($B169, Paste!$J$3:$L$933, 3, FALSE), "") | F169: =IFERROR(VLOOKUP($B169, Paste!$J$3:$L$933, 2, FALSE), "") | G169: =VLOOKUP($B169, Paste!$A$3:$H$933, 8, FALSE) -> PHI | H169: =VLOOKUP($B169, Paste!$A$3:$H$933, 2, FALSE) -> 79 | I169: =VLOOKUP($B169, Paste!$A$3:$H$933, 3, FALSE) -> 17.38 | J169: =K169-I169 -> 32.993323 | K169: =VLOOKUP($B169, Paste!$A$3:$H$933, 4, FALSE) -> 50.373323 | L169: =IF(ISBLANK(VLOOKUP(B169, 'SOG&PlusMinus'!$B$7:$E$912, 3, FALSE)), "", VLOOKUP(B169,'SOG&PlusMinus'!$B$7:$E$912, 3, FALSE)) -> B | M169: =IF(ISBLANK(VLOOKUP(B169, 'SOG&PlusMinus'!$B$7:$E$912, 4, FALSE)), "", VLOOKUP(B169, 'SOG&PlusMinus'!$B$7:$E$912, 4, FALSE)) -> 2 | N169: =VLOOKUP($B169, Paste!$A$3:$H$933, 5, FALSE) -> 22.12 | O169: =IF(ISERROR(VLOOKUP(B169, Paste!$AB$3:$AE$2349, 3, FALSE)), "", VLOOKUP(B169, Paste!$AB$3:$AE$2349, 3, FALSE)) -> 36 | P169: =IF(ISERROR(VLOOKUP(B169, Paste!$AB$3:$AC$2343, 2, FALSE)), "", VLOOKUP(B169, Paste!$AB$3:$AC$2343, 2, FALSE)) -> 55 | Q169: =IF(ISERROR(VLOOKUP(B169, Paste!$AB$3:$AE$2349, 4, FALSE)), "", VLOOKUP(B169, Paste!$AB$3:$AE$2349, 4, FALSE)) -> 142 | R169: =IF(ISERROR(VLOOKUP(B169, Paste!$N$3:$N$250, 1, FALSE)), "", VLOOKUP(B169, Paste!$N$3:$O$250, 2, FALSE)) | S169: =VLOOKUP($B169, Paste!$W$3:$Z$10064, IF($H$4="Cap Hit",3, IF($H$4="AAV", 4, 2)), FALSE) -> 5.15 | T169: =IF(ISERROR(VLOOKUP(B169, Paste!$Q$3:$Q$245, 1, FALSE)), "", VLOOKUP(B169, Paste!$Q$3:$R$245, 2, FALSE)) | U169: =IF(VLOOKUP(B169, 'Points&Potential'!$B$7:$O$943, 14, FALSE)=0, "", VLOOKUP(B169, 'Points&Potential'!$B$7:$O$943, 14, FALSE)) | V169: =IF(ISERROR(VLOOKUP(B169, Paste!$T$3:$T$1045, 1, FALSE)), "", VLOOKUP(B169, Paste!$T$3:$U$1144, 2, FALSE))
A170: 164 | B170: Anthony Cirelli | C170: =VLOOKUP(B170, Paste!$AG$3:$AH$2083, 2, FALSE) -> 28.9 | D170: =VLOOKUP($B170, Paste!$A$3:$H$933, 6, FALSE) -> C | E170: =IFERROR(VLOOKUP($B170, Paste!$J$3:$L$933, 3, FALSE), "") -> 55 | F170: =IFERROR(VLOOKUP($B170, Paste!$J$3:$L$933, 2, FALSE), "") -> 70 | G170: =VLOOKUP($B170, Paste!$A$3:$H$933, 8, FALSE) -> TBL | H170: =VLOOKUP($B170, Paste!$A$3:$H$933, 2, FALSE) -> 78.666667 | I170: =VLOOKUP($B170, Paste!$A$3:$H$933, 3, FALSE) -> 24.221956 | J170: =K170-I170 -> 26.036535 | K170: =VLOOKUP($B170, Paste!$A$3:$H$933, 4, FALSE) -> 50.258491 | L170: =IF(ISBLANK(VLOOKUP(B170, 'SOG&PlusMinus'!$B$7:$E$912, 3, FALSE)), "", VLOOKUP(B170,'SOG&PlusMinus'!$B$7:$E$912, 3, FALSE)) -> A | M170: =IF(ISBLANK(VLOOKUP(B170, 'SOG&PlusMinus'!$B$7:$E$912, 4, FALSE)), "", VLOOKUP(B170, 'SOG&PlusMinus'!$B$7:$E$912, 4, FALSE)) -> 2 | N170: =VLOOKUP($B170, Paste!$A$3:$H$933, 5, FALSE) -> 38.991304 | O170: =IF(ISERROR(VLOOKUP(B170, Paste!$AB$3:$AE$2349, 3, FALSE)), "", VLOOKUP(B170, Paste!$AB$3:$AE$2349, 3, FALSE)) -> 48 | P170: =IF(ISERROR(VLOOKUP(B170, Paste!$AB$3:$AC$2343, 2, FALSE)), "", VLOOKUP(B170, Paste!$AB$3:$AC$2343, 2, FALSE)) -> 55 | Q170: =IF(ISERROR(VLOOKUP(B170, Paste!$AB$3:$AE$2349, 4, FALSE)), "", VLOOKUP(B170, Paste!$AB$3:$AE$2349, 4, FALSE)) -> 142 | R170: =IF(ISERROR(VLOOKUP(B170, Paste!$N$3:$N$250, 1, FALSE)), "", VLOOKUP(B170, Paste!$N$3:$O$250, 2, FALSE)) | S170: =VLOOKUP($B170, Paste!$W$3:$Z$10064, IF($H$4="Cap Hit",3, IF($H$4="AAV", 4, 2)), FALSE) -> 6.25 | T170: =IF(ISERROR(VLOOKUP(B170, Paste!$Q$3:$Q$245, 1, FALSE)), "", VLOOKUP(B170, Paste!$Q$3:$R$245, 2, FALSE)) | U170: =IF(VLOOKUP(B170, 'Points&Potential'!$B$7:$O$943, 14, FALSE)=0, "", VLOOKUP(B170, 'Points&Potential'!$B$7:$O$943, 14, FALSE)) | V170: =IF(ISERROR(VLOOKUP(B170, Paste!$T$3:$T$1045, 1, FALSE)), "", VLOOKUP(B170, Paste!$T$3:$U$1144, 2, FALSE))
A171: 165 | B171: Jonathan Huberdeau | C171: =VLOOKUP(B171, Paste!$AG$3:$AH$2083, 2, FALSE) -> 33 | D171: =VLOOKUP($B171, Paste!$A$3:$H$933, 6, FALSE) -> LW | E171: =IFERROR(VLOOKUP($B171, Paste!$J$3:$L$933, 3, FALSE), "") -> 50 | F171: =IFERROR(VLOOKUP($B171, Paste!$J$3:$L$933, 2, FALSE), "") -> 67 | G171: =VLOOKUP($B171, Paste!$A$3:$H$933, 8, FALSE) -> CGY | H171: =VLOOKUP($B171, Paste!$A$3:$H$933, 2, FALSE) -> 78 | I171: =VLOOKUP($B171, Paste!$A$3:$H$933, 3, FALSE) -> 17.665871 | J171: =K171-I171 -> 32.512058 | K171: =VLOOKUP($B171, Paste!$A$3:$H$933, 4, FALSE) -> 50.177929 | L171: =IF(ISBLANK(VLOOKUP(B171, 'SOG&PlusMinus'!$B$7:$E$912, 3, FALSE)), "", VLOOKUP(B171,'SOG&PlusMinus'!$B$7:$E$912, 3, FALSE)) -> D | M171: =IF(ISBLANK(VLOOKUP(B171, 'SOG&PlusMinus'!$B$7:$E$912, 4, FALSE)), "", VLOOKUP(B171, 'SOG&PlusMinus'!$B$7:$E$912, 4, FALSE)) -> 1 | N171: =VLOOKUP($B171, Paste!$A$3:$H$933, 5, FALSE) -> 45.622642 | O171: =IF(ISERROR(VLOOKUP(B171, Paste!$AB$3:$AE$2349, 3, FALSE)), "", VLOOKUP(B171, Paste!$AB$3:$AE$2349, 3, FALSE)) -> 43 | P171: =IF(ISERROR(VLOOKUP(B171, Paste!$AB$3:$AC$2343, 2, FALSE)), "", VLOOKUP(B171, Paste!$AB$3:$AC$2343, 2, FALSE)) -> 39 | Q171: =IF(ISERROR(VLOOKUP(B171, Paste!$AB$3:$AE$2349, 4, FALSE)), "", VLOOKUP(B171, Paste!$AB$3:$AE$2349, 4, FALSE)) -> 133 | R171: =IF(ISERROR(VLOOKUP(B171, Paste!$N$3:$N$250, 1, FALSE)), "", VLOOKUP(B171, Paste!$N$3:$O$250, 2, FALSE)) | S171: =VLOOKUP($B171, Paste!$W$3:$Z$10064, IF($H$4="Cap Hit",3, IF($H$4="AAV", 4, 2)), FALSE) -> 10.5 | T171: =IF(ISERROR(VLOOKUP(B171, Paste!$Q$3:$Q$245, 1, FALSE)), "", VLOOKUP(B171, Paste!$Q$3:$R$245, 2, FALSE)) | U171: =IF(VLOOKUP(B171, 'Points&Potential'!$B$7:$O$943, 14, FALSE)=0, "", VLOOKUP(B171, 'Points&Potential'!$B$7:$O$943, 14, FALSE)) | V171: =IF(ISERROR(VLOOKUP(B171, Paste!$T$3:$T$1045, 1, FALSE)), "", VLOOKUP(B171, Paste!$T$3:$U$1144, 2, FALSE))
A172: 166 | B172: Owen Tippett | C172: =VLOOKUP(B172, Paste!$AG$3:$AH$2083, 2, FALSE) -> 27.3 | D172: =VLOOKUP($B172, Paste!$A$3:$H$933, 6, FALSE) -> RW | E172: =IFERROR(VLOOKUP($B172, Paste!$J$3:$L$933, 3, FALSE), "") -> 58 | F172: =IFERROR(VLOOKUP($B172, Paste!$J$3:$L$933, 2, FALSE), "") -> 73 | G172: =VLOOKUP($B172, Paste!$A$3:$H$933, 8, FALSE) -> PHI | H172: =VLOOKUP($B172, Paste!$A$3:$H$933, 2, FALSE) -> 80.666667 | I172: =VLOOKUP($B172, Paste!$A$3:$H$933, 3, FALSE) -> 26.62 | J172: =K172-I172 -> 23.471035 | K172: =VLOOKUP($B172, Paste!$A$3:$H$933, 4, FALSE) -> 50.091035 | L172: =IF(ISBLANK(VLOOKUP(B172, 'SOG&PlusMinus'!$B$7:$E$912, 3, FALSE)), "", VLOOKUP(B172,'SOG&PlusMinus'!$B$7:$E$912, 3, FALSE)) -> C | M172: =IF(ISBLANK(VLOOKUP(B172, 'SOG&PlusMinus'!$B$7:$E$912, 4, FALSE)), "", VLOOKUP(B172, 'SOG&PlusMinus'!$B$7:$E$912, 4, FALSE)) -> 2 | N172: =VLOOKUP($B172, Paste!$A$3:$H$933, 5, FALSE) -> 20.508475 | O172: =IF(ISERROR(VLOOKUP(B172, Paste!$AB$3:$AE$2349, 3, FALSE)), "", VLOOKUP(B172, Paste!$AB$3:$AE$2349, 3, FALSE)) -> 147 | P172: =IF(ISERROR(VLOOKUP(B172, Paste!$AB$3:$AC$2343, 2, FALSE)), "", VLOOKUP(B172, Paste!$AB$3:$AC$2343, 2, FALSE)) -> 55 | Q172: =IF(ISERROR(VLOOKUP(B172, Paste!$AB$3:$AE$2349, 4, FALSE)), "", VLOOKUP(B172, Paste!$AB$3:$AE$2349, 4, FALSE)) -> 210 | R172: =IF(ISERROR(VLOOKUP(B172, Paste!$N$3:$N$250, 1, FALSE)), "", VLOOKUP(B172, Paste!$N$3:$O$250, 2, FALSE)) | S172: =VLOOKUP($B172, Paste!$W$3:$Z$10064, IF($H$4="Cap Hit",3, IF($H$4="AAV", 4, 2)), FALSE) -> 6.2 | T172: =IF(ISERROR(VLOOKUP(B172, Paste!$Q$3:$Q$245, 1, FALSE)), "", VLOOKUP(B172, Paste!$Q$3:$R$245, 2, FALSE)) | U172: =IF(VLOOKUP(B172, 'Points&Potential'!$B$7:$O$943, 14, FALSE)=0, "", VLOOKUP(B172, 'Points&Potential'!$B$7:$O$943, 14, FALSE)) | V172: =IF(ISERROR(VLOOKUP(B172, Paste!$T$3:$T$1045, 1, FALSE)), "", VLOOKUP(B172, Paste!$T$3:$U$1144, 2, FALSE))
A173: 167 | B173: Cole Hutson | C173: =VLOOKUP(B173, Paste!$AG$3:$AH$2083, 2, FALSE) -> 20 | D173: =VLOOKUP($B173, Paste!$A$3:$H$933, 6, FALSE) -> LD | E173: =IFERROR(VLOOKUP($B173, Paste!$J$3:$L$933, 3, FALSE), "") -> 58 | F173: =IFERROR(VLOOKUP($B173, Paste!$J$3:$L$933, 2, FALSE), "") -> 75 | G173: =VLOOKUP($B173, Paste!$A$3:$H$933, 8, FALSE) -> WAS | H173: =VLOOKUP($B173, Paste!$A$3:$H$933, 2, FALSE) -> 80 | I173: =VLOOKUP($B173, Paste!$A$3:$H$933, 3, FALSE) -> 14.155036 | J173: =K173-I173 -> 35.929089 | K173: =VLOOKUP($B173, Paste!$A$3:$H$933, 4, FALSE) -> 50.084125 | L173: =IF(ISBLANK(VLOOKUP(B173, 'SOG&PlusMinus'!$B$7:$E$912, 3, FALSE)), "", VLOOKUP(B173,'SOG&PlusMinus'!$B$7:$E$912, 3, FALSE)) -> C | M173: =IF(ISBLANK(VLOOKUP(B173, 'SOG&PlusMinus'!$B$7:$E$912, 4, FALSE)), "", VLOOKUP(B173, 'SOG&PlusMinus'!$B$7:$E$912, 4, FALSE)) -> 2 | N173: =VLOOKUP($B173, Paste!$A$3:$H$933, 5, FALSE) -> 48 | O173: =IF(ISERROR(VLOOKUP(B173, Paste!$AB$3:$AE$2349, 3, FALSE)), "", VLOOKUP(B173, Paste!$AB$3:$AE$2349, 3, FALSE)) -> 91 | P173: =IF(ISERROR(VLOOKUP(B173, Paste!$AB$3:$AC$2343, 2, FALSE)), "", VLOOKUP(B173, Paste!$AB$3:$AC$2343, 2, FALSE)) -> 56 | Q173: =IF(ISERROR(VLOOKUP(B173, Paste!$AB$3:$AE$2349, 4, FALSE)), "", VLOOKUP(B173, Paste!$AB$3:$AE$2349, 4, FALSE)) -> 160 | R173: =IF(ISERROR(VLOOKUP(B173, Paste!$N$3:$N$250, 1, FALSE)), "", VLOOKUP(B173, Paste!$N$3:$O$250, 2, FALSE)) -> 55 | S173: =VLOOKUP($B173, Paste!$W$3:$Z$10064, IF($H$4="Cap Hit",3, IF($H$4="AAV", 4, 2)), FALSE) -> 2.229167 | T173: =IF(ISERROR(VLOOKUP(B173, Paste!$Q$3:$Q$245, 1, FALSE)), "", VLOOKUP(B173, Paste!$Q$3:$R$245, 2, FALSE)) | U173: =IF(VLOOKUP(B173, 'Points&Potential'!$B$7:$O$943, 14, FALSE)=0, "", VLOOKUP(B173, 'Points&Potential'!$B$7:$O$943, 14, FALSE)) | V173: =IF(ISERROR(VLOOKUP(B173, Paste!$T$3:$T$1045, 1, FALSE)), "", VLOOKUP(B173, Paste!$T$3:$U$1144, 2, FALSE)) -> Y
A174: 168 | B174: Pavel Buchnevich | C174: =VLOOKUP(B174, Paste!$AG$3:$AH$2083, 2, FALSE) -> 31.2 | D174: =VLOOKUP($B174, Paste!$A$3:$H$933, 6, FALSE) -> LW | E174: =IFERROR(VLOOKUP($B174, Paste!$J$3:$L$933, 3, FALSE), "") -> 53 | F174: =IFERROR(VLOOKUP($B174, Paste!$J$3:$L$933, 2, FALSE), "") -> 70 | G174: =VLOOKUP($B174, Paste!$A$3:$H$933, 8, FALSE) -> STL | H174: =VLOOKUP($B174, Paste!$A$3:$H$933, 2, FALSE) -> 81 | I174: =VLOOKUP($B174, Paste!$A$3:$H$933, 3, FALSE) -> 21.475989 | J174: =K174-I174 -> 28.602109 | K174: =VLOOKUP($B174, Paste!$A$3:$H$933, 4, FALSE) -> 50.078098 | L174: =IF(ISBLANK(VLOOKUP(B174, 'SOG&PlusMinus'!$B$7:$E$912, 3, FALSE)), "", VLOOKUP(B174,'SOG&PlusMinus'!$B$7:$E$912, 3, FALSE)) -> D | M174: =IF(ISBLANK(VLOOKUP(B174, 'SOG&PlusMinus'!$B$7:$E$912, 4, FALSE)), "", VLOOKUP(B174, 'SOG&PlusMinus'!$B$7:$E$912, 4, FALSE)) -> 2 | N174: =VLOOKUP($B174, Paste!$A$3:$H$933, 5, FALSE) -> 33.151899 | O174: =IF(ISERROR(VLOOKUP(B174, Paste!$AB$3:$AE$2349, 3, FALSE)), "", VLOOKUP(B174, Paste!$AB$3:$AE$2349, 3, FALSE)) -> 36 | P174: =IF(ISERROR(VLOOKUP(B174, Paste!$AB$3:$AC$2343, 2, FALSE)), "", VLOOKUP(B174, Paste!$AB$3:$AC$2343, 2, FALSE)) -> 36 | Q174: =IF(ISERROR(VLOOKUP(B174, Paste!$AB$3:$AE$2349, 4, FALSE)), "", VLOOKUP(B174, Paste!$AB$3:$AE$2349, 4, FALSE)) -> 154 | R174: =IF(ISERROR(VLOOKUP(B174, Paste!$N$3:$N$250, 1, FALSE)), "", VLOOKUP(B174, Paste!$N$3:$O$250, 2, FALSE)) | S174: =VLOOKUP($B174, Paste!$W$3:$Z$10064, IF($H$4="Cap Hit",3, IF($H$4="AAV", 4, 2)), FALSE) -> 8 | T174: =IF(ISERROR(VLOOKUP(B174, Paste!$Q$3:$Q$245, 1, FALSE)), "", VLOOKUP(B174, Paste!$Q$3:$R$245, 2, FALSE)) | U174: =IF(VLOOKUP(B174, 'Points&Potential'!$B$7:$O$943, 14, FALSE)=0, "", VLOOKUP(B174, 'Points&Potential'!$B$7:$O$943, 14, FALSE)) | V174: =IF(ISERROR(VLOOKUP(B174, Paste!$T$3:$T$1045, 1, FALSE)), "", VLOOKUP(B174, Paste!$T$3:$U$1144, 2, FALSE))
A175: 169 | B175: Jordan Eberle | C175: =VLOOKUP(B175, Paste!$AG$3:$AH$2083, 2, FALSE) -> 36.1 | D175: =VLOOKUP($B175, Paste!$A$3:$H$933, 6, FALSE) -> RW | E175: =IFERROR(VLOOKUP($B175, Paste!$J$3:$L$933, 3, FALSE), "") -> 45 | F175: =IFERROR(VLOOKUP($B175, Paste!$J$3:$L$933, 2, FALSE), "") -> 65 | G175: =VLOOKUP($B175, Paste!$A$3:$H$933, 8, FALSE) -> SEA | H175: =VLOOKUP($B175, Paste!$A$3:$H$933, 2, FALSE) -> 79 | I175: =VLOOKUP($B175, Paste!$A$3:$H$933, 3, FALSE) -> 19.967568 | J175: =K175-I175 -> 30.101242 | K175: =VLOOKUP($B175, Paste!$A$3:$H$933, 4, FALSE) -> 50.06881 | L175: =IF(ISBLANK(VLOOKUP(B175, 'SOG&PlusMinus'!$B$7:$E$912, 3, FALSE)), "", VLOOKUP(B175,'SOG&PlusMinus'!$B$7:$E$912, 3, FALSE)) -> C | M175: =IF(ISBLANK(VLOOKUP(B175, 'SOG&PlusMinus'!$B$7:$E$912, 4, FALSE)), "", VLOOKUP(B175, 'SOG&PlusMinus'!$B$7:$E$912, 4, FALSE)) -> 1 | N175: =VLOOKUP($B175, Paste!$A$3:$H$933, 5, FALSE) -> 23.305 | O175: =IF(ISERROR(VLOOKUP(B175, Paste!$AB$3:$AE$2349, 3, FALSE)), "", VLOOKUP(B175, Paste!$AB$3:$AE$2349, 3, FALSE)) -> 39 | P175: =IF(ISERROR(VLOOKUP(B175, Paste!$AB$3:$AC$2343, 2, FALSE)), "", VLOOKUP(B175, Paste!$AB$3:$AC$2343, 2, FALSE)) -> 39 | Q175: =IF(ISERROR(VLOOKUP(B175, Paste!$AB$3:$AE$2349, 4, FALSE)), "", VLOOKUP(B175, Paste!$AB$3:$AE$2349, 4, FALSE)) -> 158 | R175: =IF(ISERROR(VLOOKUP(B175, Paste!$N$3:$N$250, 1, FALSE)), "", VLOOKUP(B175, Paste!$N$3:$O$250, 2, FALSE)) | S175: =VLOOKUP($B175, Paste!$W$3:$Z$10064, IF($H$4="Cap Hit",3, IF($H$4="AAV", 4, 2)), FALSE) -> 5.5 | T175: =IF(ISERROR(VLOOKUP(B175, Paste!$Q$3:$Q$245, 1, FALSE)), "", VLOOKUP(B175, Paste!$Q$3:$R$245, 2, FALSE)) | U175: =IF(VLOOKUP(B175, 'Points&Potential'!$B$7:$O$943, 14, FALSE)=0, "", VLOOKUP(B175, 'Points&Potential'!$B$7:$O$943, 14, FALSE)) | V175: =IF(ISERROR(VLOOKUP(B175, Paste!$T$3:$T$1045, 1, FALSE)), "", VLOOKUP(B175, Paste!$T$3:$U$1144, 2, FALSE))
... A188: 182 | B188: Frank Nazar | C188: =VLOOKUP(B188, Paste!$AG$3:$AH$2083, 2, FALSE) -> 22.4 | D188: =VLOOKUP($B188, Paste!$A$3:$H$933, 6, FALSE) -> C | E188: =IFERROR(VLOOKUP($B188, Paste!$J$3:$L$933, 3, FALSE), "") -> 63 | F188: =IFERROR(VLOOKUP($B188, Paste!$J$3:$L$933, 2, FALSE), "") -> 80 | G188: =VLOOKUP($B188, Paste!$A$3:$H$933, 8, FALSE) -> CHI | H188: =VLOOKUP($B188, Paste!$A$3:$H$933, 2, FALSE) -> 72 | I188: =VLOOKUP($B188, Paste!$A$3:$H$933, 3, FALSE) -> 20.16 | J188: =K188-I188 -> 26.776332 | K188: =VLOOKUP($B188, Paste!$A$3:$H$933, 4, FALSE) -> 46.936332 | L188: =IF(ISBLANK(VLOOKUP(B188, 'SOG&PlusMinus'!$B$7:$E$912, 3, FALSE)), "", VLOOKUP(B188,'SOG&PlusMinus'!$B$7:$E$912, 3, FALSE)) -> D | M188: =IF(ISBLANK(VLOOKUP(B188, 'SOG&PlusMinus'!$B$7:$E$912, 4, FALSE)), "", VLOOKUP(B188, 'SOG&PlusMinus'!$B$7:$E$912, 4, FALSE)) -> 2 | N188: =VLOOKUP($B188, Paste!$A$3:$H$933, 5, FALSE) -> 29.508197 | O188: =IF(ISERROR(VLOOKUP(B188, Paste!$AB$3:$AE$2349, 3, FALSE)), "", VLOOKUP(B188, Paste!$AB$3:$AE$2349, 3, FALSE)) -> 41 | P188: =IF(ISERROR(VLOOKUP(B188, Paste!$AB$3:$AC$2343, 2, FALSE)), "", VLOOKUP(B188, Paste!$AB$3:$AC$2343, 2, FALSE)) -> 47 | Q188: =IF(ISERROR(VLOOKUP(B188, Paste!$AB$3:$AE$2349, 4, FALSE)), "", VLOOKUP(B188, Paste!$AB$3:$AE$2349, 4, FALSE)) -> 158 | R188: =IF(ISERROR(VLOOKUP(B188, Paste!$N$3:$N$250, 1, FALSE)), "", VLOOKUP(B188, Paste!$N$3:$O$250, 2, FALSE)) | S188: =VLOOKUP($B188, Paste!$W$3:$Z$10064, IF($H$4="Cap Hit",3, IF($H$4="AAV", 4, 2)), FALSE) -> 6.599991 | T188: =IF(ISERROR(VLOOKUP(B188, Paste!$Q$3:$Q$245, 1, FALSE)), "", VLOOKUP(B188, Paste!$Q$3:$R$245, 2, FALSE)) -> Y | U188: =IF(VLOOKUP(B188, 'Points&Potential'!$B$7:$O$943, 14, FALSE)=0, "", VLOOKUP(B188, 'Points&Potential'!$B$7:$O$943, 14, FALSE)) | V188: =IF(ISERROR(VLOOKUP(B188, Paste!$T$3:$T$1045, 1, FALSE)), "", VLOOKUP(B188, Paste!$T$3:$U$1144, 2, FALSE))
A189: 183 | B189: Noah Dobson | C189: =VLOOKUP(B189, Paste!$AG$3:$AH$2083, 2, FALSE) -> 26.4 | D189: =VLOOKUP($B189, Paste!$A$3:$H$933, 6, FALSE) -> RD | E189: =IFERROR(VLOOKUP($B189, Paste!$J$3:$L$933, 3, FALSE), "") -> 57 | F189: =IFERROR(VLOOKUP($B189, Paste!$J$3:$L$933, 2, FALSE), "") -> 75 | G189: =VLOOKUP($B189, Paste!$A$3:$H$933, 8, FALSE) -> MTL | H189: =VLOOKUP($B189, Paste!$A$3:$H$933, 2, FALSE) -> 78.666667 | I189: =VLOOKUP($B189, Paste!$A$3:$H$933, 3, FALSE) -> 11.001851 | J189: =K189-I189 -> 35.780731 | K189: =VLOOKUP($B189, Paste!$A$3:$H$933, 4, FALSE) -> 46.782583 | L189: =IF(ISBLANK(VLOOKUP(B189, 'SOG&PlusMinus'!$B$7:$E$912, 3, FALSE)), "", VLOOKUP(B189,'SOG&PlusMinus'!$B$7:$E$912, 3, FALSE)) -> C | M189: =IF(ISBLANK(VLOOKUP(B189, 'SOG&PlusMinus'!$B$7:$E$912, 4, FALSE)), "", VLOOKUP(B189, 'SOG&PlusMinus'!$B$7:$E$912, 4, FALSE)) -> 2 | N189: =VLOOKUP($B189, Paste!$A$3:$H$933, 5, FALSE) -> 33.518841 | O189: =IF(ISERROR(VLOOKUP(B189, Paste!$AB$3:$AE$2349, 3, FALSE)), "", VLOOKUP(B189, Paste!$AB$3:$AE$2349, 3, FALSE)) -> 63 | P189: =IF(ISERROR(VLOOKUP(B189, Paste!$AB$3:$AC$2343, 2, FALSE)), "", VLOOKUP(B189, Paste!$AB$3:$AC$2343, 2, FALSE)) -> 165 | Q189: =IF(ISERROR(VLOOKUP(B189, Paste!$AB$3:$AE$2349, 4, FALSE)), "", VLOOKUP(B189, Paste!$AB$3:$AE$2349, 4, FALSE)) -> 165 | R189: =IF(ISERROR(VLOOKUP(B189, Paste!$N$3:$N$250, 1, FALSE)), "", VLOOKUP(B189, Paste!$N$3:$O$250, 2, FALSE)) | S189: =VLOOKUP($B189, Paste!$W$3:$Z$10064, IF($H$4="Cap Hit",3, IF($H$4="AAV", 4, 2)), FALSE) -> 9.5 | U189: =IF(VLOOKUP(B189, 'Points&Potential'!$B$7:$O$943, 14, FALSE)=0, "", VLOOKUP(B189, 'Points&Potential'!$B$7:$O$943, 14, FALSE)) | V189: =IF(ISERROR(VLOOKUP(B189, Paste!$T$3:$T$1045, 1, FALSE)), "", VLOOKUP(B189, Paste!$T$3:$U$1144, 2, FALSE))
A190: 184 | B190: Seth Jarvis | C190: =VLOOKUP(B190, Paste!$AG$3:$AH$2083, 2, FALSE) -> 24.4 | D190: =VLOOKUP($B190, Paste!$A$3:$H$933, 6, FALSE) -> RW | E190: =IFERROR(VLOOKUP($B190, Paste!$J$3:$L$933, 3, FALSE), "") -> 73 | F190: =IFERROR(VLOOKUP($B190, Paste!$J$3:$L$933, 2, FALSE), "") -> 85 | G190: =VLOOKUP($B190, Paste!$A$3:$H$933, 8, FALSE) -> CAR | H190: =VLOOKUP($B190, Paste!$A$3:$H$933, 2, FALSE) -> 54 | I190: =VLOOKUP($B190, Paste!$A$3:$H$933, 3, FALSE) -> 23.76 | J190: =K190-I190 -> 22.969683 | K190: =VLOOKUP($B190, Paste!$A$3:$H$933, 4, FALSE) -> 46.729683 | L190: =IF(ISBLANK(VLOOKUP(B190, 'SOG&PlusMinus'!$B$7:$E$912, 3, FALSE)), "", VLOOKUP(B190,'SOG&PlusMinus'!$B$7:$E$912, 3, FALSE)) -> B | M190: =IF(ISBLANK(VLOOKUP(B190, 'SOG&PlusMinus'!$B$7:$E$912, 4, FALSE)), "", VLOOKUP(B190, 'SOG&PlusMinus'!$B$7:$E$912, 4, FALSE)) -> 1 | N190: =VLOOKUP($B190, Paste!$A$3:$H$933, 5, FALSE) -> 12.72 | O190: =IF(ISERROR(VLOOKUP(B190, Paste!$AB$3:$AE$2349, 3, FALSE)), "", VLOOKUP(B190, Paste!$AB$3:$AE$2349, 3, FALSE)) -> 57 | P190: =IF(ISERROR(VLOOKUP(B190, Paste!$AB$3:$AC$2343, 2, FALSE)), "", VLOOKUP(B190, Paste!$AB$3:$AC$2343, 2, FALSE)) -> 27 | Q190: =IF(ISERROR(VLOOKUP(B190, Paste!$AB$3:$AE$2349, 4, FALSE)), "", VLOOKUP(B190, Paste!$AB$3:$AE$2349, 4, FALSE)) -> 178 | R190: =IF(ISERROR(VLOOKUP(B190, Paste!$N$3:$N$250, 1, FALSE)), "", VLOOKUP(B190, Paste!$N$3:$O$250, 2, FALSE)) | S190: =VLOOKUP($B190, Paste!$W$3:$Z$10064, IF($H$4="Cap Hit",3, IF($H$4="AAV", 4, 2)), FALSE) -> 7.420087 | T190: =IF(ISERROR(VLOOKUP(B190, Paste!$Q$3:$Q$245, 1, FALSE)), "", VLOOKUP(B190, Paste!$Q$3:$R$245, 2, FALSE)) | U190: =IF(VLOOKUP(B190, 'Points&Potential'!$B$7:$O$943, 14, FALSE)=0, "", VLOOKUP(B190, 'Points&Potential'!$B$7:$O$943, 14, FALSE)) | V190: =IF(ISERROR(VLOOKUP(B190, Paste!$T$3:$T$1045, 1, FALSE)), "", VLOOKUP(B190, Paste!$T$3:$U$1144, 2, FALSE))
A191: 185 | B191: Luke Hughes | C191: =VLOOKUP(B191, Paste!$AG$3:$AH$2083, 2, FALSE) -> 22.8 | D191: =VLOOKUP($B191, Paste!$A$3:$H$933, 6, FALSE) -> LD | E191: =IFERROR(VLOOKUP($B191, Paste!$J$3:$L$933, 3, FALSE), "") -> 52 | F191: =IFERROR(VLOOKUP($B191, Paste!$J$3:$L$933, 2, FALSE), "") -> 70 | G191: =VLOOKUP($B191, Paste!$A$3:$H$933, 8, FALSE) -> NJD | H191: =VLOOKUP($B191, Paste!$A$3:$H$933, 2, FALSE) -> 75.666667 | I191: =VLOOKUP($B191, Paste!$A$3:$H$933, 3, FALSE) -> 8.0724784 | J191: =K191-I191 -> 38.637869 | K191: =VLOOKUP($B191, Paste!$A$3:$H$933, 4, FALSE) -> 46.710347 | L191: =IF(ISBLANK(VLOOKUP(B191, 'SOG&PlusMinus'!$B$7:$E$912, 3, FALSE)), "", VLOOKUP(B191,'SOG&PlusMinus'!$B$7:$E$912, 3, FALSE)) -> C | M191: =IF(ISBLANK(VLOOKUP(B191, 'SOG&PlusMinus'!$B$7:$E$912, 4, FALSE)), "", VLOOKUP(B191, 'SOG&PlusMinus'!$B$7:$E$912, 4, FALSE)) -> 2 | N191: =VLOOKUP($B191, Paste!$A$3:$H$933, 5, FALSE) -> 26.021116 | O191: =IF(ISERROR(VLOOKUP(B191, Paste!$AB$3:$AE$2349, 3, FALSE)), "", VLOOKUP(B191, Paste!$AB$3:$AE$2349, 3, FALSE)) -> 21 | P191: =IF(ISERROR(VLOOKUP(B191, Paste!$AB$3:$AC$2343, 2, FALSE)), "", VLOOKUP(B191, Paste!$AB$3:$AC$2343, 2, FALSE)) -> 64 | Q191: =IF(ISERROR(VLOOKUP(B191, Paste!$AB$3:$AE$2349, 4, FALSE)), "", VLOOKUP(B191, Paste!$AB$3:$AE$2349, 4, FALSE)) -> 182 | R191: =IF(ISERROR(VLOOKUP(B191, Paste!$N$3:$N$250, 1, FALSE)), "", VLOOKUP(B191, Paste!$N$3:$O$250, 2, FALSE)) -> 65 | S191: =VLOOKUP($B191, Paste!$W$3:$Z$10064, IF($H$4="Cap Hit",3, IF($H$4="AAV", 4, 2)), FALSE) -> 9 | T191: =IF(ISERROR(VLOOKUP(B191, Paste!$Q$3:$Q$245, 1, FALSE)), "", VLOOKUP(B191, Paste!$Q$3:$R$245, 2, FALSE)) -> Y | U191: =IF(VLOOKUP(B191, 'Points&Potential'!$B$7:$O$943, 14, FALSE)=0, "", VLOOKUP(B191, 'Points&Potential'!$B$7:$O$943, 14, FALSE)) | V191: =IF(ISERROR(VLOOKUP(B191, Paste!$T$3:$T$1045, 1, FALSE)), "", VLOOKUP(B191, Paste!$T$3:$U$1144, 2, FALSE))
A192: 186 | B192: Alexander Wennberg | C192: =VLOOKUP(B192, Paste!$AG$3:$AH$2083, 2, FALSE) -> 31.7 | D192: =VLOOKUP($B192, Paste!$A$3:$H$933, 6, FALSE) -> C | E192: =IFERROR(VLOOKUP($B192, Paste!$J$3:$L$933, 3, FALSE), "") -> 48 | F192: =IFERROR(VLOOKUP($B192, Paste!$J$3:$L$933, 2, FALSE), "") -> 57 | G192: =VLOOKUP($B192, Paste!$A$3:$H$933, 8, FALSE) -> SJS | H192: =VLOOKUP($B192, Paste!$A$3:$H$933, 2, FALSE) -> 80.666667 | I192: =VLOOKUP($B192, Paste!$A$3:$H$933, 3, FALSE) -> 13.713333 | J192: =K192-I192 -> 32.964837 | K192: =VLOOKUP($B192, Paste!$A$3:$H$933, 4, FALSE) -> 46.67817 | L192: =IF(ISBLANK(VLOOKUP(B192, 'SOG&PlusMinus'!$B$7:$E$912, 3, FALSE)), "", VLOOKUP(B192,'SOG&PlusMinus'!$B$7:$E$912, 3, FALSE)) -> D | M192: =IF(ISBLANK(VLOOKUP(B192, 'SOG&PlusMinus'!$B$7:$E$912, 4, FALSE)), "", VLOOKUP(B192, 'SOG&PlusMinus'!$B$7:$E$912, 4, FALSE)) -> 2 | N192: =VLOOKUP($B192, Paste!$A$3:$H$933, 5, FALSE) -> 15.723164 | O192: =IF(ISERROR(VLOOKUP(B192, Paste!$AB$3:$AE$2349, 3, FALSE)), "", VLOOKUP(B192, Paste!$AB$3:$AE$2349, 3, FALSE)) -> 24 | P192: =IF(ISERROR(VLOOKUP(B192, Paste!$AB$3:$AC$2343, 2, FALSE)), "", VLOOKUP(B192, Paste!$AB$3:$AC$2343, 2, FALSE)) -> 84 | Q192: =IF(ISERROR(VLOOKUP(B192, Paste!$AB$3:$AE$2349, 4, FALSE)), "", VLOOKUP(B192, Paste!$AB$3:$AE$2349, 4, FALSE)) -> 89 | R192: =IF(ISERROR(VLOOKUP(B192, Paste!$N$3:$N$250, 1, FALSE)), "", VLOOKUP(B192, Paste!$N$3:$O$250, 2, FALSE)) | S192: =VLOOKUP($B192, Paste!$W$3:$Z$10064, IF($H$4="Cap Hit",3, IF($H$4="AAV", 4, 2)), FALSE) -> 6 | T192: =IF(ISERROR(VLOOKUP(B192, Paste!$Q$3:$Q$245, 1, FALSE)), "", VLOOKUP(B192, Paste!$Q$3:$R$245, 2, FALSE)) | U192: =IF(VLOOKUP(B192, 'Points&Potential'!$B$7:$O$943, 14, FALSE)=0, "", VLOOKUP(B192, 'Points&Potential'!$B$7:$O$943, 14, FALSE)) | V192: =IF(ISERROR(VLOOKUP(B192, Paste!$T$3:$T$1045, 1, FALSE)), "", VLOOKUP(B192, Paste!$T$3:$U$1144, 2, FALSE))
A193: 187 | B193: Teuvo Teravainen | C193: =VLOOKUP(B193, Paste!$AG$3:$AH$2083, 2, FALSE) -> 31.8 | D193: =VLOOKUP($B193, Paste!$A$3:$H$933, 6, FALSE) -> LW | E193: =IFERROR(VLOOKUP($B193, Paste!$J$3:$L$933, 3, FALSE), "") -> 50 | F193: =IFERROR(VLOOKUP($B193, Paste!$J$3:$L$933, 2, FALSE), "") -> 67 | G193: =VLOOKUP($B193, Paste!$A$3:$H$933, 8, FALSE) -> CHI | H193: =VLOOKUP($B193, Paste!$A$3:$H$933, 2, FALSE) -> 79.666667 | I193: =VLOOKUP($B193, Paste!$A$3:$H$933, 3, FALSE) -> 16.869644 | J193: =K193-I193 -> 29.777211 | K193: =VLOOKUP($B193, Paste!$A$3:$H$933, 4, FALSE) -> 46.646855 | L193: =IF(ISBLANK(VLOOKUP(B193, 'SOG&PlusMinus'!$B$7:$E$912, 3, FALSE)), "", VLOOKUP(B193,'SOG&PlusMinus'!$B$7:$E$912, 3, FALSE)) -> D | M193: =IF(ISBLANK(VLOOKUP(B193, 'SOG&PlusMinus'!$B$7:$E$912, 4, FALSE)), "", VLOOKUP(B193, 'SOG&PlusMinus'!$B$7:$E$912, 4, FALSE)) -> 2 | N193: =VLOOKUP($B193, Paste!$A$3:$H$933, 5, FALSE) -> 11.95 | O193: =IF(ISERROR(VLOOKUP(B193, Paste!$AB$3:$AE$2349, 3, FALSE)), "", VLOOKUP(B193, Paste!$AB$3:$AE$2349, 3, FALSE)) -> 20 | P193: =IF(ISERROR(VLOOKUP(B193, Paste!$AB$3:$AC$2343, 2, FALSE)), "", VLOOKUP(B193, Paste!$AB$3:$AC$2343, 2, FALSE)) -> 32 | Q193: =IF(ISERROR(VLOOKUP(B193, Paste!$AB$3:$AE$2349, 4, FALSE)), "", VLOOKUP(B193, Paste!$AB$3:$AE$2349, 4, FALSE)) -> 112 | R193: =IF(ISERROR(VLOOKUP(B193, Paste!$N$3:$N$250, 1, FALSE)), "", VLOOKUP(B193, Paste!$N$3:$O$250, 2, FALSE)) | S193: =VLOOKUP($B193, Paste!$W$3:$Z$10064, IF($H$4="Cap Hit",3, IF($H$4="AAV", 4, 2)), FALSE) -> 5.4 | T193: =IF(ISERROR(VLOOKUP(B193, Paste!$Q$3:$Q$245, 1, FALSE)), "", VLOOKUP(B193, Paste!$Q$3:$R$245, 2, FALSE)) | U193: =IF(VLOOKUP(B193, 'Points&Potential'!$B$7:$O$943, 14, FALSE)=0, "", VLOOKUP(B193, 'Points&Potential'!$B$7:$O$943, 14, FALSE)) | V193: =IF(ISERROR(VLOOKUP(B193, Paste!$T$3:$T$1045, 1, FALSE)), "", VLOOKUP(B193, Paste!$T$3:$U$1144, 2, FALSE))
A194: 188 | B194: Vince Dunn | C194: =VLOOKUP(B194, Paste!$AG$3:$AH$2083, 2, FALSE) -> 29.6 | D194: =VLOOKUP($B194, Paste!$A$3:$H$933, 6, FALSE) -> LD | E194: =IFERROR(VLOOKUP($B194, Paste!$J$3:$L$933, 3, FALSE), "") -> 55 | F194: =IFERROR(VLOOKUP($B194, Paste!$J$3:$L$933, 2, FALSE), "") -> 70 | G194: =VLOOKUP($B194, Paste!$A$3:$H$933, 8, FALSE) -> SEA | H194: =VLOOKUP($B194, Paste!$A$3:$H$933, 2, FALSE) -> 76 | I194: =VLOOKUP($B194, Paste!$A$3:$H$933, 3, FALSE) -> 12.893361 | J194: =K194-I194 -> 33.558444 | K194: =VLOOKUP($B194, Paste!$A$3:$H$933, 4, FALSE) -> 46.451805 | L194: =IF(ISBLANK(VLOOKUP(B194, 'SOG&PlusMinus'!$B$7:$E$912, 3, FALSE)), "", VLOOKUP(B194,'SOG&PlusMinus'!$B$7:$E$912, 3, FALSE)) -> D | M194: =IF(ISBLANK(VLOOKUP(B194, 'SOG&PlusMinus'!$B$7:$E$912, 4, FALSE)), "", VLOOKUP(B194, 'SOG&PlusMinus'!$B$7:$E$912, 4, FALSE)) -> 1 | N194: =VLOOKUP($B194, Paste!$A$3:$H$933, 5, FALSE) -> 62.079208 | O194: =IF(ISERROR(VLOOKUP(B194, Paste!$AB$3:$AE$2349, 3, FALSE)), "", VLOOKUP(B194, Paste!$AB$3:$AE$2349, 3, FALSE)) -> 30 | P194: =IF(ISERROR(VLOOKUP(B194, Paste!$AB$3:$AC$2343, 2, FALSE)), "", VLOOKUP(B194, Paste!$AB$3:$AC$2343, 2, FALSE)) -> 86 | Q194: =IF(ISERROR(VLOOKUP(B194, Paste!$AB$3:$AE$2349, 4, FALSE)), "", VLOOKUP(B194, Paste!$AB$3:$AE$2349, 4, FALSE)) -> 160 | R194: =IF(ISERROR(VLOOKUP(B194, Paste!$N$3:$N$250, 1, FALSE)), "", VLOOKUP(B194, Paste!$N$3:$O$250, 2, FALSE)) | S194: =VLOOKUP($B194, Paste!$W$3:$Z$10064, IF($H$4="Cap Hit",3, IF($H$4="AAV", 4, 2)), FALSE) -> 7.35 | T194: =IF(ISERROR(VLOOKUP(B194, Paste!$Q$3:$Q$245, 1, FALSE)), "", VLOOKUP(B194, Paste!$Q$3:$R$245, 2, FALSE)) -> Y | U194: =IF(VLOOKUP(B194, 'Points&Potential'!$B$7:$O$943, 14, FALSE)=0, "", VLOOKUP(B194, 'Points&Potential'!$B$7:$O$943, 14, FALSE)) | V194: =IF(ISERROR(VLOOKUP(B194, Paste!$T$3:$T$1045, 1, FALSE)), "", VLOOKUP(B194, Paste!$T$3:$U$1144, 2, FALSE))
A195: 189 | B195: Mavrik Bourque | C195: =VLOOKUP(B195, Paste!$AG$3:$AH$2083, 2, FALSE) -> 24.4 | D195: =VLOOKUP($B195, Paste!$A$3:$H$933, 6, FALSE) -> RW | E195: =IFERROR(VLOOKUP($B195, Paste!$J$3:$L$933, 3, FALSE), "") -> 58 | F195: =IFERROR(VLOOKUP($B195, Paste!$J$3:$L$933, 2, FALSE), "") -> 78 | G195: =VLOOKUP($B195, Paste!$A$3:$H$933, 8, FALSE) -> NSH | H195: =VLOOKUP($B195, Paste!$A$3:$H$933, 2, FALSE) -> 83 | I195: =VLOOKUP($B195, Paste!$A$3:$H$933, 3, FALSE) -> 20.75 | J195: =K195-I195 -> 25.634204 | K195: =VLOOKUP($B195, Paste!$A$3:$H$933, 4, FALSE) -> 46.384204 | L195: =IF(ISBLANK(VLOOKUP(B195, 'SOG&PlusMinus'!$B$7:$E$912, 3, FALSE)), "", VLOOKUP(B195,'SOG&PlusMinus'!$B$7:$E$912, 3, FALSE)) -> C | M195: =IF(ISBLANK(VLOOKUP(B195, 'SOG&PlusMinus'!$B$7:$E$912, 4, FALSE)), "", VLOOKUP(B195, 'SOG&PlusMinus'!$B$7:$E$912, 4, FALSE)) -> 1 | N195: =VLOOKUP($B195, Paste!$A$3:$H$933, 5, FALSE) -> 24.9 | O195: =IF(ISERROR(VLOOKUP(B195, Paste!$AB$3:$AE$2349, 3, FALSE)), "", VLOOKUP(B195, Paste!$AB$3:$AE$2349, 3, FALSE)) -> 87 | P195: =IF(ISERROR(VLOOKUP(B195, Paste!$AB$3:$AC$2343, 2, FALSE)), "", VLOOKUP(B195, Paste!$AB$3:$AC$2343, 2, FALSE)) -> 31 | Q195: =IF(ISERROR(VLOOKUP(B195, Paste!$AB$3:$AE$2349, 4, FALSE)), "", VLOOKUP(B195, Paste!$AB$3:$AE$2349, 4, FALSE)) -> 166 | R195: =IF(ISERROR(VLOOKUP(B195, Paste!$N$3:$N$250, 1, FALSE)), "", VLOOKUP(B195, Paste!$N$3:$O$250, 2, FALSE)) -> 60 | S195: =VLOOKUP($B195, Paste!$W$3:$Z$10064, IF($H$4="Cap Hit",3, IF($H$4="AAV", 4, 2)), FALSE) -> 5.5 | U195: =IF(VLOOKUP(B195, 'Points&Potential'!$B$7:$O$943, 14, FALSE)=0, "", VLOOKUP(B195, 'Points&Potential'!$B$7:$O$943, 14, FALSE)) | V195: =IF(ISERROR(VLOOKUP(B195, Paste!$T$3:$T$1045, 1, FALSE)), "", VLOOKUP(B195, Paste!$T$3:$U$1144, 2, FALSE))
A196: 190 | B196: Shane Pinto | C196: =VLOOKUP(B196, Paste!$AG$3:$AH$2083, 2, FALSE) -> 25.6 | D196: =VLOOKUP($B196, Paste!$A$3:$H$933, 6, FALSE) -> C | E196: =IFERROR(VLOOKUP($B196, Paste!$J$3:$L$933, 3, FALSE), "") -> 52 | F196: =IFERROR(VLOOKUP($B196, Paste!$J$3:$L$933, 2, FALSE), "") -> 70 | G196: =VLOOKUP($B196, Paste!$A$3:$H$933, 8, FALSE) -> OTT | H196: =VLOOKUP($B196, Paste!$A$3:$H$933, 2, FALSE) -> 70 | I196: =VLOOKUP($B196, Paste!$A$3:$H$933, 3, FALSE) -> 19.677376 | J196: =K196-I196 -> 26.589541 | K196: =VLOOKUP($B196, Paste!$A$3:$H$933, 4, FALSE) -> 46.266918 | L196: =IF(ISBLANK(VLOOKUP(B196, 'SOG&PlusMinus'!$B$7:$E$912, 3, FALSE)), "", VLOOKUP(B196,'SOG&PlusMinus'!$B$7:$E$912, 3, FALSE)) -> C | M196: =IF(ISBLANK(VLOOKUP(B196, 'SOG&PlusMinus'!$B$7:$E$912, 4, FALSE)), "", VLOOKUP(B196, 'SOG&PlusMinus'!$B$7:$E$912, 4, FALSE)) -> 2 | N196: =VLOOKUP($B196, Paste!$A$3:$H$933, 5, FALSE) -> 31.36612 | O196: =IF(ISERROR(VLOOKUP(B196, Paste!$AB$3:$AE$2349, 3, FALSE)), "", VLOOKUP(B196, Paste!$AB$3:$AE$2349, 3, FALSE)) -> 102 | P196: =IF(ISERROR(VLOOKUP(B196, Paste!$AB$3:$AC$2343, 2, FALSE)), "", VLOOKUP(B196, Paste!$AB$3:$AC$2343, 2, FALSE)) -> 53 | Q196: =IF(ISERROR(VLOOKUP(B196, Paste!$AB$3:$AE$2349, 4, FALSE)), "", VLOOKUP(B196, Paste!$AB$3:$AE$2349, 4, FALSE)) -> 161 | R196: =IF(ISERROR(VLOOKUP(B196, Paste!$N$3:$N$250, 1, FALSE)), "", VLOOKUP(B196, Paste!$N$3:$O$250, 2, FALSE)) | S196: =VLOOKUP($B196, Paste!$W$3:$Z$10064, IF($H$4="Cap Hit",3, IF($H$4="AAV", 4, 2)), FALSE) -> 7.5 | T196: =IF(ISERROR(VLOOKUP(B196, Paste!$Q$3:$Q$245, 1, FALSE)), "", VLOOKUP(B196, Paste!$Q$3:$R$245, 2, FALSE)) -> Y | U196: =IF(VLOOKUP(B196, 'Points&Potential'!$B$7:$O$943, 14, FALSE)=0, "", VLOOKUP(B196, 'Points&Potential'!$B$7:$O$943, 14, FALSE)) | V196: =IF(ISERROR(VLOOKUP(B196, Paste!$T$3:$T$1045, 1, FALSE)), "", VLOOKUP(B196, Paste!$T$3:$U$1144, 2, FALSE))
A197: 191 | B197: Claude Giroux | C197: =VLOOKUP(B197, Paste!$AG$3:$AH$2083, 2, FALSE) -> 38.4 | D197: =VLOOKUP($B197, Paste!$A$3:$H$933, 6, FALSE) -> RW | E197: =IFERROR(VLOOKUP($B197, Paste!$J$3:$L$933, 3, FALSE), "") -> 50 | F197: =IFERROR(VLOOKUP($B197, Paste!$J$3:$L$933, 2, FALSE), "") -> 67 | G197: =VLOOKUP($B197, Paste!$A$3:$H$933, 8, FALSE) -> OTT | H197: =VLOOKUP($B197, Paste!$A$3:$H$933, 2, FALSE) -> 83.666667 | I197: =VLOOKUP($B197, Paste!$A$3:$H$933, 3, FALSE) -> 16.138983 | J197: =K197-I197 -> 30.054743 | K197: =VLOOKUP($B197, Paste!$A$3:$H$933, 4, FALSE) -> 46.193726 | L197: =IF(ISBLANK(VLOOKUP(B197, 'SOG&PlusMinus'!$B$7:$E$912, 3, FALSE)), "", VLOOKUP(B197,'SOG&PlusMinus'!$B$7:$E$912, 3, FALSE)) -> A | M197: =IF(ISBLANK(VLOOKUP(B197, 'SOG&PlusMinus'!$B$7:$E$912, 4, FALSE)), "", VLOOKUP(B197, 'SOG&PlusMinus'!$B$7:$E$912, 4, FALSE)) -> 2 | N197: =VLOOKUP($B197, Paste!$A$3:$H$933, 5, FALSE) -> 22.538776 | O197: =IF(ISERROR(VLOOKUP(B197, Paste!$AB$3:$AE$2349, 3, FALSE)), "", VLOOKUP(B197, Paste!$AB$3:$AE$2349, 3, FALSE)) -> 59 | P197: =IF(ISERROR(VLOOKUP(B197, Paste!$AB$3:$AC$2343, 2, FALSE)), "", VLOOKUP(B197, Paste!$AB$3:$AC$2343, 2, FALSE)) -> 25 | Q197: =IF(ISERROR(VLOOKUP(B197, Paste!$AB$3:$AE$2349, 4, FALSE)), "", VLOOKUP(B197, Paste!$AB$3:$AE$2349, 4, FALSE)) -> 134 | R197: =IF(ISERROR(VLOOKUP(B197, Paste!$N$3:$N$250, 1, FALSE)), "", VLOOKUP(B197, Paste!$N$3:$O$250, 2, FALSE)) | S197: =VLOOKUP($B197, Paste!$W$3:$Z$10064, IF($H$4="Cap Hit",3, IF($H$4="AAV", 4, 2)), FALSE) -> 5 | T197: =IF(ISERROR(VLOOKUP(B197, Paste!$Q$3:$Q$245, 1, FALSE)), "", VLOOKUP(B197, Paste!$Q$3:$R$245, 2, FALSE)) | U197: =IF(VLOOKUP(B197, 'Points&Potential'!$B$7:$O$943, 14, FALSE)=0, "", VLOOKUP(B197, 'Points&Potential'!$B$7:$O$943, 14, FALSE)) | V197: =IF(ISERROR(VLOOKUP(B197, Paste!$T$3:$T$1045, 1, FALSE)), "", VLOOKUP(B197, Paste!$T$3:$U$1144, 2, FALSE))
...

Sheet SOG&PlusMinus
K1: Quick Jumps: | M1: Goalies | N1: Plus/Minus & PP
M2: PIM/Hits/BS | N2: Help & Info
H3: AAV, Salary or Cap Hit? (Type it): | M3: Potential | N3: EVERYTHING
H4: Cap Hit
M5: sorted by team
A6: Team | B6: Player | C6: Pos | D6: +/- | E6: PP Unit | F6: Tm | G6: Games | H6: Goals | I6: Assists | J6: Points | K6: SOG | L6: Sleeper | M6: =IF(H4="2011 - 2012 Cap #","Cap Hit", "Salary") -> Salary | N6: Band-Aid Boy | O6: Notes | P6: Rookie
A7: =F7 -> ANA | B7: Leo Carlsson | C7: =VLOOKUP($B7, Paste!$A$3:$H$933, 6, FALSE) -> C | D7: C | E7: 1 | F7: =VLOOKUP($B7, Paste!$A$3:$H$933, 8, FALSE) -> ANA | G7: =VLOOKUP($B7, Paste!$A$3:$H$933, 2, FALSE) -> 72 | H7: =VLOOKUP($B7, Paste!$A$3:$H$933, 3, FALSE) -> 32.4 | I7: =J7-H7 -> 41.73705 | J7: =VLOOKUP($B7, Paste!$A$3:$H$933, 4, FALSE) -> 74.13705 | K7: =VLOOKUP($B7, Paste!$AB$3:$AE$1033, 4, FALSE) -> 209 | L7: =IF(ISERROR(VLOOKUP(B7, Paste!$N$3:$N$250, 1, FALSE)), "", VLOOKUP(B7, Paste!$N$3:$O$250, 2, FALSE)) -> 85 | M7: =VLOOKUP($B7, Paste!$W$3:$Z$10064, IF($H$4="Cap Hit",3, IF($H$4="AAV", 4, 2)), FALSE) -> 18 | N7: =IF(ISERROR(VLOOKUP(B7, Paste!$Q$3:$Q$245, 1, FALSE)), "", VLOOKUP(B7, Paste!$Q$3:$R$245, 2, FALSE)) -> Y | O7: =IF(VLOOKUP(B7, 'Points&Potential'!$B$7:$O$1835, 14, FALSE)=0, "", VLOOKUP(B7, 'Points&Potential'!$B$7:$O$1835, 14, FALSE)) | P7: =IF(ISERROR(VLOOKUP(B7, Paste!$T$3:$T$1045, 1, FALSE)), "", VLOOKUP(B7, Paste!$T$3:$U$1045, 2, FALSE))
A8: =F8 -> ANA | B8: Cutter Gauthier | C8: =VLOOKUP($B8, Paste!$A$3:$H$933, 6, FALSE) -> RW | D8: C | E8: 1 | F8: =VLOOKUP($B8, Paste!$A$3:$H$933, 8, FALSE) -> ANA | G8: =VLOOKUP($B8, Paste!$A$3:$H$933, 2, FALSE) -> 79 | H8: =VLOOKUP($B8, Paste!$A$3:$H$933, 3, FALSE) -> 41.08 | I8: =J8-H8 -> 32.49902 | J8: =VLOOKUP($B8, Paste!$A$3:$H$933, 4, FALSE) -> 73.57902 | K8: =VLOOKUP($B8, Paste!$AB$3:$AE$1033, 4, FALSE) -> 316 | L8: =IF(ISERROR(VLOOKUP(B8, Paste!$N$3:$N$250, 1, FALSE)), "", VLOOKUP(B8, Paste!$N$3:$O$250, 2, FALSE)) | M8: =VLOOKUP($B8, Paste!$W$3:$Z$10064, IF($H$4="Cap Hit",3, IF($H$4="AAV", 4, 2)), FALSE) -> #N/A | N8: =IF(ISERROR(VLOOKUP(B8, Paste!$Q$3:$Q$245, 1, FALSE)), "", VLOOKUP(B8, Paste!$Q$3:$R$245, 2, FALSE)) | O8: =IF(VLOOKUP(B8, 'Points&Potential'!$B$7:$O$1835, 14, FALSE)=0, "", VLOOKUP(B8, 'Points&Potential'!$B$7:$O$1835, 14, FALSE)) | P8: =IF(ISERROR(VLOOKUP(B8, Paste!$T$3:$T$1045, 1, FALSE)), "", VLOOKUP(B8, Paste!$T$3:$U$1045, 2, FALSE))
A9: =F9 -> ANA | B9: Beckett Sennecke | C9: =VLOOKUP($B9, Paste!$A$3:$H$933, 6, FALSE) -> RW | D9: D | E9: 1 | F9: =VLOOKUP($B9, Paste!$A$3:$H$933, 8, FALSE) -> ANA | G9: =VLOOKUP($B9, Paste!$A$3:$H$933, 2, FALSE) -> 84 | H9: =VLOOKUP($B9, Paste!$A$3:$H$933, 3, FALSE) -> 21.366444 | I9: =J9-H9 -> 48.903275 | J9: =VLOOKUP($B9, Paste!$A$3:$H$933, 4, FALSE) -> 70.269719 | K9: =VLOOKUP($B9, Paste!$AB$3:$AE$1033, 4, FALSE) -> 210 | L9: =IF(ISERROR(VLOOKUP(B9, Paste!$N$3:$N$250, 1, FALSE)), "", VLOOKUP(B9, Paste!$N$3:$O$250, 2, FALSE)) | M9: =VLOOKUP($B9, Paste!$W$3:$Z$10064, IF($H$4="Cap Hit",3, IF($H$4="AAV", 4, 2)), FALSE) -> 0.9425 | N9: =IF(ISERROR(VLOOKUP(B9, Paste!$Q$3:$Q$245, 1, FALSE)), "", VLOOKUP(B9, Paste!$Q$3:$R$245, 2, FALSE)) | O9: =IF(VLOOKUP(B9, 'Points&Potential'!$B$7:$O$1835, 14, FALSE)=0, "", VLOOKUP(B9, 'Points&Potential'!$B$7:$O$1835, 14, FALSE)) | P9: =IF(ISERROR(VLOOKUP(B9, Paste!$T$3:$T$1045, 1, FALSE)), "", VLOOKUP(B9, Paste!$T$3:$U$1045, 2, FALSE))
A10: =F10 -> ANA | B10: Jackson Lacombe | C10: =VLOOKUP($B10, Paste!$A$3:$H$933, 6, FALSE) -> LD | D10: C | E10: 1 | F10: =VLOOKUP($B10, Paste!$A$3:$H$933, 8, FALSE) -> ANA | G10: =VLOOKUP($B10, Paste!$A$3:$H$933, 2, FALSE) -> 78 | H10: =VLOOKUP($B10, Paste!$A$3:$H$933, 3, FALSE) -> 12 | I10: =J10-H10 -> 46.289131 | J10: =VLOOKUP($B10, Paste!$A$3:$H$933, 4, FALSE) -> 58.289131 | K10: =VLOOKUP($B10, Paste!$AB$3:$AE$1033, 4, FALSE) -> 164 | L10: =IF(ISERROR(VLOOKUP(B10, Paste!$N$3:$N$250, 1, FALSE)), "", VLOOKUP(B10, Paste!$N$3:$O$250, 2, FALSE)) | M10: =VLOOKUP($B10, Paste!$W$3:$Z$10064, IF($H$4="Cap Hit",3, IF($H$4="AAV", 4, 2)), FALSE) -> 9 | N10: =IF(ISERROR(VLOOKUP(B10, Paste!$Q$3:$Q$245, 1, FALSE)), "", VLOOKUP(B10, Paste!$Q$3:$R$245, 2, FALSE)) | O10: =IF(VLOOKUP(B10, 'Points&Potential'!$B$7:$O$1835, 14, FALSE)=0, "", VLOOKUP(B10, 'Points&Potential'!$B$7:$O$1835, 14, FALSE)) | P10: =IF(ISERROR(VLOOKUP(B10, Paste!$T$3:$T$1045, 1, FALSE)), "", VLOOKUP(B10, Paste!$T$3:$U$1045, 2, FALSE))
A11: =F11 -> ANA | B11: Mikael Granlund | C11: =VLOOKUP($B11, Paste!$A$3:$H$933, 6, FALSE) -> C | D11: D | E11: 1 | F11: =VLOOKUP($B11, Paste!$A$3:$H$933, 8, FALSE) -> ANA | G11: =VLOOKUP($B11, Paste!$A$3:$H$933, 2, FALSE) -> 72 | H11: =VLOOKUP($B11, Paste!$A$3:$H$933, 3, FALSE) -> 18.443338 | I11: =J11-H11 -> 33.525914 | J11: =VLOOKUP($B11, Paste!$A$3:$H$933, 4, FALSE) -> 51.969251 | K11: =VLOOKUP($B11, Paste!$AB$3:$AE$1033, 4, FALSE) -> 137 | L11: =IF(ISERROR(VLOOKUP(B11, Paste!$N$3:$N$250, 1, FALSE)), "", VLOOKUP(B11, Paste!$N$3:$O$250, 2, FALSE)) | M11: =VLOOKUP($B11, Paste!$W$3:$Z$10064, IF($H$4="Cap Hit",3, IF($H$4="AAV", 4, 2)), FALSE) -> 7 | N11: =IF(ISERROR(VLOOKUP(B11, Paste!$Q$3:$Q$245, 1, FALSE)), "", VLOOKUP(B11, Paste!$Q$3:$R$245, 2, FALSE)) -> Y | O11: =IF(VLOOKUP(B11, 'Points&Potential'!$B$7:$O$1835, 14, FALSE)=0, "", VLOOKUP(B11, 'Points&Potential'!$B$7:$O$1835, 14, FALSE)) | P11: =IF(ISERROR(VLOOKUP(B11, Paste!$T$3:$T$1045, 1, FALSE)), "", VLOOKUP(B11, Paste!$T$3:$U$1045, 2, FALSE))
A12: =F12 -> ANA | B12: Chris Kreider | C12: =VLOOKUP($B12, Paste!$A$3:$H$933, 6, FALSE) -> LW | D12: C | E12: 2 | F12: =VLOOKUP($B12, Paste!$A$3:$H$933, 8, FALSE) -> ANA | G12: =VLOOKUP($B12, Paste!$A$3:$H$933, 2, FALSE) -> 77 | H12: =VLOOKUP($B12, Paste!$A$3:$H$933, 3, FALSE) -> 25.722763 | I12: =J12-H12 -> 16.282283 | J12: =VLOOKUP($B12, Paste!$A$3:$H$933, 4, FALSE) -> 42.005046 | K12: =VLOOKUP($B12, Paste!$AB$3:$AE$1033, 4, FALSE) -> 154 | L12: =IF(ISERROR(VLOOKUP(B12, Paste!$N$3:$N$250, 1, FALSE)), "", VLOOKUP(B12, Paste!$N$3:$O$250, 2, FALSE)) | M12: =VLOOKUP($B12, Paste!$W$3:$Z$10064, IF($H$4="Cap Hit",3, IF($H$4="AAV", 4, 2)), FALSE) -> 6.5 | N12: =IF(ISERROR(VLOOKUP(B12, Paste!$Q$3:$Q$245, 1, FALSE)), "", VLOOKUP(B12, Paste!$Q$3:$R$245, 2, FALSE)) | O12: =IF(VLOOKUP(B12, 'Points&Potential'!$B$7:$O$1835, 14, FALSE)=0, "", VLOOKUP(B12, 'Points&Potential'!$B$7:$O$1835, 14, FALSE)) | P12: =IF(ISERROR(VLOOKUP(B12, Paste!$T$3:$T$1045, 1, FALSE)), "", VLOOKUP(B12, Paste!$T$3:$U$1045, 2, FALSE))
A13: =F13 -> ANA | B13: Troy Terry | C13: =VLOOKUP($B13, Paste!$A$3:$H$933, 6, FALSE) -> RW | D13: B | E13: 2 | F13: =VLOOKUP($B13, Paste!$A$3:$H$933, 8, FALSE) -> ANA | G13: =VLOOKUP($B13, Paste!$A$3:$H$933, 2, FALSE) -> 43 | H13: =VLOOKUP($B13, Paste!$A$3:$H$933, 3, FALSE) -> 12.451258 | I13: =J13-H13 -> 23.785246 | J13: =VLOOKUP($B13, Paste!$A$3:$H$933, 4, FALSE) -> 36.236503 | K13: =VLOOKUP($B13, Paste!$AB$3:$AE$1033, 4, FALSE) -> 103 | L13: =IF(ISERROR(VLOOKUP(B13, Paste!$N$3:$N$250, 1, FALSE)), "", VLOOKUP(B13, Paste!$N$3:$O$250, 2, FALSE)) | M13: =VLOOKUP($B13, Paste!$W$3:$Z$10064, IF($H$4="Cap Hit",3, IF($H$4="AAV", 4, 2)), FALSE) -> 7 | N13: =IF(ISERROR(VLOOKUP(B13, Paste!$Q$3:$Q$245, 1, FALSE)), "", VLOOKUP(B13, Paste!$Q$3:$R$245, 2, FALSE)) | O13: =IF(VLOOKUP(B13, 'Points&Potential'!$B$7:$O$1835, 14, FALSE)=0, "", VLOOKUP(B13, 'Points&Potential'!$B$7:$O$1835, 14, FALSE)) | P13: =IF(ISERROR(VLOOKUP(B13, Paste!$T$3:$T$1045, 1, FALSE)), "", VLOOKUP(B13, Paste!$T$3:$U$1045, 2, FALSE))
A14: =F14 -> ANA | B14: Ryan Poehling | C14: =VLOOKUP($B14, Paste!$A$3:$H$933, 6, FALSE) -> C | D14: C | F14: =VLOOKUP($B14, Paste!$A$3:$H$933, 8, FALSE) -> ANA | G14: =VLOOKUP($B14, Paste!$A$3:$H$933, 2, FALSE) -> 75.333333 | H14: =VLOOKUP($B14, Paste!$A$3:$H$933, 3, FALSE) -> 11.75012 | I14: =J14-H14 -> 20.332111 | J14: =VLOOKUP($B14, Paste!$A$3:$H$933, 4, FALSE) -> 32.082231 | K14: =VLOOKUP($B14, Paste!$AB$3:$AE$1033, 4, FALSE) -> 98 | L14: =IF(ISERROR(VLOOKUP(B14, Paste!$N$3:$N$250, 1, FALSE)), "", VLOOKUP(B14, Paste!$N$3:$O$250, 2, FALSE)) | M14: =VLOOKUP($B14, Paste!$W$3:$Z$10064, IF($H$4="Cap Hit",3, IF($H$4="AAV", 4, 2)), FALSE) -> 3.75 | N14: =IF(ISERROR(VLOOKUP(B14, Paste!$Q$3:$Q$245, 1, FALSE)), "", VLOOKUP(B14, Paste!$Q$3:$R$245, 2, FALSE)) | O14: =IF(VLOOKUP(B14, 'Points&Potential'!$B$7:$O$1835, 14, FALSE)=0, "", VLOOKUP(B14, 'Points&Potential'!$B$7:$O$1835, 14, FALSE)) | P14: =IF(ISERROR(VLOOKUP(B14, Paste!$T$3:$T$1045, 1, FALSE)), "", VLOOKUP(B14, Paste!$T$3:$U$1045, 2, FALSE))
A15: =F15 -> ANA | B15: Pavel Mintyukov | C15: =VLOOKUP($B15, Paste!$A$3:$H$933, 6, FALSE) -> LD | D15: C | E15: 2 | F15: =VLOOKUP($B15, Paste!$A$3:$H$933, 8, FALSE) -> ANA | G15: =VLOOKUP($B15, Paste!$A$3:$H$933, 2, FALSE) -> 76 | H15: =VLOOKUP($B15, Paste!$A$3:$H$933, 3, FALSE) -> 8 | I15: =J15-H15 -> 23.2246 | J15: =VLOOKUP($B15, Paste!$A$3:$H$933, 4, FALSE) -> 31.2246 | K15: =VLOOKUP($B15, Paste!$AB$3:$AE$1033, 4, FALSE) -> 106 | L15: =IF(ISERROR(VLOOKUP(B15, Paste!$N$3:$N$250, 1, FALSE)), "", VLOOKUP(B15, Paste!$N$3:$O$250, 2, FALSE)) -> 40 | M15: =VLOOKUP($B15, Paste!$W$3:$Z$10064, IF($H$4="Cap Hit",3, IF($H$4="AAV", 4, 2)), FALSE) -> 7.2 | N15: =IF(ISERROR(VLOOKUP(B15, Paste!$Q$3:$Q$245, 1, FALSE)), "", VLOOKUP(B15, Paste!$Q$3:$R$245, 2, FALSE)) -> Y | O15: =IF(VLOOKUP(B15, 'Points&Potential'!$B$7:$O$1835, 14, FALSE)=0, "", VLOOKUP(B15, 'Points&Potential'!$B$7:$O$1835, 14, FALSE)) | P15: =IF(ISERROR(VLOOKUP(B15, Paste!$T$3:$T$1045, 1, FALSE)), "", VLOOKUP(B15, Paste!$T$3:$U$1045, 2, FALSE))
A16: =F16 -> ANA | B16: Alex Killorn | C16: =VLOOKUP($B16, Paste!$A$3:$H$933, 6, FALSE) -> LW | D16: C | E16: 2 | F16: =VLOOKUP($B16, Paste!$A$3:$H$933, 8, FALSE) -> ANA | G16: =VLOOKUP($B16, Paste!$A$3:$H$933, 2, FALSE) -> 77.666667 | H16: =VLOOKUP($B16, Paste!$A$3:$H$933, 3, FALSE) -> 17.419436 | I16: =J16-H16 -> 12.918795 | J16: =VLOOKUP($B16, Paste!$A$3:$H$933, 4, FALSE) -> 30.338231 | K16: =VLOOKUP($B16, Paste!$AB$3:$AE$1033, 4, FALSE) -> 124 | L16: =IF(ISERROR(VLOOKUP(B16, Paste!$N$3:$N$250, 1, FALSE)), "", VLOOKUP(B16, Paste!$N$3:$O$250, 2, FALSE)) | M16: =VLOOKUP($B16, Paste!$W$3:$Z$10064, IF($H$4="Cap Hit",3, IF($H$4="AAV", 4, 2)), FALSE) -> 6.25 | N16: =IF(ISERROR(VLOOKUP(B16, Paste!$Q$3:$Q$245, 1, FALSE)), "", VLOOKUP(B16, Paste!$Q$3:$R$245, 2, FALSE)) | O16: =IF(VLOOKUP(B16, 'Points&Potential'!$B$7:$O$1835, 14, FALSE)=0, "", VLOOKUP(B16, 'Points&Potential'!$B$7:$O$1835, 14, FALSE)) | P16: =IF(ISERROR(VLOOKUP(B16, Paste!$T$3:$T$1045, 1, FALSE)), "", VLOOKUP(B16, Paste!$T$3:$U$1045, 2, FALSE))
A17: =F17 -> ANA | B17: A.J. Greer | C17: =VLOOKUP($B17, Paste!$A$3:$H$933, 6, FALSE) -> RW | D17: C | F17: =VLOOKUP($B17, Paste!$A$3:$H$933, 8, FALSE) -> ANA | G17: =VLOOKUP($B17, Paste!$A$3:$H$933, 2, FALSE) -> 74.666667 | H17: =VLOOKUP($B17, Paste!$A$3:$H$933, 3, FALSE) -> 9.9545592 | I17: =J17-H17 -> 12.293459 | J17: =VLOOKUP($B17, Paste!$A$3:$H$933, 4, FALSE) -> 22.248018 | K17: =VLOOKUP($B17, Paste!$AB$3:$AE$1033, 4, FALSE) -> 82 | L17: =IF(ISERROR(VLOOKUP(B17, Paste!$N$3:$N$250, 1, FALSE)), "", VLOOKUP(B17, Paste!$N$3:$O$250, 2, FALSE)) | M17: =VLOOKUP($B17, Paste!$W$3:$Z$10064, IF($H$4="Cap Hit",3, IF($H$4="AAV", 4, 2)), FALSE) -> 4.25 | N17: =IF(ISERROR(VLOOKUP(B17, Paste!$Q$3:$Q$245, 1, FALSE)), "", VLOOKUP(B17, Paste!$Q$3:$R$245, 2, FALSE)) | O17: =IF(VLOOKUP(B17, 'Points&Potential'!$B$7:$O$1835, 14, FALSE)=0, "", VLOOKUP(B17, 'Points&Potential'!$B$7:$O$1835, 14, FALSE)) | P17: =IF(ISERROR(VLOOKUP(B17, Paste!$T$3:$T$1045, 1, FALSE)), "", VLOOKUP(B17, Paste!$T$3:$U$1045, 2, FALSE))
A18: =F18 -> ANA | B18: Frank Vatrano | C18: =VLOOKUP($B18, Paste!$A$3:$H$933, 6, FALSE) -> RW | D18: D | E18: 2 | F18: =VLOOKUP($B18, Paste!$A$3:$H$933, 8, FALSE) -> ANA | G18: =VLOOKUP($B18, Paste!$A$3:$H$933, 2, FALSE) -> 73 | H18: =VLOOKUP($B18, Paste!$A$3:$H$933, 3, FALSE) -> 12 | I18: =J18-H18 -> 7.3161422 | J18: =VLOOKUP($B18, Paste!$A$3:$H$933, 4, FALSE) -> 19.316142 | K18: =VLOOKUP($B18, Paste!$AB$3:$AE$1033, 4, FALSE) -> 131 | L18: =IF(ISERROR(VLOOKUP(B18, Paste!$N$3:$N$250, 1, FALSE)), "", VLOOKUP(B18, Paste!$N$3:$O$250, 2, FALSE)) | M18: =VLOOKUP($B18, Paste!$W$3:$Z$10064, IF($H$4="Cap Hit",3, IF($H$4="AAV", 4, 2)), FALSE) -> 4.571189 | N18: =IF(ISERROR(VLOOKUP(B18, Paste!$Q$3:$Q$245, 1, FALSE)), "", VLOOKUP(B18, Paste!$Q$3:$R$245, 2, FALSE)) | O18: =IF(VLOOKUP(B18, 'Points&Potential'!$B$7:$O$1835, 14, FALSE)=0, "", VLOOKUP(B18, 'Points&Potential'!$B$7:$O$1835, 14, FALSE)) | P18: =IF(ISERROR(VLOOKUP(B18, Paste!$T$3:$T$1045, 1, FALSE)), "", VLOOKUP(B18, Paste!$T$3:$U$1045, 2, FALSE))
A19: =F19 -> ANA | B19: Tyson Hinds | C19: =VLOOKUP($B19, Paste!$A$3:$H$933, 6, FALSE) -> LD | D19: C | F19: =VLOOKUP($B19, Paste!$A$3:$H$933, 8, FALSE) -> ANA | G19: =VLOOKUP($B19, Paste!$A$3:$H$933, 2, FALSE) -> 70 | H19: =VLOOKUP($B19, Paste!$A$3:$H$933, 3, FALSE) -> 4.9217778 | I19: =J19-H19 -> 11.475722 | J19: =VLOOKUP($B19, Paste!$A$3:$H$933, 4, FALSE) -> 16.3975 | K19: =VLOOKUP($B19, Paste!$AB$3:$AE$1033, 4, FALSE) -> 95 | L19: =IF(ISERROR(VLOOKUP(B19, Paste!$N$3:$N$250, 1, FALSE)), "", VLOOKUP(B19, Paste!$N$3:$O$250, 2, FALSE)) | M19: =VLOOKUP($B19, Paste!$W$3:$Z$10064, IF($H$4="Cap Hit",3, IF($H$4="AAV", 4, 2)), FALSE) -> 0.9 | N19: =IF(ISERROR(VLOOKUP(B19, Paste!$Q$3:$Q$245, 1, FALSE)), "", VLOOKUP(B19, Paste!$Q$3:$R$245, 2, FALSE)) | O19: =IF(VLOOKUP(B19, 'Points&Potential'!$B$7:$O$1835, 14, FALSE)=0, "", VLOOKUP(B19, 'Points&Potential'!$B$7:$O$1835, 14, FALSE)) | P19: =IF(ISERROR(VLOOKUP(B19, Paste!$T$3:$T$1045, 1, FALSE)), "", VLOOKUP(B19, Paste!$T$3:$U$1045, 2, FALSE)) -> Y
A20: =F20 -> ANA | B20: Drew Helleson | C20: =VLOOKUP($B20, Paste!$A$3:$H$933, 6, FALSE) -> RD | D20: C | F20: =VLOOKUP($B20, Paste!$A$3:$H$933, 8, FALSE) -> ANA | G20: =VLOOKUP($B20, Paste!$A$3:$H$933, 2, FALSE) -> 69 | H20: =VLOOKUP($B20, Paste!$A$3:$H$933, 3, FALSE) -> 3.3575015 | I20: =J20-H20 -> 12.681419 | J20: =VLOOKUP($B20, Paste!$A$3:$H$933, 4, FALSE) -> 16.038921 | K20: =VLOOKUP($B20, Paste!$AB$3:$AE$1033, 4, FALSE) -> 62 | L20: =IF(ISERROR(VLOOKUP(B20, Paste!$N$3:$N$250, 1, FALSE)), "", VLOOKUP(B20, Paste!$N$3:$O$250, 2, FALSE)) | M20: =VLOOKUP($B20, Paste!$W$3:$Z$10064, IF($H$4="Cap Hit",3, IF($H$4="AAV", 4, 2)), FALSE) -> 1.1 | N20: =IF(ISERROR(VLOOKUP(B20, Paste!$Q$3:$Q$245, 1, FALSE)), "", VLOOKUP(B20, Paste!$Q$3:$R$245, 2, FALSE)) | O20: =IF(VLOOKUP(B20, 'Points&Potential'!$B$7:$O$1835, 14, FALSE)=0, "", VLOOKUP(B20, 'Points&Potential'!$B$7:$O$1835, 14, FALSE)) | P20: =IF(ISERROR(VLOOKUP(B20, Paste!$T$3:$T$1045, 1, FALSE)), "", VLOOKUP(B20, Paste!$T$3:$U$1045, 2, FALSE))
A21: =F21 -> ANA | B21: Nick Jensen | C21: =VLOOKUP($B21, Paste!$A$3:$H$933, 6, FALSE) -> RD | D21: C | F21: =VLOOKUP($B21, Paste!$A$3:$H$933, 8, FALSE) -> ANA | G21: =VLOOKUP($B21, Paste!$A$3:$H$933, 2, FALSE) -> 72 | H21: =VLOOKUP($B21, Paste!$A$3:$H$933, 3, FALSE) -> 3.1844831 | I21: =J21-H21 -> 11.397443 | J21: =VLOOKUP($B21, Paste!$A$3:$H$933, 4, FALSE) -> 14.581926 | K21: =VLOOKUP($B21, Paste!$AB$3:$AE$1033, 4, FALSE) -> 58 | L21: =IF(ISERROR(VLOOKUP(B21, Paste!$N$3:$N$250, 1, FALSE)), "", VLOOKUP(B21, Paste!$N$3:$O$250, 2, FALSE)) | M21: =VLOOKUP($B21, Paste!$W$3:$Z$10064, IF($H$4="Cap Hit",3, IF($H$4="AAV", 4, 2)), FALSE) -> 2.25 | N21: =IF(ISERROR(VLOOKUP(B21, Paste!$Q$3:$Q$245, 1, FALSE)), "", VLOOKUP(B21, Paste!$Q$3:$R$245, 2, FALSE)) | O21: =IF(VLOOKUP(B21, 'Points&Potential'!$B$7:$O$1835, 14, FALSE)=0, "", VLOOKUP(B21, 'Points&Potential'!$B$7:$O$1835, 14, FALSE)) | P21: =IF(ISERROR(VLOOKUP(B21, Paste!$T$3:$T$1045, 1, FALSE)), "", VLOOKUP(B21, Paste!$T$3:$U$1045, 2, FALSE))
A22: =F22 -> ANA | B22: Nikita Nesterenko | C22: =VLOOKUP($B22, Paste!$A$3:$H$933, 6, FALSE) -> LW | D22: C | F22: =VLOOKUP($B22, Paste!$A$3:$H$933, 8, FALSE) -> ANA | G22: =VLOOKUP($B22, Paste!$A$3:$H$933, 2, FALSE) -> 42 | H22: =VLOOKUP($B22, Paste!$A$3:$H$933, 3, FALSE) -> 6.5997281 | I22: =J22-H22 -> 6.5007719 | J22: =VLOOKUP($B22, Paste!$A$3:$H$933, 4, FALSE) -> 13.1005 | K22: =VLOOKUP($B22, Paste!$AB$3:$AE$1033, 4, FALSE) -> 50 | L22: =IF(ISERROR(VLOOKUP(B22, Paste!$N$3:$N$250, 1, FALSE)), "", VLOOKUP(B22, Paste!$N$3:$O$250, 2, FALSE)) | M22: =VLOOKUP($B22, Paste!$W$3:$Z$10064, IF($H$4="Cap Hit",3, IF($H$4="AAV", 4, 2)), FALSE) -> 0.7875 | N22: =IF(ISERROR(VLOOKUP(B22, Paste!$Q$3:$Q$245, 1, FALSE)), "", VLOOKUP(B22, Paste!$Q$3:$R$245, 2, FALSE)) | O22: =IF(VLOOKUP(B22, 'Points&Potential'!$B$7:$O$1835, 14, FALSE)=0, "", VLOOKUP(B22, 'Points&Potential'!$B$7:$O$1835, 14, FALSE)) | P22: =IF(ISERROR(VLOOKUP(B22, Paste!$T$3:$T$1045, 1, FALSE)), "", VLOOKUP(B22, Paste!$T$3:$U$1045, 2, FALSE))
A23: =F23 -> ANA | B23: Tim Washe | C23: =VLOOKUP($B23, Paste!$A$3:$H$933, 6, FALSE) -> C | D23: D | F23: =VLOOKUP($B23, Paste!$A$3:$H$933, 8, FALSE) -> ANA | G23: =VLOOKUP($B23, Paste!$A$3:$H$933, 2, FALSE) -> 77 | H23: =VLOOKUP($B23, Paste!$A$3:$H$933, 3, FALSE) -> 7.7 | I23: =J23-H23 -> 4.0506108 | J23: =VLOOKUP($B23, Paste!$A$3:$H$933, 4, FALSE) -> 11.750611 | K23: =VLOOKUP($B23, Paste!$AB$3:$AE$1033, 4, FALSE) -> 85 | L23: =IF(ISERROR(VLOOKUP(B23, Paste!$N$3:$N$250, 1, FALSE)), "", VLOOKUP(B23, Paste!$N$3:$O$250, 2, FALSE)) | M23: =VLOOKUP($B23, Paste!$W$3:$Z$10064, IF($H$4="Cap Hit",3, IF($H$4="AAV", 4, 2)), FALSE) -> 0.8125 | N23: =IF(ISERROR(VLOOKUP(B23, Paste!$Q$3:$Q$245, 1, FALSE)), "", VLOOKUP(B23, Paste!$Q$3:$R$245, 2, FALSE)) | O23: =IF(VLOOKUP(B23, 'Points&Potential'!$B$7:$O$1835, 14, FALSE)=0, "", VLOOKUP(B23, 'Points&Potential'!$B$7:$O$1835, 14, FALSE)) | P23: =IF(ISERROR(VLOOKUP(B23, Paste!$T$3:$T$1045, 1, FALSE)), "", VLOOKUP(B23, Paste!$T$3:$U$1045, 2, FALSE))
A24: =F24 -> ANA | B24: Tristan Luneau | C24: =VLOOKUP($B24, Paste!$A$3:$H$933, 6, FALSE) -> RD | D24: C | F24: =VLOOKUP($B24, Paste!$A$3:$H$933, 8, FALSE) -> ANA | G24: =VLOOKUP($B24, Paste!$A$3:$H$933, 2, FALSE) -> 35 | H24: =VLOOKUP($B24, Paste!$A$3:$H$933, 3, FALSE) -> 5.25 | I24: =J24-H24 -> 4.9145833 | J24: =VLOOKUP($B24, Paste!$A$3:$H$933, 4, FALSE) -> 10.164583 | K24: =VLOOKUP($B24, Paste!$AB$3:$AE$1033, 4, FALSE) -> 49 | L24: =IF(ISERROR(VLOOKUP(B24, Paste!$N$3:$N$250, 1, FALSE)), "", VLOOKUP(B24, Paste!$N$3:$O$250, 2, FALSE)) | M24: =VLOOKUP($B24, Paste!$W$3:$Z$10064, IF($H$4="Cap Hit",3, IF($H$4="AAV", 4, 2)), FALSE) -> 0.865 | N24: =IF(ISERROR(VLOOKUP(B24, Paste!$Q$3:$Q$245, 1, FALSE)), "", VLOOKUP(B24, Paste!$Q$3:$R$245, 2, FALSE)) | O24: =IF(VLOOKUP(B24, 'Points&Potential'!$B$7:$O$1835, 14, FALSE)=0, "", VLOOKUP(B24, 'Points&Potential'!$B$7:$O$1835, 14, FALSE)) | P24: =IF(ISERROR(VLOOKUP(B24, Paste!$T$3:$T$1045, 1, FALSE)), "", VLOOKUP(B24, Paste!$T$3:$U$1045, 2, FALSE))
A25: =F25 -> ANA | B25: Ian Moore | C25: =VLOOKUP($B25, Paste!$A$3:$H$933, 6, FALSE) -> RD | D25: D | F25: =VLOOKUP($B25, Paste!$A$3:$H$933, 8, FALSE) -> ANA | G25: =VLOOKUP($B25, Paste!$A$3:$H$933, 2, FALSE) -> 37 | H25: =VLOOKUP($B25, Paste!$A$3:$H$933, 3, FALSE) -> 2.7307605 | I25: =J25-H25 -> 5.5747868 | J25: =VLOOKUP($B25, Paste!$A$3:$H$933, 4, FALSE) -> 8.3055473 | K25: =VLOOKUP($B25, Paste!$AB$3:$AE$1033, 4, FALSE) -> 48 | L25: =IF(ISERROR(VLOOKUP(B25, Paste!$N$3:$N$250, 1, FALSE)), "", VLOOKUP(B25, Paste!$N$3:$O$250, 2, FALSE)) | M25: =VLOOKUP($B25, Paste!$W$3:$Z$10064, IF($H$4="Cap Hit",3, IF($H$4="AAV", 4, 2)), FALSE) -> 1.15 | N25: =IF(ISERROR(VLOOKUP(B25, Paste!$Q$3:$Q$245, 1, FALSE)), "", VLOOKUP(B25, Paste!$Q$3:$R$245, 2, FALSE)) | O25: =IF(VLOOKUP(B25, 'Points&Potential'!$B$7:$O$1835, 14, FALSE)=0, "", VLOOKUP(B25, 'Points&Potential'!$B$7:$O$1835, 14, FALSE)) | P25: =IF(ISERROR(VLOOKUP(B25, Paste!$T$3:$T$1045, 1, FALSE)), "", VLOOKUP(B25, Paste!$T$3:$U$1045, 2, FALSE))
A26: =F26 -> MTL | B26: Sasha Pastujov | C26: =VLOOKUP($B26, Paste!$A$3:$H$933, 6, FALSE) -> LW | D26: C | F26: =VLOOKUP($B26, Paste!$A$3:$H$933, 8, FALSE) -> MTL | G26: =VLOOKUP($B26, Paste!$A$3:$H$933, 2, FALSE) -> 20 | H26: =VLOOKUP($B26, Paste!$A$3:$H$933, 3, FALSE) -> 1.6 | I26: =J26-H26 -> 2.8835366 | J26: =VLOOKUP($B26, Paste!$A$3:$H$933, 4, FALSE) -> 4.4835366 | K26: =VLOOKUP($B26, Paste!$AB$3:$AE$1033, 4, FALSE) -> 40 | L26: =IF(ISERROR(VLOOKUP(B26, Paste!$N$3:$N$250, 1, FALSE)), "", VLOOKUP(B26, Paste!$N$3:$O$250, 2, FALSE)) | M26: =VLOOKUP($B26, Paste!$W$3:$Z$10064, IF($H$4="Cap Hit",3, IF($H$4="AAV", 4, 2)), FALSE) -> #N/A | N26: =IF(ISERROR(VLOOKUP(B26, Paste!$Q$3:$Q$245, 1, FALSE)), "", VLOOKUP(B26, Paste!$Q$3:$R$245, 2, FALSE)) | O26: =IF(VLOOKUP(B26, 'Points&Potential'!$B$7:$O$1835, 14, FALSE)=0, "", VLOOKUP(B26, 'Points&Potential'!$B$7:$O$1835, 14, FALSE)) | P26: =IF(ISERROR(VLOOKUP(B26, Paste!$T$3:$T$1045, 1, FALSE)), "", VLOOKUP(B26, Paste!$T$3:$U$1045, 2, FALSE)) -> Y
A27: =F27 -> ANA | B27: Jeff Malott | C27: =VLOOKUP($B27, Paste!$A$3:$H$933, 6, FALSE) -> LW | D27: C | F27: =VLOOKUP($B27, Paste!$A$3:$H$933, 8, FALSE) -> ANA | G27: =VLOOKUP($B27, Paste!$A$3:$H$933, 2, FALSE) -> 37 | H27: =VLOOKUP($B27, Paste!$A$3:$H$933, 3, FALSE) -> 2.3099847 | I27: =J27-H27 -> 1.6878005 | J27: =VLOOKUP($B27, Paste!$A$3:$H$933, 4, FALSE) -> 3.9977852 | K27: =VLOOKUP($B27, Paste!$AB$3:$AE$1033, 4, FALSE) -> 33 | L27: =IF(ISERROR(VLOOKUP(B27, Paste!$N$3:$N$250, 1, FALSE)), "", VLOOKUP(B27, Paste!$N$3:$O$250, 2, FALSE)) | M27: =VLOOKUP($B27, Paste!$W$3:$Z$10064, IF($H$4="Cap Hit",3, IF($H$4="AAV", 4, 2)), FALSE) -> 1.85 | N27: =IF(ISERROR(VLOOKUP(B27, Paste!$Q$3:$Q$245, 1, FALSE)), "", VLOOKUP(B27, Paste!$Q$3:$R$245, 2, FALSE)) | O27: =IF(VLOOKUP(B27, 'Points&Potential'!$B$7:$O$1835, 14, FALSE)=0, "", VLOOKUP(B27, 'Points&Potential'!$B$7:$O$1835, 14, FALSE)) | P27: =IF(ISERROR(VLOOKUP(B27, Paste!$T$3:$T$1045, 1, FALSE)), "", VLOOKUP(B27, Paste!$T$3:$U$1045, 2, FALSE))
A28: =F28 -> ANA | B28: Sam Colangelo | C28: =VLOOKUP($B28, Paste!$A$3:$H$933, 6, FALSE) -> RW | D28: C | F28: =VLOOKUP($B28, Paste!$A$3:$H$933, 8, FALSE) -> ANA | G28: =VLOOKUP($B28, Paste!$A$3:$H$933, 2, FALSE) -> 16.666667 | H28: =VLOOKUP($B28, Paste!$A$3:$H$933, 3, FALSE) -> 2 | I28: =J28-H28 -> 1.536169 | J28: =VLOOKUP($B28, Paste!$A$3:$H$933, 4, FALSE) -> 3.536169 | K28: =VLOOKUP($B28, Paste!$AB$3:$AE$1033, 4, FALSE) -> 17 | L28: =IF(ISERROR(VLOOKUP(B28, Paste!$N$3:$N$250, 1, FALSE)), "", VLOOKUP(B28, Paste!$N$3:$O$250, 2, FALSE)) | M28: =VLOOKUP($B28, Paste!$W$3:$Z$10064, IF($H$4="Cap Hit",3, IF($H$4="AAV", 4, 2)), FALSE) -> 0.85 | N28: =IF(ISERROR(VLOOKUP(B28, Paste!$Q$3:$Q$245, 1, FALSE)), "", VLOOKUP(B28, Paste!$Q$3:$R$245, 2, FALSE)) | O28: =IF(VLOOKUP(B28, 'Points&Potential'!$B$7:$O$1835, 14, FALSE)=0, "", VLOOKUP(B28, 'Points&Potential'!$B$7:$O$1835, 14, FALSE)) | P28: =IF(ISERROR(VLOOKUP(B28, Paste!$T$3:$T$1045, 1, FALSE)), "", VLOOKUP(B28, Paste!$T$3:$U$1045, 2, FALSE))
A29: =F29 -> ANA | B29: Roger McQueen | C29: =VLOOKUP($B29, Paste!$A$3:$H$933, 6, FALSE) -> C | D29: C | F29: =VLOOKUP($B29, Paste!$A$3:$H$933, 8, FALSE) -> ANA | G29: =VLOOKUP($B29, Paste!$A$3:$H$933, 2, FALSE) -> 14 | H29: =VLOOKUP($B29, Paste!$A$3:$H$933, 3, FALSE) -> 0.98 | I29: =J29-H29 -> 1.2866768 | J29: =VLOOKUP($B29, Paste!$A$3:$H$933, 4, FALSE) -> 2.2666768 | K29: =VLOOKUP($B29, Paste!$AB$3:$AE$1033, 4, FALSE) -> 18 | L29: =IF(ISERROR(VLOOKUP(B29, Paste!$N$3:$N$250, 1, FALSE)), "", VLOOKUP(B29, Paste!$N$3:$O$250, 2, FALSE)) -> 45 | M29: =VLOOKUP($B29, Paste!$W$3:$Z$10064, IF($H$4="Cap Hit",3, IF($H$4="AAV", 4, 2)), FALSE) -> 1.075 | N29: =IF(ISERROR(VLOOKUP(B29, Paste!$Q$3:$Q$245, 1, FALSE)), "", VLOOKUP(B29, Paste!$Q$3:$R$245, 2, FALSE)) | O29: =IF(VLOOKUP(B29, 'Points&Potential'!$B$7:$O$1835, 14, FALSE)=0, "", VLOOKUP(B29, 'Points&Potential'!$B$7:$O$1835, 14, FALSE)) | P29: =IF(ISERROR(VLOOKUP(B29, Paste!$T$3:$T$1045, 1, FALSE)), "", VLOOKUP(B29, Paste!$T$3:$U$1045, 2, FALSE)) -> Y
